Workbook
Name BeginningInventory: 'Aggregate Planning'!$C$6
Name LaborStandard: 'Aggregate Planning'!$C$8

Sheet Assumptions
B2: Team: SONY
B4: Yong-Qi Gao
B5: Berta Leach
B6: Ivan Ushakov
B7: Huiyun Zhu
B10: Menu | F10: Summary
C12: Relevant tabs
B13: Data | C13: Sony Black (Cleaned)
C14: Sony Silver (Cleaned)
C15: Sony Black (Aggregated)
C16: Sony Silver (Aggregated)
C17: Sony Data (Aggregated)
B18: Forecasting | C18: Forecast Validation
C19: Parameters Optimisation
B20: Supply and inventory management | C20: Aggregate Planning
C21: Initial MPS and RCCP
C22: Authorised MPS
C23: MRP
C24: EOQ
C25: EPQ
C26: Discount model
C27: Inventory management Models
B32: Helper tabs | C32: (ACF Helper)
C33: (EOQ v EPQ helper)

Sheet Black (Cleaned)
A1: Assumptions
C2: Cleaned Sales data for SONY WH1000-MX5 Black | S2: Helpers
S3: First correction | V3: Second correction
F4: Date Time | G4: Date Time | H4: Item Qty | I4: lower boundary of IC | J4: upper boundary IC | K4: Cleaning (IC =95%) | L4: Sales data after first correction | M4: lower boundary IC | N4: upper boundary IC | O4: Cleaning (IC =95%) | P4: Sales data after 2nd correc. | Q4: Cleaned data | S4: mean | T4: sigma | V4: mean | W4: sigma
F5: 45561.423 | G5: 45561.423 | H5: 3328 | I5: =$S$5-$T$5*1.96 -> -1017182.2 | J5: =$S$5+$T$5*1.96 -> 1049634.1 | K5: =IF(AND(H5>=I5,H5<=J5),"Good","For Replacement") -> Good | L5: =IF(K5="Good",H5,(H6+H4)/2) -> 3328 | M5: =$V$5-$W$5*1.96 -> -13975.836 | N5: =$V$5+$W$5*1.96 -> 20870.015 | O5: =IF(AND(L5>=M5,L5<=N5),"Good","For Replacement") -> Good | P5: =IF(O5="Good",L5,(L6+L4)/2) -> 3328 | Q5: =P5 -> 3328 | S5: =AVERAGE(H5:H1706) -> 16225.977 | T5: =STDEV(H5:H1706) -> 527249.05 | V5: =AVERAGE(L5:L1706) -> 3447.0893 | W5: =STDEV(L5:L1706) -> 8889.2477
F6: 45560.885 | G6: 45560.885 | H6: 3521 | I6: =$S$5-$T$5*1.96 -> -1017182.2 | J6: =$S$5+$T$5*1.96 -> 1049634.1 | K6: =IF(AND(H6>=I6,H6<=J6),"Good","For Replacement") -> Good | L6: =IF(K6="Good",H6,(H7+H5)/2) -> 3521 | M6: =$V$5-$W$5*1.96 -> -13975.836 | N6: =$V$5+$W$5*1.96 -> 20870.015 | O6: =IF(AND(L6>=M6,L6<=N6),"Good","For Replacement") -> Good | P6: =IF(O6="Good",L6,(L7+L5)/2) -> 3521 | Q6: =P6 -> 3521
F7: 45560.326 | G7: 45560.326 | H7: 3680 | I7: =$S$5-$T$5*1.96 -> -1017182.2 | J7: =$S$5+$T$5*1.96 -> 1049634.1 | K7: =IF(AND(H7>=I7,H7<=J7),"Good","For Replacement") -> Good | L7: =IF(K7="Good",H7,(H8+H6)/2) -> 3680 | M7: =$V$5-$W$5*1.96 -> -13975.836 | N7: =$V$5+$W$5*1.96 -> 20870.015 | O7: =IF(AND(L7>=M7,L7<=N7),"Good","For Replacement") -> Good | P7: =IF(O7="Good",L7,(L8+L6)/2) -> 3680 | Q7: =P7 -> 3680
F8: 45559.729 | G8: 45559.729 | H8: 3546 | I8: =$S$5-$T$5*1.96 -> -1017182.2 | J8: =$S$5+$T$5*1.96 -> 1049634.1 | K8: =IF(AND(H8>=I8,H8<=J8),"Good","For Replacement") -> Good | L8: =IF(K8="Good",H8,(H9+H7)/2) -> 3546 | M8: =$V$5-$W$5*1.96 -> -13975.836 | N8: =$V$5+$W$5*1.96 -> 20870.015 | O8: =IF(AND(L8>=M8,L8<=N8),"Good","For Replacement") -> Good | P8: =IF(O8="Good",L8,(L9+L7)/2) -> 3546 | Q8: =P8 -> 3546
F9: 45559.116 | G9: 45559.116 | H9: 4032 | I9: =$S$5-$T$5*1.96 -> -1017182.2 | J9: =$S$5+$T$5*1.96 -> 1049634.1 | K9: =IF(AND(H9>=I9,H9<=J9),"Good","For Replacement") -> Good | L9: =IF(K9="Good",H9,(H10+H8)/2) -> 4032 | M9: =$V$5-$W$5*1.96 -> -13975.836 | N9: =$V$5+$W$5*1.96 -> 20870.015 | O9: =IF(AND(L9>=M9,L9<=N9),"Good","For Replacement") -> Good | P9: =IF(O9="Good",L9,(L10+L8)/2) -> 4032 | Q9: =P9 -> 4032
F10: 45558.51 | G10: 45558.51 | H10: 3511 | I10: =$S$5-$T$5*1.96 -> -1017182.2 | J10: =$S$5+$T$5*1.96 -> 1049634.1 | K10: =IF(AND(H10>=I10,H10<=J10),"Good","For Replacement") -> Good | L10: =IF(K10="Good",H10,(H11+H9)/2) -> 3511 | M10: =$V$5-$W$5*1.96 -> -13975.836 | N10: =$V$5+$W$5*1.96 -> 20870.015 | O10: =IF(AND(L10>=M10,L10<=N10),"Good","For Replacement") -> Good | P10: =IF(O10="Good",L10,(L11+L9)/2) -> 3511 | Q10: =P10 -> 3511
F11: 45555.591 | G11: 45555.591 | H11: 3740 | I11: =$S$5-$T$5*1.96 -> -1017182.2 | J11: =$S$5+$T$5*1.96 -> 1049634.1 | K11: =IF(AND(H11>=I11,H11<=J11),"Good","For Replacement") -> Good | L11: =IF(K11="Good",H11,(H12+H10)/2) -> 3740 | M11: =$V$5-$W$5*1.96 -> -13975.836 | N11: =$V$5+$W$5*1.96 -> 20870.015 | O11: =IF(AND(L11>=M11,L11<=N11),"Good","For Replacement") -> Good | P11: =IF(O11="Good",L11,(L12+L10)/2) -> 3740 | Q11: =P11 -> 3740
F12: 45555.058 | G12: 45555.058 | H12: 3367 | I12: =$S$5-$T$5*1.96 -> -1017182.2 | J12: =$S$5+$T$5*1.96 -> 1049634.1 | K12: =IF(AND(H12>=I12,H12<=J12),"Good","For Replacement") -> Good | L12: =IF(K12="Good",H12,(H13+H11)/2) -> 3367 | M12: =$V$5-$W$5*1.96 -> -13975.836 | N12: =$V$5+$W$5*1.96 -> 20870.015 | O12: =IF(AND(L12>=M12,L12<=N12),"Good","For Replacement") -> Good | P12: =IF(O12="Good",L12,(L13+L11)/2) -> 3367 | Q12: =P12 -> 3367
F13: 45554.475 | G13: 45554.475 | H13: 3264 | I13: =$S$5-$T$5*1.96 -> -1017182.2 | J13: =$S$5+$T$5*1.96 -> 1049634.1 | K13: =IF(AND(H13>=I13,H13<=J13),"Good","For Replacement") -> Good | L13: =IF(K13="Good",H13,(H14+H12)/2) -> 3264 | M13: =$V$5-$W$5*1.96 -> -13975.836 | N13: =$V$5+$W$5*1.96 -> 20870.015 | O13: =IF(AND(L13>=M13,L13<=N13),"Good","For Replacement") -> Good | P13: =IF(O13="Good",L13,(L14+L12)/2) -> 3264 | Q13: =P13 -> 3264
F14: 45553.867 | G14: 45553.867 | H14: 3735 | I14: =$S$5-$T$5*1.96 -> -1017182.2 | J14: =$S$5+$T$5*1.96 -> 1049634.1 | K14: =IF(AND(H14>=I14,H14<=J14),"Good","For Replacement") -> Good | L14: =IF(K14="Good",H14,(H15+H13)/2) -> 3735 | M14: =$V$5-$W$5*1.96 -> -13975.836 | N14: =$V$5+$W$5*1.96 -> 20870.015 | O14: =IF(AND(L14>=M14,L14<=N14),"Good","For Replacement") -> Good | P14: =IF(O14="Good",L14,(L15+L13)/2) -> 3735 | Q14: =P14 -> 3735
F15: 45553.26 | G15: 45553.26 | H15: 3338 | I15: =$S$5-$T$5*1.96 -> -1017182.2 | J15: =$S$5+$T$5*1.96 -> 1049634.1 | K15: =IF(AND(H15>=I15,H15<=J15),"Good","For Replacement") -> Good | L15: =IF(K15="Good",H15,(H16+H14)/2) -> 3338 | M15: =$V$5-$W$5*1.96 -> -13975.836 | N15: =$V$5+$W$5*1.96 -> 20870.015 | O15: =IF(AND(L15>=M15,L15<=N15),"Good","For Replacement") -> Good | P15: =IF(O15="Good",L15,(L16+L14)/2) -> 3338 | Q15: =P15 -> 3338
F16: 45552.721 | G16: 45552.721 | H16: 3890 | I16: =$S$5-$T$5*1.96 -> -1017182.2 | J16: =$S$5+$T$5*1.96 -> 1049634.1 | K16: =IF(AND(H16>=I16,H16<=J16),"Good","For Replacement") -> Good | L16: =IF(K16="Good",H16,(H17+H15)/2) -> 3890 | M16: =$V$5-$W$5*1.96 -> -13975.836 | N16: =$V$5+$W$5*1.96 -> 20870.015 | O16: =IF(AND(L16>=M16,L16<=N16),"Good","For Replacement") -> Good | P16: =IF(O16="Good",L16,(L17+L15)/2) -> 3890 | Q16: =P16 -> 3890
F17: 45552.181 | G17: 45552.181 | H17: 3352 | I17: =$S$5-$T$5*1.96 -> -1017182.2 | J17: =$S$5+$T$5*1.96 -> 1049634.1 | K17: =IF(AND(H17>=I17,H17<=J17),"Good","For Replacement") -> Good | L17: =IF(K17="Good",H17,(H18+H16)/2) -> 3352 | M17: =$V$5-$W$5*1.96 -> -13975.836 | N17: =$V$5+$W$5*1.96 -> 20870.015 | O17: =IF(AND(L17>=M17,L17<=N17),"Good","For Replacement") -> Good | P17: =IF(O17="Good",L17,(L18+L16)/2) -> 3352 | Q17: =P17 -> 3352
... F1706: 44197.261 | G1706: 44197.261 | H1706: 2128 | I1706: =$S$5-$T$5*1.96 -> -1017182.2 | J1706: =$S$5+$T$5*1.96 -> 1049634.1 | K1706: =IF(AND(H1706>=I1706,H1706<=J1706),"Good","For Replacement") -> Good | L1706: =IF(K1706="Good",H1706,(H1707+H1705)/2) -> 2128 | M1706: =$V$5-$W$5*1.96 -> -13975.836 | N1706: =$V$5+$W$5*1.96 -> 20870.015 | O1706: =IF(AND(L1706>=M1706,L1706<=N1706),"Good","For Replacement") -> Good | P1706: =IF(O1706="Good",L1706,(L1707+L1705)/2) -> 2128 | Q1706: =P1706 -> 2128

Sheet Silver (Cleaned)
A1: Assumptions
C2: Cleaned Sales Data for SONY WH1000-MX5 Silver | T2: Helpers
T3: First correction | W3: Second correction
F4: Date Time | G4: Date Time | H4: Item Qty | I4: lower boundary | J4: upper boundary | K4: Cleaning (IC =95%) | L4: Sales data after first correction | M4: lower boundary IC | N4: upper boundary IC | O4: Cleaning (IC =95%) | P4: Sales data after second correction | Q4: Cleaned data | T4: mean | U4: sigma | W4: mean | X4: sigma
F5: 45561.423 | G5: 45561.41 | H5: 1820 | I5: =$T$5-$U$5*1.96 -> -764.65463 | J5: =$T$5+$U$5*1.96 -> 4310.3027 | K5: =IF(AND(H5>=I5,H5<=J5),"Good","For Replacement") -> Good | L5: =IF(K5="Good",H5,(H6+H4)/2) -> 1820 | M5: =$W$5-$X$5*1.96 -> 674.62058 | N5: =$W$5+$X$5*1.96 -> 2778.6017 | O5: =IF(AND(L5>=M5,L5<=N5),"Good","For Replacement") -> Good | P5: =IF(O5="Good",L5,(L6+L4)/2) -> 1820 | Q5: =P5 -> 1820 | T5: =AVERAGE(H5:H1709) -> 1772.824 | U5: =STDEV(H5:H1709) -> 1294.632 | W5: =AVERAGE(L5:L1709) -> 1726.6111 | X5: =STDEV(L5:L1709) -> 536.72988
F6: 45560.885 | G6: 45560.809 | H6: 1820 | I6: =$T$5-$U$5*1.96 -> -764.65463 | J6: =$T$5+$U$5*1.96 -> 4310.3027 | K6: =IF(AND(H6>=I6,H6<=J6),"Good","For Replacement") -> Good | L6: =IF(K6="Good",H6,(H7+H5)/2) -> 1820 | M6: =$W$5-$X$5*1.96 -> 674.62058 | N6: =$W$5+$X$5*1.96 -> 2778.6017 | O6: =IF(AND(L6>=M6,L6<=N6),"Good","For Replacement") -> Good | P6: =IF(O6="Good",L6,(L7+L5)/2) -> 1820 | Q6: =P6 -> 1820
F7: 45560.326 | G7: 45560.21 | H7: 1804 | I7: =$T$5-$U$5*1.96 -> -764.65463 | J7: =$T$5+$U$5*1.96 -> 4310.3027 | K7: =IF(AND(H7>=I7,H7<=J7),"Good","For Replacement") -> Good | L7: =IF(K7="Good",H7,(H8+H6)/2) -> 1804 | M7: =$W$5-$X$5*1.96 -> 674.62058 | N7: =$W$5+$X$5*1.96 -> 2778.6017 | O7: =IF(AND(L7>=M7,L7<=N7),"Good","For Replacement") -> Good | P7: =IF(O7="Good",L7,(L8+L6)/2) -> 1804 | Q7: =P7 -> 1804
F8: 45559.729 | G8: 45559.607 | H8: 1946 | I8: =$T$5-$U$5*1.96 -> -764.65463 | J8: =$T$5+$U$5*1.96 -> 4310.3027 | K8: =IF(AND(H8>=I8,H8<=J8),"Good","For Replacement") -> Good | L8: =IF(K8="Good",H8,(H9+H7)/2) -> 1946 | M8: =$W$5-$X$5*1.96 -> 674.62058 | N8: =$W$5+$X$5*1.96 -> 2778.6017 | O8: =IF(AND(L8>=M8,L8<=N8),"Good","For Replacement") -> Good | P8: =IF(O8="Good",L8,(L9+L7)/2) -> 1946 | Q8: =P8 -> 1946
F9: 45559.116 | G9: 45559.02 | H9: 1842 | I9: =$T$5-$U$5*1.96 -> -764.65463 | J9: =$T$5+$U$5*1.96 -> 4310.3027 | K9: =IF(AND(H9>=I9,H9<=J9),"Good","For Replacement") -> Good | L9: =IF(K9="Good",H9,(H10+H8)/2) -> 1842 | M9: =$W$5-$X$5*1.96 -> 674.62058 | N9: =$W$5+$X$5*1.96 -> 2778.6017 | O9: =IF(AND(L9>=M9,L9<=N9),"Good","For Replacement") -> Good | P9: =IF(O9="Good",L9,(L10+L8)/2) -> 1842 | Q9: =P9 -> 1842
F10: 45558.51 | G10: 45558.458 | H10: 1678 | I10: =$T$5-$U$5*1.96 -> -764.65463 | J10: =$T$5+$U$5*1.96 -> 4310.3027 | K10: =IF(AND(H10>=I10,H10<=J10),"Good","For Replacement") -> Good | L10: =IF(K10="Good",H10,(H11+H9)/2) -> 1678 | M10: =$W$5-$X$5*1.96 -> 674.62058 | N10: =$W$5+$X$5*1.96 -> 2778.6017 | O10: =IF(AND(L10>=M10,L10<=N10),"Good","For Replacement") -> Good | P10: =IF(O10="Good",L10,(L11+L9)/2) -> 1678 | Q10: =P10 -> 1678
F11: 45555.591 | G11: 45555.709 | H11: 1919 | I11: =$T$5-$U$5*1.96 -> -764.65463 | J11: =$T$5+$U$5*1.96 -> 4310.3027 | K11: =IF(AND(H11>=I11,H11<=J11),"Good","For Replacement") -> Good | L11: =IF(K11="Good",H11,(H12+H10)/2) -> 1919 | M11: =$W$5-$X$5*1.96 -> 674.62058 | N11: =$W$5+$X$5*1.96 -> 2778.6017 | O11: =IF(AND(L11>=M11,L11<=N11),"Good","For Replacement") -> Good | P11: =IF(O11="Good",L11,(L12+L10)/2) -> 1919 | Q11: =P11 -> 1919
F12: 45555.058 | G12: 45555.166 | H12: 1912 | I12: =$T$5-$U$5*1.96 -> -764.65463 | J12: =$T$5+$U$5*1.96 -> 4310.3027 | K12: =IF(AND(H12>=I12,H12<=J12),"Good","For Replacement") -> Good | L12: =IF(K12="Good",H12,(H13+H11)/2) -> 1912 | M12: =$W$5-$X$5*1.96 -> 674.62058 | N12: =$W$5+$X$5*1.96 -> 2778.6017 | O12: =IF(AND(L12>=M12,L12<=N12),"Good","For Replacement") -> Good | P12: =IF(O12="Good",L12,(L13+L11)/2) -> 1912 | Q12: =P12 -> 1912
F13: 45554.475 | G13: 45554.63 | H13: 1868 | I13: =$T$5-$U$5*1.96 -> -764.65463 | J13: =$T$5+$U$5*1.96 -> 4310.3027 | K13: =IF(AND(H13>=I13,H13<=J13),"Good","For Replacement") -> Good | L13: =IF(K13="Good",H13,(H14+H12)/2) -> 1868 | M13: =$W$5-$X$5*1.96 -> 674.62058 | N13: =$W$5+$X$5*1.96 -> 2778.6017 | O13: =IF(AND(L13>=M13,L13<=N13),"Good","For Replacement") -> Good | P13: =IF(O13="Good",L13,(L14+L12)/2) -> 1868 | Q13: =P13 -> 1868
F14: 45553.867 | G14: 45554.101 | H14: 1685 | I14: =$T$5-$U$5*1.96 -> -764.65463 | J14: =$T$5+$U$5*1.96 -> 4310.3027 | K14: =IF(AND(H14>=I14,H14<=J14),"Good","For Replacement") -> Good | L14: =IF(K14="Good",H14,(H15+H13)/2) -> 1685 | M14: =$W$5-$X$5*1.96 -> 674.62058 | N14: =$W$5+$X$5*1.96 -> 2778.6017 | O14: =IF(AND(L14>=M14,L14<=N14),"Good","For Replacement") -> Good | P14: =IF(O14="Good",L14,(L15+L13)/2) -> 1685 | Q14: =P14 -> 1685
F15: 45553.26 | G15: 45553.553 | H15: 1766 | I15: =$T$5-$U$5*1.96 -> -764.65463 | J15: =$T$5+$U$5*1.96 -> 4310.3027 | K15: =IF(AND(H15>=I15,H15<=J15),"Good","For Replacement") -> Good | L15: =IF(K15="Good",H15,(H16+H14)/2) -> 1766 | M15: =$W$5-$X$5*1.96 -> 674.62058 | N15: =$W$5+$X$5*1.96 -> 2778.6017 | O15: =IF(AND(L15>=M15,L15<=N15),"Good","For Replacement") -> Good | P15: =IF(O15="Good",L15,(L16+L14)/2) -> 1766 | Q15: =P15 -> 1766
F16: 45552.721 | G16: 45552.964 | H16: 1713 | I16: =$T$5-$U$5*1.96 -> -764.65463 | J16: =$T$5+$U$5*1.96 -> 4310.3027 | K16: =IF(AND(H16>=I16,H16<=J16),"Good","For Replacement") -> Good | L16: =IF(K16="Good",H16,(H17+H15)/2) -> 1713 | M16: =$W$5-$X$5*1.96 -> 674.62058 | N16: =$W$5+$X$5*1.96 -> 2778.6017 | O16: =IF(AND(L16>=M16,L16<=N16),"Good","For Replacement") -> Good | P16: =IF(O16="Good",L16,(L17+L15)/2) -> 1713 | Q16: =P16 -> 1713
F17: 45552.181 | G17: 45552.368 | H17: 1861 | I17: =$T$5-$U$5*1.96 -> -764.65463 | J17: =$T$5+$U$5*1.96 -> 4310.3027 | K17: =IF(AND(H17>=I17,H17<=J17),"Good","For Replacement") -> Good | L17: =IF(K17="Good",H17,(H18+H16)/2) -> 1861 | M17: =$W$5-$X$5*1.96 -> 674.62058 | N17: =$W$5+$X$5*1.96 -> 2778.6017 | O17: =IF(AND(L17>=M17,L17<=N17),"Good","For Replacement") -> Good | P17: =IF(O17="Good",L17,(L18+L16)/2) -> 1861 | Q17: =P17 -> 1861
... F1706: 44197.261 | G1706: 44201.368 | H1706: 2016 | I1706: =$T$5-$U$5*1.96 -> -764.65463 | J1706: =$T$5+$U$5*1.96 -> 4310.3027 | K1706: =IF(AND(H1706>=I1706,H1706<=J1706),"Good","For Replacement") -> Good | L1706: =IF(K1706="Good",H1706,(H1707+H1705)/2) -> 2016 | M1706: =$W$5-$X$5*1.96 -> 674.62058 | N1706: =$W$5+$X$5*1.96 -> 2778.6017 | O1706: =IF(AND(L1706>=M1706,L1706<=N1706),"Good","For Replacement") -> Good | P1706: =IF(O1706="Good",L1706,(L1707+L1705)/2) -> 2016 | Q1706: =P1706 -> 2016
G1707: 44200.826 | H1707: 1761 | I1707: =$T$5-$U$5*1.96 -> -764.65463 | J1707: =$T$5+$U$5*1.96 -> 4310.3027 | K1707: =IF(AND(H1707>=I1707,H1707<=J1707),"Good","For Replacement") -> Good | L1707: =IF(K1707="Good",H1707,(H1708+H1706)/2) -> 1761 | M1707: =$W$5-$X$5*1.96 -> 674.62058 | N1707: =$W$5+$X$5*1.96 -> 2778.6017 | O1707: =IF(AND(L1707>=M1707,L1707<=N1707),"Good","For Replacement") -> Good | P1707: =IF(O1707="Good",L1707,(L1708+L1706)/2) -> 1761 | Q1707: =P1707 -> 1761
G1708: 44200.286 | H1708: 1966 | I1708: =$T$5-$U$5*1.96 -> -764.65463 | J1708: =$T$5+$U$5*1.96 -> 4310.3027 | K1708: =IF(AND(H1708>=I1708,H1708<=J1708),"Good","For Replacement") -> Good | L1708: =IF(K1708="Good",H1708,(H1709+H1707)/2) -> 1966 | M1708: =$W$5-$X$5*1.96 -> 674.62058 | N1708: =$W$5+$X$5*1.96 -> 2778.6017 | O1708: =IF(AND(L1708>=M1708,L1708<=N1708),"Good","For Replacement") -> Good | P1708: =IF(O1708="Good",L1708,(L1709+L1707)/2) -> 1966 | Q1708: =P1708 -> 1966
G1709: 44197.475 | H1709: 1521 | I1709: =$T$5-$U$5*1.96 -> -764.65463 | J1709: =$T$5+$U$5*1.96 -> 4310.3027 | K1709: =IF(AND(H1709>=I1709,H1709<=J1709),"Good","For Replacement") -> Good | L1709: =IF(K1709="Good",H1709,(H1710+H1708)/2) -> 1521 | M1709: =$W$5-$X$5*1.96 -> 674.62058 | N1709: =$W$5+$X$5*1.96 -> 2778.6017 | O1709: =IF(AND(L1709>=M1709,L1709<=N1709),"Good","For Replacement") -> Good | P1709: =IF(O1709="Good",L1709,(L1710+L1708)/2) -> 1521 | Q1709: =P1709 -> 1521

Sheet Black (Aggregated)
A1: Assumptions
C2: Aggregation of Sales Data for Only WH1000-MX5 Black
G4: Cleaned data SONY WH1000-MX5 Black | M4: Aggregated last 36M SONY WH1000-MX5 Black
G5: Date Time | H5: Clean Data | I5: Month | J5: helper column | L5: Month cnt (helper) | M5: Month | N5: Sum of Sales | P5: Summary
G6: ='Black (Cleaned)'!G5 -> 45561.423 | H6: ='Black (Cleaned)'!Q5 -> 3328 | I6: =TEXT(G6, "YYYY-MM") -> 2024-09 | J6: =TEXT(M6, "YYYY-MM") -> 2024-09 | L6: 1 | M6: 45536 | N6: =IF(L6<37,SUMIF(I:I, J6, H:H),"Out of Scope") -> 112872 | P6: Sum of Clean Data | Q6: Column Labels
G7: ='Black (Cleaned)'!G6 -> 45560.885 | H7: ='Black (Cleaned)'!Q6 -> 3521 | I7: =TEXT(G7, "YYYY-MM") -> 2024-09 | J7: =TEXT(M7, "YYYY-MM") -> 2024-08 | L7: =L6+1 -> 2 | M7: 45505 | N7: =IF(L7<37,SUMIF(I:I, J7, H:H),"Out of Scope") -> 90886 | P7: Row Labels | Q7: Jan | R7: Feb | S7: Mar | T7: Apr | U7: May | V7: Jun | W7: Jul | X7: Aug | Y7: Sep | Z7: Oct | AA7: Nov | AB7: Dec | AC7: Grand Total
G8: ='Black (Cleaned)'!G7 -> 45560.326 | H8: ='Black (Cleaned)'!Q7 -> 3680 | I8: =TEXT(G8, "YYYY-MM") -> 2024-09 | J8: =TEXT(M8, "YYYY-MM") -> 2024-07 | L8: =L7+1 -> 3 | M8: 45474 | N8: =IF(L8<37,SUMIF(I:I, J8, H:H),"Out of Scope") -> 88716 | P8: 2021 | Q8: 131274 | R8: 115805 | S8: 108273 | T8: 88454 | U8: 95250 | V8: 86653 | W8: 71870 | X8: 71480.5 | Y8: 104097 | Z8: 105878 | AA8: 146396 | AB8: 206971 | AC8: 1332401.5
G9: ='Black (Cleaned)'!G8 -> 45559.729 | H9: ='Black (Cleaned)'!Q8 -> 3546 | I9: =TEXT(G9, "YYYY-MM") -> 2024-09 | J9: =TEXT(M9, "YYYY-MM") -> 2024-06 | L9: =L8+1 -> 4 | M9: 45444 | N9: =IF(L9<37,SUMIF(I:I, J9, H:H),"Out of Scope") -> 100669 | P9: 2022 | Q9: 171166 | R9: 112402 | S9: 122690 | T9: 88678 | U9: 96735 | V9: 98843 | W9: 74539 | X9: 84181 | Y9: 112346 | Z9: 116187 | AA9: 163412 | AB9: 199766 | AC9: 1440945
G10: ='Black (Cleaned)'!G9 -> 45559.116 | H10: ='Black (Cleaned)'!Q9 -> 4032 | I10: =TEXT(G10, "YYYY-MM") -> 2024-09 | J10: =TEXT(M10, "YYYY-MM") -> 2024-05 | L10: =L9+1 -> 5 | M10: 45413 | N10: =IF(L10<37,SUMIF(I:I, J10, H:H),"Out of Scope") -> 116472 | P10: 2023 | Q10: 188781 | R10: 128220 | S10: 122870 | T10: 89010 | U10: 113131 | V10: 102145 | W10: 73332 | X10: 86770 | Y10: 111564 | Z10: 128256 | AA10: 163313 | AB10: 206038 | AC10: 1513430
G11: ='Black (Cleaned)'!G10 -> 45558.51 | H11: ='Black (Cleaned)'!Q10 -> 3511 | I11: =TEXT(G11, "YYYY-MM") -> 2024-09 | J11: =TEXT(M11, "YYYY-MM") -> 2024-04 | L11: =L10+1 -> 6 | M11: 45383 | N11: =IF(L11<37,SUMIF(I:I, J11, H:H),"Out of Scope") -> 105989 | P11: 2024 | Q11: 205208 | R11: 134180 | S11: 123627 | T11: 105989 | U11: 116472 | V11: 100669 | W11: 88716 | X11: 90886 | Y11: 112872 | AC11: 1078619
G12: ='Black (Cleaned)'!G11 -> 45555.591 | H12: ='Black (Cleaned)'!Q11 -> 3740 | I12: =TEXT(G12, "YYYY-MM") -> 2024-09 | J12: =TEXT(M12, "YYYY-MM") -> 2024-03 | L12: =L11+1 -> 7 | M12: 45352 | N12: =IF(L12<37,SUMIF(I:I, J12, H:H),"Out of Scope") -> 123627 | P12: Grand Total | Q12: 696429 | R12: 490607 | S12: 477460 | T12: 372131 | U12: 421588 | V12: 388310 | W12: 308457 | X12: 333317.5 | Y12: 440879 | Z12: 350321 | AA12: 473121 | AB12: 612775 | AC12: 5365395.5
G13: ='Black (Cleaned)'!G12 -> 45555.058 | H13: ='Black (Cleaned)'!Q12 -> 3367 | I13: =TEXT(G13, "YYYY-MM") -> 2024-09 | J13: =TEXT(M13, "YYYY-MM") -> 2024-02 | L13: =L12+1 -> 8 | M13: 45323 | N13: =IF(L13<37,SUMIF(I:I, J13, H:H),"Out of Scope") -> 134180
G14: ='Black (Cleaned)'!G13 -> 45554.475 | H14: ='Black (Cleaned)'!Q13 -> 3264 | I14: =TEXT(G14, "YYYY-MM") -> 2024-09 | J14: =TEXT(M14, "YYYY-MM") -> 2024-01 | L14: =L13+1 -> 9 | M14: 45292 | N14: =IF(L14<37,SUMIF(I:I, J14, H:H),"Out of Scope") -> 205208
G15: ='Black (Cleaned)'!G14 -> 45553.867 | H15: ='Black (Cleaned)'!Q14 -> 3735 | I15: =TEXT(G15, "YYYY-MM") -> 2024-09 | J15: =TEXT(M15, "YYYY-MM") -> 2023-12 | L15: =L14+1 -> 10 | M15: 45261 | N15: =IF(L15<37,SUMIF(I:I, J15, H:H),"Out of Scope") -> 206038
G16: ='Black (Cleaned)'!G15 -> 45553.26 | H16: ='Black (Cleaned)'!Q15 -> 3338 | I16: =TEXT(G16, "YYYY-MM") -> 2024-09 | J16: =TEXT(M16, "YYYY-MM") -> 2023-11 | L16: =L15+1 -> 11 | M16: 45231 | N16: =IF(L16<37,SUMIF(I:I, J16, H:H),"Out of Scope") -> 163313
G17: ='Black (Cleaned)'!G16 -> 45552.721 | H17: ='Black (Cleaned)'!Q16 -> 3890 | I17: =TEXT(G17, "YYYY-MM") -> 2024-09 | J17: =TEXT(M17, "YYYY-MM") -> 2023-10 | L17: =L16+1 -> 12 | M17: 45200 | N17: =IF(L17<37,SUMIF(I:I, J17, H:H),"Out of Scope") -> 128256
G18: ='Black (Cleaned)'!G17 -> 45552.181 | H18: ='Black (Cleaned)'!Q17 -> 3352 | I18: =TEXT(G18, "YYYY-MM") -> 2024-09 | J18: =TEXT(M18, "YYYY-MM") -> 2023-09 | L18: =L17+1 -> 13 | M18: 45170 | N18: =IF(L18<37,SUMIF(I:I, J18, H:H),"Out of Scope") -> 111564
G19: ='Black (Cleaned)'!G18 -> 45551.608 | H19: ='Black (Cleaned)'!Q18 -> 3327 | I19: =TEXT(G19, "YYYY-MM") -> 2024-09 | J19: =TEXT(M19, "YYYY-MM") -> 2023-08 | L19: =L18+1 -> 14 | M19: 45139 | N19: =IF(L19<37,SUMIF(I:I, J19, H:H),"Out of Scope") -> 86770
G20: ='Black (Cleaned)'!G19 -> 45551.059 | H20: ='Black (Cleaned)'!Q19 -> 3690 | I20: =TEXT(G20, "YYYY-MM") -> 2024-09 | J20: =TEXT(M20, "YYYY-MM") -> 2023-07 | L20: =L19+1 -> 15 | M20: 45108 | N20: =IF(L20<37,SUMIF(I:I, J20, H:H),"Out of Scope") -> 73332
G21: ='Black (Cleaned)'!G20 -> 45548.78 | H21: ='Black (Cleaned)'!Q20 -> 3655 | I21: =TEXT(G21, "YYYY-MM") -> 2024-09 | J21: =TEXT(M21, "YYYY-MM") -> 2023-06 | L21: =L20+1 -> 16 | M21: 45078 | N21: =IF(L21<37,SUMIF(I:I, J21, H:H),"Out of Scope") -> 102145
G22: ='Black (Cleaned)'!G21 -> 45548.181 | H22: ='Black (Cleaned)'!Q21 -> 3607 | I22: =TEXT(G22, "YYYY-MM") -> 2024-09 | J22: =TEXT(M22, "YYYY-MM") -> 2023-05 | L22: =L21+1 -> 17 | M22: 45047 | N22: =IF(L22<37,SUMIF(I:I, J22, H:H),"Out of Scope") -> 113131
G23: ='Black (Cleaned)'!G22 -> 45547.579 | H23: ='Black (Cleaned)'!Q22 -> 3246 | I23: =TEXT(G23, "YYYY-MM") -> 2024-09 | J23: =TEXT(M23, "YYYY-MM") -> 2023-04 | L23: =L22+1 -> 18 | M23: 45017 | N23: =IF(L23<37,SUMIF(I:I, J23, H:H),"Out of Scope") -> 89010
G24: ='Black (Cleaned)'!G23 -> 45547.015 | H24: ='Black (Cleaned)'!Q23 -> 3599 | I24: =TEXT(G24, "YYYY-MM") -> 2024-09 | J24: =TEXT(M24, "YYYY-MM") -> 2023-03 | L24: =L23+1 -> 19 | M24: 44986 | N24: =IF(L24<37,SUMIF(I:I, J24, H:H),"Out of Scope") -> 122870
... G50: ='Black (Cleaned)'!G49 -> 45525.865 | H50: ='Black (Cleaned)'!Q49 -> 2612 | I50: =TEXT(G50, "YYYY-MM") -> 2024-08 | J50: =TEXT(M50, "YYYY-MM") -> 2021-01 | L50: =L49+1 -> 45 | M50: 44197 | N50: =IF(L50<37,SUMIF(I:I, J50, H:H),"Out of Scope") -> Out of Scope
G51: ='Black (Cleaned)'!G50 -> 45525.309 | H51: ='Black (Cleaned)'!Q50 -> 2320 | I51: =TEXT(G51, "YYYY-MM") -> 2024-08 | J51: =TEXT(M51, "YYYY-MM") -> 1900-01
G52: ='Black (Cleaned)'!G51 -> 45524.735 | H52: ='Black (Cleaned)'!Q51 -> 2486 | I52: =TEXT(G52, "YYYY-MM") -> 2024-08 | J52: =TEXT(M52, "YYYY-MM") -> 1900-01
G53: ='Black (Cleaned)'!G52 -> 45524.146 | H53: ='Black (Cleaned)'!Q52 -> 2625 | I53: =TEXT(G53, "YYYY-MM") -> 2024-08 | J53: =TEXT(M53, "YYYY-MM") -> 1900-01
G54: ='Black (Cleaned)'!G53 -> 45523.581 | H54: ='Black (Cleaned)'!Q53 -> 2111 | I54: =TEXT(G54, "YYYY-MM") -> 2024-08 | J54: =TEXT(M54, "YYYY-MM") -> 1900-01
G55: ='Black (Cleaned)'!G54 -> 45520.696 | H55: ='Black (Cleaned)'!Q54 -> 2103 | I55: =TEXT(G55, "YYYY-MM") -> 2024-08 | J55: =TEXT(M55, "YYYY-MM") -> 1900-01
G56: ='Black (Cleaned)'!G55 -> 45520.13 | H56: ='Black (Cleaned)'!Q55 -> 2363 | I56: =TEXT(G56, "YYYY-MM") -> 2024-08 | J56: =TEXT(M56, "YYYY-MM") -> 1900-01
G57: ='Black (Cleaned)'!G56 -> 45519.587 | H57: ='Black (Cleaned)'!Q56 -> 2349 | I57: =TEXT(G57, "YYYY-MM") -> 2024-08 | J57: =TEXT(M57, "YYYY-MM") -> 1900-01
G58: ='Black (Cleaned)'!G57 -> 45519.017 | H58: ='Black (Cleaned)'!Q57 -> 2378 | I58: =TEXT(G58, "YYYY-MM") -> 2024-08 | J58: =TEXT(M58, "YYYY-MM") -> 1900-01
G59: ='Black (Cleaned)'!G58 -> 45518.41 | H59: ='Black (Cleaned)'!Q58 -> 2139 | I59: =TEXT(G59, "YYYY-MM") -> 2024-08 | J59: =TEXT(M59, "YYYY-MM") -> 1900-01
G60: ='Black (Cleaned)'!G59 -> 45517.869 | H60: ='Black (Cleaned)'!Q59 -> 2451 | I60: =TEXT(G60, "YYYY-MM") -> 2024-08 | J60: =TEXT(M60, "YYYY-MM") -> 1900-01
G61: ='Black (Cleaned)'!G60 -> 45517.265 | H61: ='Black (Cleaned)'!Q60 -> 2293 | I61: =TEXT(G61, "YYYY-MM") -> 2024-08 | J61: =TEXT(M61, "YYYY-MM") -> 1900-01
G62: ='Black (Cleaned)'!G61 -> 45516.705 | H62: ='Black (Cleaned)'!Q61 -> 2280 | I62: =TEXT(G62, "YYYY-MM") -> 2024-08 | J62: =TEXT(M62, "YYYY-MM") -> 1900-01
... G1707: ='Black (Cleaned)'!G1706 -> 44197.261 | H1707: ='Black (Cleaned)'!Q1706 -> 2128 | I1707: =TEXT(G1707, "YYYY-MM") -> 2021-01 | J1707: =TEXT(M1707, "YYYY-MM") -> 1900-01

Sheet Silver (Aggregated)
A1: Assumptions
C2: Aggregation of Sales data for ony WH1000-MX5 Silver
G4: Cleaned data SONY WH1000-MX5 Silver | M4: Aggregated last 36M SONY WH1000-MX5 Silver | P4: Summary
G5: Date Time | H5: Clean Data | I5: Month | J5: helper column | L5: Month cnt (helper) | M5: Month | N5: Sum of Sales | P5: Sum of Clean Data | Q5: Column Labels
G6: ='Silver (Cleaned)'!G5 -> 45561.41 | H6: ='Silver (Cleaned)'!Q5 -> 1820 | I6: =TEXT(G6, "YYYY-MM") -> 2024-09 | J6: =TEXT(M6, "YYYY-MM") -> 2024-09 | L6: ='Black (Aggregated)'!L6 -> 1 | M6: 45536 | N6: =IF(L6<37,SUMIF(I:I, J6, H:H),"Out of Scope") -> 57705 | P6: Row Labels | Q6: Jan | R6: Feb | S6: Mar | T6: Apr | U6: May | V6: Jun | W6: Jul | X6: Aug | Y6: Sep | Z6: Oct | AA6: Nov | AB6: Dec | AC6: Grand Total
G7: ='Silver (Cleaned)'!G6 -> 45560.809 | H7: ='Silver (Cleaned)'!Q6 -> 1820 | I7: =TEXT(G7, "YYYY-MM") -> 2024-09 | J7: =TEXT(M7, "YYYY-MM") -> 2024-08 | L7: ='Black (Aggregated)'!L7 -> 2 | M7: 45505 | N7: =IF(L7<37,SUMIF(I:I, J7, H:H),"Out of Scope") -> 58140 | P7: 2021 | Q7: 83333.5 | R7: 65073 | S7: 53224 | T7: 45934 | U7: 49472 | V7: 52318 | W7: 41171 | X7: 45435 | Y7: 60779 | Z7: 58854 | AA7: 83385.5 | AB7: 102522.5 | AC7: 741501.5
G8: ='Silver (Cleaned)'!G7 -> 45560.21 | H8: ='Silver (Cleaned)'!Q7 -> 1804 | I8: =TEXT(G8, "YYYY-MM") -> 2024-09 | J8: =TEXT(M8, "YYYY-MM") -> 2024-07 | L8: ='Black (Aggregated)'!L8 -> 3 | M8: 45474 | N8: =IF(L8<37,SUMIF(I:I, J8, H:H),"Out of Scope") -> 50461 | P8: 2022 | Q8: 93397.5 | R8: 63266 | S8: 58838 | T8: 49232 | U8: 57246 | V8: 53813 | W8: 42482 | X8: 51840 | Y8: 60565 | Z8: 58754 | AA8: 80660 | AB8: 102245.5 | AC8: 772339
G9: ='Silver (Cleaned)'!G8 -> 45559.607 | H9: ='Silver (Cleaned)'!Q8 -> 1946 | I9: =TEXT(G9, "YYYY-MM") -> 2024-09 | J9: =TEXT(M9, "YYYY-MM") -> 2024-06 | L9: ='Black (Aggregated)'!L9 -> 4 | M9: 45444 | N9: =IF(L9<37,SUMIF(I:I, J9, H:H),"Out of Scope") -> 53435 | P9: 2023 | Q9: 107744.5 | R9: 75007 | S9: 61321 | T9: 48871 | U9: 58469 | V9: 58342 | W9: 43882 | X9: 55306 | Y9: 63171 | Z9: 66299 | AA9: 85614 | AB9: 101606 | AC9: 825632.5
G10: ='Silver (Cleaned)'!G9 -> 45559.02 | H10: ='Silver (Cleaned)'!Q9 -> 1842 | I10: =TEXT(G10, "YYYY-MM") -> 2024-09 | J10: =TEXT(M10, "YYYY-MM") -> 2024-05 | L10: ='Black (Aggregated)'!L10 -> 5 | M10: 45413 | N10: =IF(L10<37,SUMIF(I:I, J10, H:H),"Out of Scope") -> 64106 | P10: 2024 | Q10: 114572.5 | R10: 76839.5 | S10: 58243 | T10: 56954 | U10: 64106 | V10: 53435 | W10: 50461 | X10: 58140 | Y10: 57705 | AC10: 590456
G11: ='Silver (Cleaned)'!G10 -> 45558.458 | H11: ='Silver (Cleaned)'!Q10 -> 1678 | I11: =TEXT(G11, "YYYY-MM") -> 2024-09 | J11: =TEXT(M11, "YYYY-MM") -> 2024-04 | L11: ='Black (Aggregated)'!L11 -> 6 | M11: 45383 | N11: =IF(L11<37,SUMIF(I:I, J11, H:H),"Out of Scope") -> 56954 | P11: Grand Total | Q11: 399048 | R11: 280185.5 | S11: 231626 | T11: 200991 | U11: 229293 | V11: 217908 | W11: 177996 | X11: 210721 | Y11: 242220 | Z11: 183907 | AA11: 249659.5 | AB11: 306374 | AC11: 2929929
G12: ='Silver (Cleaned)'!G11 -> 45555.709 | H12: ='Silver (Cleaned)'!Q11 -> 1919 | I12: =TEXT(G12, "YYYY-MM") -> 2024-09 | J12: =TEXT(M12, "YYYY-MM") -> 2024-03 | L12: ='Black (Aggregated)'!L12 -> 7 | M12: 45352 | N12: =IF(L12<37,SUMIF(I:I, J12, H:H),"Out of Scope") -> 58243
G13: ='Silver (Cleaned)'!G12 -> 45555.166 | H13: ='Silver (Cleaned)'!Q12 -> 1912 | I13: =TEXT(G13, "YYYY-MM") -> 2024-09 | J13: =TEXT(M13, "YYYY-MM") -> 2024-02 | L13: ='Black (Aggregated)'!L13 -> 8 | M13: 45323 | N13: =IF(L13<37,SUMIF(I:I, J13, H:H),"Out of Scope") -> 76839.5
G14: ='Silver (Cleaned)'!G13 -> 45554.63 | H14: ='Silver (Cleaned)'!Q13 -> 1868 | I14: =TEXT(G14, "YYYY-MM") -> 2024-09 | J14: =TEXT(M14, "YYYY-MM") -> 2024-01 | L14: ='Black (Aggregated)'!L14 -> 9 | M14: 45292 | N14: =IF(L14<37,SUMIF(I:I, J14, H:H),"Out of Scope") -> 114572.5
G15: ='Silver (Cleaned)'!G14 -> 45554.101 | H15: ='Silver (Cleaned)'!Q14 -> 1685 | I15: =TEXT(G15, "YYYY-MM") -> 2024-09 | J15: =TEXT(M15, "YYYY-MM") -> 2023-12 | L15: ='Black (Aggregated)'!L15 -> 10 | M15: 45261 | N15: =IF(L15<37,SUMIF(I:I, J15, H:H),"Out of Scope") -> 101606
G16: ='Silver (Cleaned)'!G15 -> 45553.553 | H16: ='Silver (Cleaned)'!Q15 -> 1766 | I16: =TEXT(G16, "YYYY-MM") -> 2024-09 | J16: =TEXT(M16, "YYYY-MM") -> 2023-11 | L16: ='Black (Aggregated)'!L16 -> 11 | M16: 45231 | N16: =IF(L16<37,SUMIF(I:I, J16, H:H),"Out of Scope") -> 85614
G17: ='Silver (Cleaned)'!G16 -> 45552.964 | H17: ='Silver (Cleaned)'!Q16 -> 1713 | I17: =TEXT(G17, "YYYY-MM") -> 2024-09 | J17: =TEXT(M17, "YYYY-MM") -> 2023-10 | L17: ='Black (Aggregated)'!L17 -> 12 | M17: 45200 | N17: =IF(L17<37,SUMIF(I:I, J17, H:H),"Out of Scope") -> 66299
G18: ='Silver (Cleaned)'!G17 -> 45552.368 | H18: ='Silver (Cleaned)'!Q17 -> 1861 | I18: =TEXT(G18, "YYYY-MM") -> 2024-09 | J18: =TEXT(M18, "YYYY-MM") -> 2023-09 | L18: ='Black (Aggregated)'!L18 -> 13 | M18: 45170 | N18: =IF(L18<37,SUMIF(I:I, J18, H:H),"Out of Scope") -> 63171
G19: ='Silver (Cleaned)'!G18 -> 45551.78 | H19: ='Silver (Cleaned)'!Q18 -> 2052 | I19: =TEXT(G19, "YYYY-MM") -> 2024-09 | J19: =TEXT(M19, "YYYY-MM") -> 2023-08 | L19: ='Black (Aggregated)'!L19 -> 14 | M19: 45139 | N19: =IF(L19<37,SUMIF(I:I, J19, H:H),"Out of Scope") -> 55306
G20: ='Silver (Cleaned)'!G19 -> 45551.215 | H20: ='Silver (Cleaned)'!Q19 -> 1849 | I20: =TEXT(G20, "YYYY-MM") -> 2024-09 | J20: =TEXT(M20, "YYYY-MM") -> 2023-07 | L20: ='Black (Aggregated)'!L20 -> 15 | M20: 45108 | N20: =IF(L20<37,SUMIF(I:I, J20, H:H),"Out of Scope") -> 43882
G21: ='Silver (Cleaned)'!G20 -> 45548.894 | H21: ='Silver (Cleaned)'!Q20 -> 1932 | I21: =TEXT(G21, "YYYY-MM") -> 2024-09 | J21: =TEXT(M21, "YYYY-MM") -> 2023-06 | L21: ='Black (Aggregated)'!L21 -> 16 | M21: 45078 | N21: =IF(L21<37,SUMIF(I:I, J21, H:H),"Out of Scope") -> 58342
G22: ='Silver (Cleaned)'!G21 -> 45548.336 | H22: ='Silver (Cleaned)'!Q21 -> 1867 | I22: =TEXT(G22, "YYYY-MM") -> 2024-09 | J22: =TEXT(M22, "YYYY-MM") -> 2023-05 | L22: ='Black (Aggregated)'!L22 -> 17 | M22: 45047 | N22: =IF(L22<37,SUMIF(I:I, J22, H:H),"Out of Scope") -> 58469
G23: ='Silver (Cleaned)'!G22 -> 45547.782 | H23: ='Silver (Cleaned)'!Q22 -> 1748 | I23: =TEXT(G23, "YYYY-MM") -> 2024-09 | J23: =TEXT(M23, "YYYY-MM") -> 2023-04 | L23: ='Black (Aggregated)'!L23 -> 18 | M23: 45017 | N23: =IF(L23<37,SUMIF(I:I, J23, H:H),"Out of Scope") -> 48871
... G50: ='Silver (Cleaned)'!G49 -> 45526.054 | H50: ='Silver (Cleaned)'!Q49 -> 1702 | I50: =TEXT(G50, "YYYY-MM") -> 2024-08 | J50: =TEXT(M50, "YYYY-MM") -> 2021-01 | L50: ='Black (Aggregated)'!L50 -> 45 | M50: 44197 | N50: =IF(L50<37,SUMIF(I:I, J50, H:H),"Out of Scope") -> Out of Scope
G51: ='Silver (Cleaned)'!G50 -> 45525.487 | H51: ='Silver (Cleaned)'!Q50 -> 1530 | I51: =TEXT(G51, "YYYY-MM") -> 2024-08 | J51: =TEXT(M51, "YYYY-MM") -> 1900-01
G52: ='Silver (Cleaned)'!G51 -> 45524.933 | H52: ='Silver (Cleaned)'!Q51 -> 1654 | I52: =TEXT(G52, "YYYY-MM") -> 2024-08 | J52: =TEXT(M52, "YYYY-MM") -> 1900-01
G53: ='Silver (Cleaned)'!G52 -> 45524.399 | H53: ='Silver (Cleaned)'!Q52 -> 1365 | I53: =TEXT(G53, "YYYY-MM") -> 2024-08 | J53: =TEXT(M53, "YYYY-MM") -> 1900-01
G54: ='Silver (Cleaned)'!G53 -> 45523.814 | H54: ='Silver (Cleaned)'!Q53 -> 1519 | I54: =TEXT(G54, "YYYY-MM") -> 2024-08 | J54: =TEXT(M54, "YYYY-MM") -> 1900-01
G55: ='Silver (Cleaned)'!G54 -> 45523.22 | H55: ='Silver (Cleaned)'!Q54 -> 1542 | I55: =TEXT(G55, "YYYY-MM") -> 2024-08 | J55: =TEXT(M55, "YYYY-MM") -> 1900-01
G56: ='Silver (Cleaned)'!G55 -> 45520.968 | H56: ='Silver (Cleaned)'!Q55 -> 1567 | I56: =TEXT(G56, "YYYY-MM") -> 2024-08 | J56: =TEXT(M56, "YYYY-MM") -> 1900-01
G57: ='Silver (Cleaned)'!G56 -> 45520.421 | H57: ='Silver (Cleaned)'!Q56 -> 1397 | I57: =TEXT(G57, "YYYY-MM") -> 2024-08 | J57: =TEXT(M57, "YYYY-MM") -> 1900-01
G58: ='Silver (Cleaned)'!G57 -> 45519.819 | H58: ='Silver (Cleaned)'!Q57 -> 1262 | I58: =TEXT(G58, "YYYY-MM") -> 2024-08 | J58: =TEXT(M58, "YYYY-MM") -> 1900-01
G59: ='Silver (Cleaned)'!G58 -> 45519.258 | H59: ='Silver (Cleaned)'!Q58 -> 1292 | I59: =TEXT(G59, "YYYY-MM") -> 2024-08 | J59: =TEXT(M59, "YYYY-MM") -> 1900-01
G60: ='Silver (Cleaned)'!G59 -> 45518.722 | H60: ='Silver (Cleaned)'!Q59 -> 1335 | I60: =TEXT(G60, "YYYY-MM") -> 2024-08 | J60: =TEXT(M60, "YYYY-MM") -> 1900-01
G61: ='Silver (Cleaned)'!G60 -> 45518.108 | H61: ='Silver (Cleaned)'!Q60 -> 1433 | I61: =TEXT(G61, "YYYY-MM") -> 2024-08 | J61: =TEXT(M61, "YYYY-MM") -> 1900-01
G62: ='Silver (Cleaned)'!G61 -> 45517.564 | H62: ='Silver (Cleaned)'!Q61 -> 1308 | I62: =TEXT(G62, "YYYY-MM") -> 2024-08 | J62: =TEXT(M62, "YYYY-MM") -> 1900-01
... G1710: ='Silver (Cleaned)'!G1709 -> 44197.475 | H1710: ='Silver (Cleaned)'!Q1709 -> 1521 | I1710: =TEXT(G1710, "YYYY-MM") -> 2021-01 | J1710: =TEXT(M1710, "YYYY-MM") -> 1900-01

Sheet Total Sales
A1: Assumptions
C2: Combined Sales Data for Product Family: SONY WH1000-MX5
G5: Month | H5: Monthly Sales Black | I5: Monthly Sales Silver | J5: Monthly Sales Combined
G6: 45536 | H6: ='Black (Aggregated)'!N6 -> 112872 | I6: ='Silver (Aggregated)'!N6 -> 57705 | J6: =IF(OR(H6="Out of Scope",I6="Out of Scope"),"Out of Scope", H6+I6) -> 170577
G7: 45505 | H7: ='Black (Aggregated)'!N7 -> 90886 | I7: ='Silver (Aggregated)'!N7 -> 58140 | J7: =IF(OR(H7="Out of Scope",I7="Out of Scope"),"Out of Scope", H7+I7) -> 149026
G8: 45474 | H8: ='Black (Aggregated)'!N8 -> 88716 | I8: ='Silver (Aggregated)'!N8 -> 50461 | J8: =IF(OR(H8="Out of Scope",I8="Out of Scope"),"Out of Scope", H8+I8) -> 139177
G9: 45444 | H9: ='Black (Aggregated)'!N9 -> 100669 | I9: ='Silver (Aggregated)'!N9 -> 53435 | J9: =IF(OR(H9="Out of Scope",I9="Out of Scope"),"Out of Scope", H9+I9) -> 154104
G10: 45413 | H10: ='Black (Aggregated)'!N10 -> 116472 | I10: ='Silver (Aggregated)'!N10 -> 64106 | J10: =IF(OR(H10="Out of Scope",I10="Out of Scope"),"Out of Scope", H10+I10) -> 180578
G11: 45383 | H11: ='Black (Aggregated)'!N11 -> 105989 | I11: ='Silver (Aggregated)'!N11 -> 56954 | J11: =IF(OR(H11="Out of Scope",I11="Out of Scope"),"Out of Scope", H11+I11) -> 162943
G12: 45352 | H12: ='Black (Aggregated)'!N12 -> 123627 | I12: ='Silver (Aggregated)'!N12 -> 58243 | J12: =IF(OR(H12="Out of Scope",I12="Out of Scope"),"Out of Scope", H12+I12) -> 181870
G13: 45323 | H13: ='Black (Aggregated)'!N13 -> 134180 | I13: ='Silver (Aggregated)'!N13 -> 76839.5 | J13: =IF(OR(H13="Out of Scope",I13="Out of Scope"),"Out of Scope", H13+I13) -> 211019.5
G14: 45292 | H14: ='Black (Aggregated)'!N14 -> 205208 | I14: ='Silver (Aggregated)'!N14 -> 114572.5 | J14: =IF(OR(H14="Out of Scope",I14="Out of Scope"),"Out of Scope", H14+I14) -> 319780.5
G15: 45261 | H15: ='Black (Aggregated)'!N15 -> 206038 | I15: ='Silver (Aggregated)'!N15 -> 101606 | J15: =IF(OR(H15="Out of Scope",I15="Out of Scope"),"Out of Scope", H15+I15) -> 307644
G16: 45231 | H16: ='Black (Aggregated)'!N16 -> 163313 | I16: ='Silver (Aggregated)'!N16 -> 85614 | J16: =IF(OR(H16="Out of Scope",I16="Out of Scope"),"Out of Scope", H16+I16) -> 248927
G17: 45200 | H17: ='Black (Aggregated)'!N17 -> 128256 | I17: ='Silver (Aggregated)'!N17 -> 66299 | J17: =IF(OR(H17="Out of Scope",I17="Out of Scope"),"Out of Scope", H17+I17) -> 194555
... G28: 44866 | H28: ='Black (Aggregated)'!N28 -> 163412 | I28: ='Silver (Aggregated)'!N28 -> 80660 | J28: =IF(OR(H28="Out of Scope",I28="Out of Scope"),"Out of Scope", H28+I28) -> 244072
G29: 44835 | H29: ='Black (Aggregated)'!N29 -> 116187 | I29: ='Silver (Aggregated)'!N29 -> 58754 | J29: =IF(OR(H29="Out of Scope",I29="Out of Scope"),"Out of Scope", H29+I29) -> 174941 | L29: Summary
G30: 44805 | H30: ='Black (Aggregated)'!N30 -> 112346 | I30: ='Silver (Aggregated)'!N30 -> 60565 | J30: =IF(OR(H30="Out of Scope",I30="Out of Scope"),"Out of Scope", H30+I30) -> 172911 | L30: Sum of Monthly Sales Combined | M30: Column Labels
G31: 44774 | H31: ='Black (Aggregated)'!N31 -> 84181 | I31: ='Silver (Aggregated)'!N31 -> 51840 | J31: =IF(OR(H31="Out of Scope",I31="Out of Scope"),"Out of Scope", H31+I31) -> 136021 | L31: Row Labels | M31: Jan | N31: Feb | O31: Mar | P31: Apr | Q31: May | R31: Jun | S31: Jul | T31: Aug | U31: Sep | V31: Oct | W31: Nov | X31: Dec | Y31: Grand Total
G32: 44743 | H32: ='Black (Aggregated)'!N32 -> 74539 | I32: ='Silver (Aggregated)'!N32 -> 42482 | J32: =IF(OR(H32="Out of Scope",I32="Out of Scope"),"Out of Scope", H32+I32) -> 117021 | L32: 2021 | V32: 164732 | W32: 229781.5 | X32: 309493.5 | Y32: 704007
G33: 44713 | H33: ='Black (Aggregated)'!N33 -> 98843 | I33: ='Silver (Aggregated)'!N33 -> 53813 | J33: =IF(OR(H33="Out of Scope",I33="Out of Scope"),"Out of Scope", H33+I33) -> 152656 | L33: 2022 | M33: 264563.5 | N33: 175668 | O33: 181528 | P33: 137910 | Q33: 153981 | R33: 152656 | S33: 117021 | T33: 136021 | U33: 172911 | V33: 174941 | W33: 244072 | X33: 302011.5 | Y33: 2213284
G34: 44682 | H34: ='Black (Aggregated)'!N34 -> 96735 | I34: ='Silver (Aggregated)'!N34 -> 57246 | J34: =IF(OR(H34="Out of Scope",I34="Out of Scope"),"Out of Scope", H34+I34) -> 153981 | L34: 2023 | M34: 296525.5 | N34: 203227 | O34: 184191 | P34: 137881 | Q34: 171600 | R34: 160487 | S34: 117214 | T34: 142076 | U34: 174735 | V34: 194555 | W34: 248927 | X34: 307644 | Y34: 2339062.5
G35: 44652 | H35: ='Black (Aggregated)'!N35 -> 88678 | I35: ='Silver (Aggregated)'!N35 -> 49232 | J35: =IF(OR(H35="Out of Scope",I35="Out of Scope"),"Out of Scope", H35+I35) -> 137910 | L35: 2024 | M35: 319780.5 | N35: 211019.5 | O35: 181870 | P35: 162943 | Q35: 180578 | R35: 154104 | S35: 139177 | T35: 149026 | U35: 170577 | Y35: 1669075
G36: 44621 | H36: ='Black (Aggregated)'!N36 -> 122690 | I36: ='Silver (Aggregated)'!N36 -> 58838 | J36: =IF(OR(H36="Out of Scope",I36="Out of Scope"),"Out of Scope", H36+I36) -> 181528
G37: 44593 | H37: ='Black (Aggregated)'!N37 -> 112402 | I37: ='Silver (Aggregated)'!N37 -> 63266 | J37: =IF(OR(H37="Out of Scope",I37="Out of Scope"),"Out of Scope", H37+I37) -> 175668
G38: 44562 | H38: ='Black (Aggregated)'!N38 -> 171166 | I38: ='Silver (Aggregated)'!N38 -> 93397.5 | J38: =IF(OR(H38="Out of Scope",I38="Out of Scope"),"Out of Scope", H38+I38) -> 264563.5
G39: 44531 | H39: ='Black (Aggregated)'!N39 -> 206971 | I39: ='Silver (Aggregated)'!N39 -> 102522.5 | J39: =IF(OR(H39="Out of Scope",I39="Out of Scope"),"Out of Scope", H39+I39) -> 309493.5 | L39: Growth rate
G40: 44501 | H40: ='Black (Aggregated)'!N40 -> 146396 | I40: ='Silver (Aggregated)'!N40 -> 83385.5 | J40: =IF(OR(H40="Out of Scope",I40="Out of Scope"),"Out of Scope", H40+I40) -> 229781.5 | L40: YoY | M40: Sales, Qty | N40: Growth YOY %
G41: 44470 | H41: ='Black (Aggregated)'!N41 -> 105878 | I41: ='Silver (Aggregated)'!N41 -> 58854 | J41: =IF(OR(H41="Out of Scope",I41="Out of Scope"),"Out of Scope", H41+I41) -> 164732 | L41: Oct21-Sep22 | M41: =SUM(V32,W32,X32,M33,N33,O33,P33,Q33,R33,S33,T33,U33) -> 2196266.5
G42: 44440 | H42: ='Black (Aggregated)'!N42 -> Out of Scope | I42: ='Silver (Aggregated)'!N42 -> Out of Scope | J42: =IF(OR(H42="Out of Scope",I42="Out of Scope"),"Out of Scope", H42+I42) -> Out of Scope | L42: Oct22-Sep23 | M42: =SUM(V33,W33,X33,M34,N34,O34,P34,Q34,R34,S34,T34,U34) -> 2308961 | N42: =M42/M41-1 -> 0.051311851
G43: 44409 | H43: ='Black (Aggregated)'!N43 -> Out of Scope | I43: ='Silver (Aggregated)'!N43 -> Out of Scope | J43: =IF(OR(H43="Out of Scope",I43="Out of Scope"),"Out of Scope", H43+I43) -> Out of Scope | L43: Oct23-Sep24 | M43: =SUM(V34,W34,X34,M35,N35,O35,P35,Q35,R35,S35,T35,U35) -> 2420201 | N43: =M43/M42-1 -> 0.048177514
G44: 44378 | H44: ='Black (Aggregated)'!N44 -> Out of Scope | I44: ='Silver (Aggregated)'!N44 -> Out of Scope | J44: =IF(OR(H44="Out of Scope",I44="Out of Scope"),"Out of Scope", H44+I44) -> Out of Scope
G45: 44348 | H45: ='Black (Aggregated)'!N45 -> Out of Scope | I45: ='Silver (Aggregated)'!N45 -> Out of Scope | J45: =IF(OR(H45="Out of Scope",I45="Out of Scope"),"Out of Scope", H45+I45) -> Out of Scope
G46: 44317 | H46: ='Black (Aggregated)'!N46 -> Out of Scope | I46: ='Silver (Aggregated)'!N46 -> Out of Scope | J46: =IF(OR(H46="Out of Scope",I46="Out of Scope"),"Out of Scope", H46+I46) -> Out of Scope
G47: 44287 | H47: ='Black (Aggregated)'!N47 -> Out of Scope | I47: ='Silver (Aggregated)'!N47 -> Out of Scope | J47: =IF(OR(H47="Out of Scope",I47="Out of Scope"),"Out of Scope", H47+I47) -> Out of Scope
G48: 44256 | H48: ='Black (Aggregated)'!N48 -> Out of Scope | I48: ='Silver (Aggregated)'!N48 -> Out of Scope | J48: =IF(OR(H48="Out of Scope",I48="Out of Scope"),"Out of Scope", H48+I48) -> Out of Scope
G49: 44228 | H49: ='Black (Aggregated)'!N49 -> Out of Scope | I49: ='Silver (Aggregated)'!N49 -> Out of Scope | J49: =IF(OR(H49="Out of Scope",I49="Out of Scope"),"Out of Scope", H49+I49) -> Out of Scope
G50: 44197 | H50: ='Black (Aggregated)'!N50 -> Out of Scope | I50: ='Silver (Aggregated)'!N50 -> Out of Scope | J50: =IF(OR(H50="Out of Scope",I50="Out of Scope"),"Out of Scope", H50+I50) -> Out of Scope

Sheet (ACF Helper)
A1: Assumptions
C2: Correlation Coefficient Calculator
E4: Monthly Sales WH1000-MX5 Black
E5: Month | F5: Monthly Sales | H5: Cross Correlation | I5: =CORREL(OFFSET($F$6,0,0,37-I$7),OFFSET($F$6,I$7,0,37-I$7)) -> 0.67847758 | J5: =CORREL(OFFSET($F$6,0,0,37-J$7),OFFSET($F$6,J$7,0,37-J$7)) -> 0.24608088 | K5: =CORREL(OFFSET($F$6,0,0,37-K$7),OFFSET($F$6,K$7,0,37-K$7)) -> -0.081041555 | L5: =CORREL(OFFSET($F$6,0,0,37-L$7),OFFSET($F$6,L$7,0,37-L$7)) -> -0.36132762 | M5: =CORREL(OFFSET($F$6,0,0,37-M$7),OFFSET($F$6,M$7,0,37-M$7)) -> -0.54344471 | N5: =CORREL(OFFSET($F$6,0,0,37-N$7),OFFSET($F$6,N$7,0,37-N$7)) -> -0.59684056 | O5: =CORREL(OFFSET($F$6,0,0,37-O$7),OFFSET($F$6,O$7,0,37-O$7)) -> -0.62483099 | P5: =CORREL(OFFSET($F$6,0,0,37-P$7),OFFSET($F$6,P$7,0,37-P$7)) -> -0.46789222 | ... AQ5: =CORREL(OFFSET($F$6,0,0,37-AQ$7),OFFSET($F$6,AQ$7,0,37-AQ$7)) -> -1
E6: 45536 | F6: {=INDEX('Black (Aggregated)'!$N$6:$N$41,MATCH(E6,'Black (Aggregated)'!$M$6:$M$41,0))} -> 112872 | H6: ACF value | I6: =SUM(OFFSET(I9,I7,0,36-I7,1))/DEVSQ($F$6:$F$41) -> 0.67753855 | J6: =SUM(OFFSET(J9,J7,0,36-J7,1))/DEVSQ($F$6:$F$41) -> 0.24252878 | K6: =SUM(OFFSET(K9,K7,0,36-K7,1))/DEVSQ($F$6:$F$41) -> -0.078373257 | L6: =SUM(OFFSET(L9,L7,0,36-L7,1))/DEVSQ($F$6:$F$41) -> -0.32740671 | M6: =SUM(OFFSET(M9,M7,0,36-M7,1))/DEVSQ($F$6:$F$41) -> -0.47936838 | N6: =SUM(OFFSET(N9,N7,0,36-N7,1))/DEVSQ($F$6:$F$41) -> -0.5232282 | O6: =SUM(OFFSET(O9,O7,0,36-O7,1))/DEVSQ($F$6:$F$41) -> -0.54735443 | P6: =SUM(OFFSET(P9,P7,0,36-P7,1))/DEVSQ($F$6:$F$41) -> -0.4038093 | ... AQ6: =SUM(OFFSET(AQ9,AQ7,0,36-AQ7,1))/DEVSQ($F$6:$F$41) -> 0.0042715224
E7: 45505 | F7: {=INDEX('Black (Aggregated)'!$N$6:$N$41,MATCH(E7,'Black (Aggregated)'!$M$6:$M$41,0))} -> 90886 | H7: Lag | I7: 1 | J7: 2 | K7: 3 | L7: 4 | M7: 5 | N7: 6 | O7: 7 | P7: 8 | Q7: 9 | R7: 10 | S7: 11 | T7: 12 | U7: 13 | V7: 14 | W7: 15 | X7: 16 | Y7: 17 | Z7: 18 | AA7: 19 | AB7: 20 | AC7: 21 | AD7: 22 | AE7: 23 | AF7: 24 | AG7: 25 | AH7: 26 | AI7: 27 | AJ7: 28 | AK7: 29 | AL7: 30 | AM7: 31 | AN7: 32 | AO7: 33 | AP7: 34 | AQ7: 35
E8: 45474 | F8: {=INDEX('Black (Aggregated)'!$N$6:$N$41,MATCH(E8,'Black (Aggregated)'!$M$6:$M$41,0))} -> 88716 | H8: Counter
E9: 45444 | F9: {=INDEX('Black (Aggregated)'!$N$6:$N$41,MATCH(E9,'Black (Aggregated)'!$M$6:$M$41,0))} -> 100669 | H9: 1 | I9: =IF($H9>I$7,($F6-$F$42)*(OFFSET($F6,-I$7,0)-$F$42),"") | J9: =IF($H9>J$7,($F6-$F$42)*(OFFSET($F6,-J$7,0)-$F$42),"") | K9: =IF($H9>K$7,($F6-$F$42)*(OFFSET($F6,-K$7,0)-$F$42),"") | L9: =IF($H9>L$7,($F6-$F$42)*(OFFSET($F6,-L$7,0)-$F$42),"") | M9: =IF($H9>M$7,($F6-$F$42)*(OFFSET($F6,-M$7,0)-$F$42),"") | N9: =IF($H9>N$7,($F6-$F$42)*(OFFSET($F6,-N$7,0)-$F$42),"") | O9: =IF($H9>O$7,($F6-$F$42)*(OFFSET($F6,-O$7,0)-$F$42),"") | P9: =IF($H9>P$7,($F6-$F$42)*(OFFSET($F6,-P$7,0)-$F$42),"") | ... AQ9: =IF($H9>AQ$7,($F6-$F$42)*(OFFSET($F6,-AQ$7,0)-$F$42),"")
E10: 45413 | F10: {=INDEX('Black (Aggregated)'!$N$6:$N$41,MATCH(E10,'Black (Aggregated)'!$M$6:$M$41,0))} -> 116472 | H10: 2 | I10: =IF($H10>I$7,($F7-$F$42)*(OFFSET($F7,-I$7,0)-$F$42),"") -> 4.0381206e+08 | J10: =IF($H10>J$7,($F7-$F$42)*(OFFSET($F7,-J$7,0)-$F$42),"") | K10: =IF($H10>K$7,($F7-$F$42)*(OFFSET($F7,-K$7,0)-$F$42),"") | L10: =IF($H10>L$7,($F7-$F$42)*(OFFSET($F7,-L$7,0)-$F$42),"") | M10: =IF($H10>M$7,($F7-$F$42)*(OFFSET($F7,-M$7,0)-$F$42),"") | N10: =IF($H10>N$7,($F7-$F$42)*(OFFSET($F7,-N$7,0)-$F$42),"") | O10: =IF($H10>O$7,($F7-$F$42)*(OFFSET($F7,-O$7,0)-$F$42),"") | P10: =IF($H10>P$7,($F7-$F$42)*(OFFSET($F7,-P$7,0)-$F$42),"") | ... AQ10: =IF($H10>AQ$7,($F7-$F$42)*(OFFSET($F7,-AQ$7,0)-$F$42),"")
E11: 45383 | F11: {=INDEX('Black (Aggregated)'!$N$6:$N$41,MATCH(E11,'Black (Aggregated)'!$M$6:$M$41,0))} -> 105989 | H11: 3 | I11: =IF($H11>I$7,($F8-$F$42)*(OFFSET($F8,-I$7,0)-$F$42),"") -> 1.2226622e+09 | J11: =IF($H11>J$7,($F8-$F$42)*(OFFSET($F8,-J$7,0)-$F$42),"") -> 4.2966201e+08 | K11: =IF($H11>K$7,($F8-$F$42)*(OFFSET($F8,-K$7,0)-$F$42),"") | L11: =IF($H11>L$7,($F8-$F$42)*(OFFSET($F8,-L$7,0)-$F$42),"") | M11: =IF($H11>M$7,($F8-$F$42)*(OFFSET($F8,-M$7,0)-$F$42),"") | N11: =IF($H11>N$7,($F8-$F$42)*(OFFSET($F8,-N$7,0)-$F$42),"") | O11: =IF($H11>O$7,($F8-$F$42)*(OFFSET($F8,-O$7,0)-$F$42),"") | P11: =IF($H11>P$7,($F8-$F$42)*(OFFSET($F8,-P$7,0)-$F$42),"") | ... AQ11: =IF($H11>AQ$7,($F8-$F$42)*(OFFSET($F8,-AQ$7,0)-$F$42),"")
E12: 45352 | F12: {=INDEX('Black (Aggregated)'!$N$6:$N$41,MATCH(E12,'Black (Aggregated)'!$M$6:$M$41,0))} -> 123627 | H12: 4 | I12: =IF($H12>I$7,($F9-$F$42)*(OFFSET($F9,-I$7,0)-$F$42),"") -> 8.698049e+08 | J12: =IF($H12>J$7,($F9-$F$42)*(OFFSET($F9,-J$7,0)-$F$42),"") -> 8.1747444e+08 | K12: =IF($H12>K$7,($F9-$F$42)*(OFFSET($F9,-K$7,0)-$F$42),"") -> 2.8727289e+08 | L12: =IF($H12>L$7,($F9-$F$42)*(OFFSET($F9,-L$7,0)-$F$42),"") | M12: =IF($H12>M$7,($F9-$F$42)*(OFFSET($F9,-M$7,0)-$F$42),"") | N12: =IF($H12>N$7,($F9-$F$42)*(OFFSET($F9,-N$7,0)-$F$42),"") | O12: =IF($H12>O$7,($F9-$F$42)*(OFFSET($F9,-O$7,0)-$F$42),"") | P12: =IF($H12>P$7,($F9-$F$42)*(OFFSET($F9,-P$7,0)-$F$42),"") | ... AQ12: =IF($H12>AQ$7,($F9-$F$42)*(OFFSET($F9,-AQ$7,0)-$F$42),"")
E13: 45323 | F13: {=INDEX('Black (Aggregated)'!$N$6:$N$41,MATCH(E13,'Black (Aggregated)'!$M$6:$M$41,0))} -> 134180 | H13: 5 | I13: =IF($H13>I$7,($F10-$F$42)*(OFFSET($F10,-I$7,0)-$F$42),"") -> 2.0045739e+08 | J13: =IF($H13>J$7,($F10-$F$42)*(OFFSET($F10,-J$7,0)-$F$42),"") -> 2.9981571e+08 | K13: =IF($H13>K$7,($F10-$F$42)*(OFFSET($F10,-K$7,0)-$F$42),"") -> 2.8177776e+08 | L13: =IF($H13>L$7,($F10-$F$42)*(OFFSET($F10,-L$7,0)-$F$42),"") -> 99020971 | M13: =IF($H13>M$7,($F10-$F$42)*(OFFSET($F10,-M$7,0)-$F$42),"") | N13: =IF($H13>N$7,($F10-$F$42)*(OFFSET($F10,-N$7,0)-$F$42),"") | O13: =IF($H13>O$7,($F10-$F$42)*(OFFSET($F10,-O$7,0)-$F$42),"") | P13: =IF($H13>P$7,($F10-$F$42)*(OFFSET($F10,-P$7,0)-$F$42),"") | ... AQ13: =IF($H13>AQ$7,($F10-$F$42)*(OFFSET($F10,-AQ$7,0)-$F$42),"")
E14: 45292 | F14: {=INDEX('Black (Aggregated)'!$N$6:$N$41,MATCH(E14,'Black (Aggregated)'!$M$6:$M$41,0))} -> 205208 | H14: 6 | I14: =IF($H14>I$7,($F11-$F$42)*(OFFSET($F11,-I$7,0)-$F$42),"") -> 1.5623533e+08 | J14: =IF($H14>J$7,($F11-$F$42)*(OFFSET($F11,-J$7,0)-$F$42),"") -> 4.532593e+08 | K14: =IF($H14>K$7,($F11-$F$42)*(OFFSET($F11,-K$7,0)-$F$42),"") -> 6.7792092e+08 | L14: =IF($H14>L$7,($F11-$F$42)*(OFFSET($F11,-L$7,0)-$F$42),"") -> 6.3713487e+08 | M14: =IF($H14>M$7,($F11-$F$42)*(OFFSET($F11,-M$7,0)-$F$42),"") -> 2.2389883e+08 | N14: =IF($H14>N$7,($F11-$F$42)*(OFFSET($F11,-N$7,0)-$F$42),"") | O14: =IF($H14>O$7,($F11-$F$42)*(OFFSET($F11,-O$7,0)-$F$42),"") | P14: =IF($H14>P$7,($F11-$F$42)*(OFFSET($F11,-P$7,0)-$F$42),"") | ... AQ14: =IF($H14>AQ$7,($F11-$F$42)*(OFFSET($F11,-AQ$7,0)-$F$42),"")
E15: 45261 | F15: {=INDEX('Black (Aggregated)'!$N$6:$N$41,MATCH(E15,'Black (Aggregated)'!$M$6:$M$41,0))} -> 206038 | H15: 7 | I15: =IF($H15>I$7,($F12-$F$42)*(OFFSET($F12,-I$7,0)-$F$42),"") -> 21754129 | J15: =IF($H15>J$7,($F12-$F$42)*(OFFSET($F12,-J$7,0)-$F$42),"") -> 9620929.6 | K15: =IF($H15>K$7,($F12-$F$42)*(OFFSET($F12,-K$7,0)-$F$42),"") -> 27911585 | L15: =IF($H15>L$7,($F12-$F$42)*(OFFSET($F12,-L$7,0)-$F$42),"") -> 41746187 | M15: =IF($H15>M$7,($F12-$F$42)*(OFFSET($F12,-M$7,0)-$F$42),"") -> 39234592 | N15: =IF($H15>N$7,($F12-$F$42)*(OFFSET($F12,-N$7,0)-$F$42),"") -> 13787630 | O15: =IF($H15>O$7,($F12-$F$42)*(OFFSET($F12,-O$7,0)-$F$42),"") | P15: =IF($H15>P$7,($F12-$F$42)*(OFFSET($F12,-P$7,0)-$F$42),"") | ... AQ15: =IF($H15>AQ$7,($F12-$F$42)*(OFFSET($F12,-AQ$7,0)-$F$42),"")
E16: 45231 | F16: {=INDEX('Black (Aggregated)'!$N$6:$N$41,MATCH(E16,'Black (Aggregated)'!$M$6:$M$41,0))} -> 163313 | H16: 8 | I16: =IF($H16>I$7,($F13-$F$42)*(OFFSET($F13,-I$7,0)-$F$42),"") -> -10874605 | J16: =IF($H16>J$7,($F13-$F$42)*(OFFSET($F13,-J$7,0)-$F$42),"") -> -1.765939e+08 | K16: =IF($H16>K$7,($F13-$F$42)*(OFFSET($F13,-K$7,0)-$F$42),"") -> -78100003 | L16: =IF($H16>L$7,($F13-$F$42)*(OFFSET($F13,-L$7,0)-$F$42),"") -> -2.2657841e+08 | M16: =IF($H16>M$7,($F13-$F$42)*(OFFSET($F13,-M$7,0)-$F$42),"") -> -3.3888381e+08 | N16: =IF($H16>N$7,($F13-$F$42)*(OFFSET($F13,-N$7,0)-$F$42),"") -> -3.184954e+08 | O16: =IF($H16>O$7,($F13-$F$42)*(OFFSET($F13,-O$7,0)-$F$42),"") -> -1.119241e+08 | P16: =IF($H16>P$7,($F13-$F$42)*(OFFSET($F13,-P$7,0)-$F$42),"") | ... AQ16: =IF($H16>AQ$7,($F13-$F$42)*(OFFSET($F13,-AQ$7,0)-$F$42),"")
E17: 45200 | F17: {=INDEX('Black (Aggregated)'!$N$6:$N$41,MATCH(E17,'Black (Aggregated)'!$M$6:$M$41,0))} -> 128256 | H17: 9 | I17: =IF($H17>I$7,($F14-$F$42)*(OFFSET($F14,-I$7,0)-$F$42),"") -> 7.5562648e+08 | J17: =IF($H17>J$7,($F14-$F$42)*(OFFSET($F14,-J$7,0)-$F$42),"") -> -93083596 | K17: =IF($H17>K$7,($F14-$F$42)*(OFFSET($F14,-K$7,0)-$F$42),"") -> -1.5115948e+09 | L17: =IF($H17>L$7,($F14-$F$42)*(OFFSET($F14,-L$7,0)-$F$42),"") -> -6.6851433e+08 | M17: =IF($H17>M$7,($F14-$F$42)*(OFFSET($F14,-M$7,0)-$F$42),"") -> -1.9394482e+09 | N17: =IF($H17>N$7,($F14-$F$42)*(OFFSET($F14,-N$7,0)-$F$42),"") -> -2.9007513e+09 | O17: =IF($H17>O$7,($F14-$F$42)*(OFFSET($F14,-O$7,0)-$F$42),"") -> -2.7262321e+09 | P17: =IF($H17>P$7,($F14-$F$42)*(OFFSET($F14,-P$7,0)-$F$42),"") -> -9.5803923e+08 | ... AQ17: =IF($H17>AQ$7,($F14-$F$42)*(OFFSET($F14,-AQ$7,0)-$F$42),"")
E18: 45170 | F18: {=INDEX('Black (Aggregated)'!$N$6:$N$41,MATCH(E18,'Black (Aggregated)'!$M$6:$M$41,0))} -> 111564 | H18: 10 | I18: =IF($H18>I$7,($F15-$F$42)*(OFFSET($F15,-I$7,0)-$F$42),"") -> 6.5347043e+09 | J18: =IF($H18>J$7,($F15-$F$42)*(OFFSET($F15,-J$7,0)-$F$42),"") -> 7.6342481e+08 | K18: =IF($H18>K$7,($F15-$F$42)*(OFFSET($F15,-K$7,0)-$F$42),"") -> -94044252 | L18: =IF($H18>L$7,($F15-$F$42)*(OFFSET($F15,-L$7,0)-$F$42),"") -> -1.527195e+09 | M18: =IF($H18>M$7,($F15-$F$42)*(OFFSET($F15,-M$7,0)-$F$42),"") -> -6.7541364e+08 | N18: =IF($H18>N$7,($F15-$F$42)*(OFFSET($F15,-N$7,0)-$F$42),"") -> -1.959464e+09 | O18: =IF($H18>O$7,($F15-$F$42)*(OFFSET($F15,-O$7,0)-$F$42),"") -> -2.9306881e+09 | P18: =IF($H18>P$7,($F15-$F$42)*(OFFSET($F15,-P$7,0)-$F$42),"") -> -2.7543678e+09 | ... AQ18: =IF($H18>AQ$7,($F15-$F$42)*(OFFSET($F15,-AQ$7,0)-$F$42),"")
E19: 45139 | F19: {=INDEX('Black (Aggregated)'!$N$6:$N$41,MATCH(E19,'Black (Aggregated)'!$M$6:$M$41,0))} -> 86770 | H19: 11 | I19: =IF($H19>I$7,($F16-$F$42)*(OFFSET($F16,-I$7,0)-$F$42),"") -> 3.1305855e+09 | J19: =IF($H19>J$7,($F16-$F$42)*(OFFSET($F16,-J$7,0)-$F$42),"") -> 3.0986067e+09 | K19: =IF($H19>K$7,($F16-$F$42)*(OFFSET($F16,-K$7,0)-$F$42),"") -> 3.6199852e+08 | L19: =IF($H19>L$7,($F16-$F$42)*(OFFSET($F16,-L$7,0)-$F$42),"") -> -44593624 | M19: =IF($H19>M$7,($F16-$F$42)*(OFFSET($F16,-M$7,0)-$F$42),"") -> -7.2416078e+08 | N19: =IF($H19>N$7,($F16-$F$42)*(OFFSET($F16,-N$7,0)-$F$42),"") -> -3.2026564e+08 | O19: =IF($H19>O$7,($F16-$F$42)*(OFFSET($F16,-O$7,0)-$F$42),"") -> -9.2913284e+08 | P19: =IF($H19>P$7,($F16-$F$42)*(OFFSET($F16,-P$7,0)-$F$42),"") -> -1.389665e+09 | ... AQ19: =IF($H19>AQ$7,($F16-$F$42)*(OFFSET($F16,-AQ$7,0)-$F$42),"")
E20: 45108 | F20: {=INDEX('Black (Aggregated)'!$N$6:$N$41,MATCH(E20,'Black (Aggregated)'!$M$6:$M$41,0))} -> 73332 | H20: 12 | I20: =IF($H20>I$7,($F17-$F$42)*(OFFSET($F17,-I$7,0)-$F$42),"") -> 1.3375519e+08 | J20: =IF($H20>J$7,($F17-$F$42)*(OFFSET($F17,-J$7,0)-$F$42),"") -> 2.8207859e+08 | K20: =IF($H20>K$7,($F17-$F$42)*(OFFSET($F17,-K$7,0)-$F$42),"") -> 2.7919717e+08 | L20: =IF($H20>L$7,($F17-$F$42)*(OFFSET($F17,-L$7,0)-$F$42),"") -> 32617551 | M20: =IF($H20>M$7,($F17-$F$42)*(OFFSET($F17,-M$7,0)-$F$42),"") -> -4018068.4 | N20: =IF($H20>N$7,($F17-$F$42)*(OFFSET($F17,-N$7,0)-$F$42),"") -> -65249855 | O20: =IF($H20>O$7,($F17-$F$42)*(OFFSET($F17,-O$7,0)-$F$42),"") -> -28857247 | P20: =IF($H20>P$7,($F17-$F$42)*(OFFSET($F17,-P$7,0)-$F$42),"") -> -83718679 | ... AQ20: =IF($H20>AQ$7,($F17-$F$42)*(OFFSET($F17,-AQ$7,0)-$F$42),"")
... E41: 44470 | F41: {=INDEX('Black (Aggregated)'!$N$6:$N$41,MATCH(E41,'Black (Aggregated)'!$M$6:$M$41,0))} -> 105878 | H41: 33 | I41: =IF($H41>I$7,($F38-$F$42)*(OFFSET($F38,-I$7,0)-$F$42),"") -> -5.7431609e+08 | J41: =IF($H41>J$7,($F38-$F$42)*(OFFSET($F38,-J$7,0)-$F$42),"") -> -97142361 | K41: =IF($H41>K$7,($F38-$F$42)*(OFFSET($F38,-K$7,0)-$F$42),"") -> -1.6746728e+09 | L41: =IF($H41>L$7,($F38-$F$42)*(OFFSET($F38,-L$7,0)-$F$42),"") -> -1.3009764e+09 | M41: =IF($H41>M$7,($F38-$F$42)*(OFFSET($F38,-M$7,0)-$F$42),"") -> -1.203204e+09 | N41: =IF($H41>N$7,($F38-$F$42)*(OFFSET($F38,-N$7,0)-$F$42),"") -> -2.330462e+09 | O41: =IF($H41>O$7,($F38-$F$42)*(OFFSET($F38,-O$7,0)-$F$42),"") -> -1.8832508e+09 | P41: =IF($H41>P$7,($F38-$F$42)*(OFFSET($F38,-P$7,0)-$F$42),"") -> -5.7691346e+08 | ... AQ41: =IF($H41>AQ$7,($F38-$F$42)*(OFFSET($F38,-AQ$7,0)-$F$42),"")
E42: Mean | F42: =AVERAGE(F6:F41) -> 124784.42 | H42: 34 | I42: =IF($H42>I$7,($F39-$F$42)*(OFFSET($F39,-I$7,0)-$F$42),"") -> 3.8119439e+09 | J42: =IF($H42>J$7,($F39-$F$42)*(OFFSET($F39,-J$7,0)-$F$42),"") -> -1.0176685e+09 | K42: =IF($H42>K$7,($F39-$F$42)*(OFFSET($F39,-K$7,0)-$F$42),"") -> -1.7213295e+08 | L42: =IF($H42>L$7,($F39-$F$42)*(OFFSET($F39,-L$7,0)-$F$42),"") -> -2.967463e+09 | M42: =IF($H42>M$7,($F39-$F$42)*(OFFSET($F39,-M$7,0)-$F$42),"") -> -2.3052857e+09 | N42: =IF($H42>N$7,($F39-$F$42)*(OFFSET($F39,-N$7,0)-$F$42),"") -> -2.1320364e+09 | O42: =IF($H42>O$7,($F39-$F$42)*(OFFSET($F39,-O$7,0)-$F$42),"") -> -4.1294991e+09 | P42: =IF($H42>P$7,($F39-$F$42)*(OFFSET($F39,-P$7,0)-$F$42),"") -> -3.3370561e+09 | ... AQ42: =IF($H42>AQ$7,($F39-$F$42)*(OFFSET($F39,-AQ$7,0)-$F$42),"")
H43: 35 | I43: =IF($H43>I$7,($F40-$F$42)*(OFFSET($F40,-I$7,0)-$F$42),"") -> 1.7761822e+09 | J43: =IF($H43>J$7,($F40-$F$42)*(OFFSET($F40,-J$7,0)-$F$42),"") -> 1.0023795e+09 | K43: =IF($H43>K$7,($F40-$F$42)*(OFFSET($F40,-K$7,0)-$F$42),"") -> -2.6760363e+08 | L43: =IF($H43>L$7,($F40-$F$42)*(OFFSET($F40,-L$7,0)-$F$42),"") -> -45263660 | M43: =IF($H43>M$7,($F40-$F$42)*(OFFSET($F40,-M$7,0)-$F$42),"") -> -7.8031683e+08 | N43: =IF($H43>N$7,($F40-$F$42)*(OFFSET($F40,-N$7,0)-$F$42),"") -> -6.0619231e+08 | O43: =IF($H43>O$7,($F40-$F$42)*(OFFSET($F40,-O$7,0)-$F$42),"") -> -5.6063509e+08 | P43: =IF($H43>P$7,($F40-$F$42)*(OFFSET($F40,-P$7,0)-$F$42),"") -> -1.085883e+09 | ... AQ43: =IF($H43>AQ$7,($F40-$F$42)*(OFFSET($F40,-AQ$7,0)-$F$42),"")
H44: 36 | I44: =IF($H44>I$7,($F41-$F$42)*(OFFSET($F41,-I$7,0)-$F$42),"") -> -4.085976e+08 | J44: =IF($H44>J$7,($F41-$F$42)*(OFFSET($F41,-J$7,0)-$F$42),"") -> -1.5538538e+09 | K44: =IF($H44>K$7,($F41-$F$42)*(OFFSET($F41,-K$7,0)-$F$42),"") -> -8.7690954e+08 | L44: =IF($H44>L$7,($F41-$F$42)*(OFFSET($F41,-L$7,0)-$F$42),"") -> 2.3410713e+08 | M44: =IF($H44>M$7,($F41-$F$42)*(OFFSET($F41,-M$7,0)-$F$42),"") -> 39597914 | N44: =IF($H44>N$7,($F41-$F$42)*(OFFSET($F41,-N$7,0)-$F$42),"") -> 6.8264296e+08 | O44: =IF($H44>O$7,($F41-$F$42)*(OFFSET($F41,-O$7,0)-$F$42),"") -> 5.3031396e+08 | P44: =IF($H44>P$7,($F41-$F$42)*(OFFSET($F41,-P$7,0)-$F$42),"") -> 4.9045923e+08 | ... AQ44: =IF($H44>AQ$7,($F41-$F$42)*(OFFSET($F41,-AQ$7,0)-$F$42),"") -> 2.2522111e+08
E45: Monthly Sales WH1000-MX5 Silver
E46: Month | F46: Monthly Sales | H46: Cross Correlation | I46: =CORREL(OFFSET($F$47,0,0,37-I$48),OFFSET($F$47,I$48,0,37-I$48)) -> 0.68168544 | J46: =CORREL(OFFSET($F$47,0,0,37-J$48),OFFSET($F$47,J$48,0,37-J$48)) -> 0.20736098 | K46: =CORREL(OFFSET($F$47,0,0,37-K$48),OFFSET($F$47,K$48,0,37-K$48)) -> -0.13131764 | L46: =CORREL(OFFSET($F$47,0,0,37-L$48),OFFSET($F$47,L$48,0,37-L$48)) -> -0.31735294 | M46: =CORREL(OFFSET($F$47,0,0,37-M$48),OFFSET($F$47,M$48,0,37-M$48)) -> -0.48318315 | N46: =CORREL(OFFSET($F$47,0,0,37-N$48),OFFSET($F$47,N$48,0,37-N$48)) -> -0.5909709 | O46: =CORREL(OFFSET($F$47,0,0,37-O$48),OFFSET($F$47,O$48,0,37-O$48)) -> -0.55103263 | P46: =CORREL(OFFSET($F$47,0,0,37-P$48),OFFSET($F$47,P$48,0,37-P$48)) -> -0.40439144 | ... AQ46: =CORREL(OFFSET($F$47,0,0,37-AQ$48),OFFSET($F$47,AQ$48,0,37-AQ$48)) -> 1
E47: 45536 | F47: {=INDEX('Silver (Aggregated)'!$N$6:$N$41,MATCH(E6,'Silver (Aggregated)'!$M$6:$M$41,0))} -> 57705 | H47: ACF value | I47: =SUM(OFFSET(I50,I48,0,36-I48,1))/DEVSQ($F$47:$F$82) -> 0.67903724 | J47: =SUM(OFFSET(J50,J48,0,36-J48,1))/DEVSQ($F$47:$F$82) -> 0.2055203 | K47: =SUM(OFFSET(K50,K48,0,36-K48,1))/DEVSQ($F$47:$F$82) -> -0.12760491 | L47: =SUM(OFFSET(L50,L48,0,36-L48,1))/DEVSQ($F$47:$F$82) -> -0.29324557 | M47: =SUM(OFFSET(M50,M48,0,36-M48,1))/DEVSQ($F$47:$F$82) -> -0.43242684 | N47: =SUM(OFFSET(N50,N48,0,36-N48,1))/DEVSQ($F$47:$F$82) -> -0.52482986 | O47: =SUM(OFFSET(O50,O48,0,36-O48,1))/DEVSQ($F$47:$F$82) -> -0.48649897 | P47: =SUM(OFFSET(P50,P48,0,36-P48,1))/DEVSQ($F$47:$F$82) -> -0.35024219 | ... AQ47: =SUM(OFFSET(AQ50,AQ48,0,36-AQ48,1))/DEVSQ($F$47:$F$82) -> 0.0066677854
E48: 45505 | F48: {=INDEX('Silver (Aggregated)'!$N$6:$N$41,MATCH(E7,'Silver (Aggregated)'!$M$6:$M$41,0))} -> 58140 | H48: Lag | I48: 1 | J48: 2 | K48: 3 | L48: 4 | M48: 5 | N48: 6 | O48: 7 | P48: 8 | Q48: 9 | R48: 10 | S48: 11 | T48: 12 | U48: 13 | V48: 14 | W48: 15 | X48: 16 | Y48: 17 | Z48: 18 | AA48: 19 | AB48: 20 | AC48: 21 | AD48: 22 | AE48: 23 | AF48: 24 | AG48: 25 | AH48: 26 | AI48: 27 | AJ48: 28 | AK48: 29 | AL48: 30 | AM48: 31 | AN48: 32 | AO48: 33 | AP48: 34 | AQ48: 35
E49: 45474 | F49: {=INDEX('Silver (Aggregated)'!$N$6:$N$41,MATCH(E8,'Silver (Aggregated)'!$M$6:$M$41,0))} -> 50461 | H49: Counter
E50: 45444 | F50: {=INDEX('Silver (Aggregated)'!$N$6:$N$41,MATCH(E9,'Silver (Aggregated)'!$M$6:$M$41,0))} -> 53435 | H50: 1 | I50: =IF($H50>I$48,($F47-$F$83)*(OFFSET($F47,-I$48,0)-$F$83),"") | J50: =IF($H50>J$48,($F47-$F$83)*(OFFSET($F47,-J$48,0)-$F$83),"") | K50: =IF($H50>K$48,($F47-$F$83)*(OFFSET($F47,-K$48,0)-$F$83),"") | L50: =IF($H50>L$48,($F47-$F$83)*(OFFSET($F47,-L$48,0)-$F$83),"") | M50: =IF($H50>M$48,($F47-$F$83)*(OFFSET($F47,-M$48,0)-$F$83),"") | N50: =IF($H50>N$48,($F47-$F$83)*(OFFSET($F47,-N$48,0)-$F$83),"") | O50: =IF($H50>O$48,($F47-$F$83)*(OFFSET($F47,-O$48,0)-$F$83),"") | P50: =IF($H50>P$48,($F47-$F$83)*(OFFSET($F47,-P$48,0)-$F$83),"") | ... AQ50: =IF($H50>AQ$48,($F47-$F$83)*(OFFSET($F47,-AQ$48,0)-$F$83),"")
E51: 45413 | F51: {=INDEX('Silver (Aggregated)'!$N$6:$N$41,MATCH(E10,'Silver (Aggregated)'!$M$6:$M$41,0))} -> 64106 | H51: 2 | I51: =IF($H51>I$48,($F48-$F$83)*(OFFSET($F48,-I$48,0)-$F$83),"") -> 93386129 | J51: =IF($H51>J$48,($F48-$F$83)*(OFFSET($F48,-J$48,0)-$F$83),"") | K51: =IF($H51>K$48,($F48-$F$83)*(OFFSET($F48,-K$48,0)-$F$83),"") | L51: =IF($H51>L$48,($F48-$F$83)*(OFFSET($F48,-L$48,0)-$F$83),"") | M51: =IF($H51>M$48,($F48-$F$83)*(OFFSET($F48,-M$48,0)-$F$83),"") | N51: =IF($H51>N$48,($F48-$F$83)*(OFFSET($F48,-N$48,0)-$F$83),"") | O51: =IF($H51>O$48,($F48-$F$83)*(OFFSET($F48,-O$48,0)-$F$83),"") | P51: =IF($H51>P$48,($F48-$F$83)*(OFFSET($F48,-P$48,0)-$F$83),"") | ... AQ51: =IF($H51>AQ$48,($F48-$F$83)*(OFFSET($F48,-AQ$48,0)-$F$83),"")
E52: 45383 | F52: {=INDEX('Silver (Aggregated)'!$N$6:$N$41,MATCH(E11,'Silver (Aggregated)'!$M$6:$M$41,0))} -> 56954 | H52: 3 | I52: =IF($H52>I$48,($F49-$F$83)*(OFFSET($F49,-I$48,0)-$F$83),"") -> 1.6183177e+08 | J52: =IF($H52>J$48,($F49-$F$83)*(OFFSET($F49,-J$48,0)-$F$83),"") -> 1.6928227e+08 | K52: =IF($H52>K$48,($F49-$F$83)*(OFFSET($F49,-K$48,0)-$F$83),"") | L52: =IF($H52>L$48,($F49-$F$83)*(OFFSET($F49,-L$48,0)-$F$83),"") | M52: =IF($H52>M$48,($F49-$F$83)*(OFFSET($F49,-M$48,0)-$F$83),"") | N52: =IF($H52>N$48,($F49-$F$83)*(OFFSET($F49,-N$48,0)-$F$83),"") | O52: =IF($H52>O$48,($F49-$F$83)*(OFFSET($F49,-O$48,0)-$F$83),"") | P52: =IF($H52>P$48,($F49-$F$83)*(OFFSET($F49,-P$48,0)-$F$83),"") | ... AQ52: =IF($H52>AQ$48,($F49-$F$83)*(OFFSET($F49,-AQ$48,0)-$F$83),"")
E53: 45352 | F53: {=INDEX('Silver (Aggregated)'!$N$6:$N$41,MATCH(E12,'Silver (Aggregated)'!$M$6:$M$41,0))} -> 58243 | H53: 4 | I53: =IF($H53>I$48,($F50-$F$83)*(OFFSET($F50,-I$48,0)-$F$83),"") -> 2.4241711e+08 | J53: =IF($H53>J$48,($F50-$F$83)*(OFFSET($F50,-J$48,0)-$F$83),"") -> 1.3373164e+08 | K53: =IF($H53>K$48,($F50-$F$83)*(OFFSET($F50,-K$48,0)-$F$83),"") -> 1.3988845e+08 | L53: =IF($H53>L$48,($F50-$F$83)*(OFFSET($F50,-L$48,0)-$F$83),"") | M53: =IF($H53>M$48,($F50-$F$83)*(OFFSET($F50,-M$48,0)-$F$83),"") | N53: =IF($H53>N$48,($F50-$F$83)*(OFFSET($F50,-N$48,0)-$F$83),"") | O53: =IF($H53>O$48,($F50-$F$83)*(OFFSET($F50,-O$48,0)-$F$83),"") | P53: =IF($H53>P$48,($F50-$F$83)*(OFFSET($F50,-P$48,0)-$F$83),"") | ... AQ53: =IF($H53>AQ$48,($F50-$F$83)*(OFFSET($F50,-AQ$48,0)-$F$83),"")
E54: 45323 | F54: {=INDEX('Silver (Aggregated)'!$N$6:$N$41,MATCH(E13,'Silver (Aggregated)'!$M$6:$M$41,0))} -> 76839.5 | H54: 5 | I54: =IF($H54>I$48,($F51-$F$83)*(OFFSET($F51,-I$48,0)-$F$83),"") -> 49291278 | J54: =IF($H54>J$48,($F51-$F$83)*(OFFSET($F51,-J$48,0)-$F$83),"") -> 59648523 | K54: =IF($H54>K$48,($F51-$F$83)*(OFFSET($F51,-K$48,0)-$F$83),"") -> 32905658 | L54: =IF($H54>L$48,($F51-$F$83)*(OFFSET($F51,-L$48,0)-$F$83),"") -> 34420588 | M54: =IF($H54>M$48,($F51-$F$83)*(OFFSET($F51,-M$48,0)-$F$83),"") | N54: =IF($H54>N$48,($F51-$F$83)*(OFFSET($F51,-N$48,0)-$F$83),"") | O54: =IF($H54>O$48,($F51-$F$83)*(OFFSET($F51,-O$48,0)-$F$83),"") | P54: =IF($H54>P$48,($F51-$F$83)*(OFFSET($F51,-P$48,0)-$F$83),"") | ... AQ54: =IF($H54>AQ$48,($F51-$F$83)*(OFFSET($F51,-AQ$48,0)-$F$83),"")
E55: 45292 | F55: {=INDEX('Silver (Aggregated)'!$N$6:$N$41,MATCH(E14,'Silver (Aggregated)'!$M$6:$M$41,0))} -> 114572.5 | H55: 6 | I55: =IF($H55>I$48,($F52-$F$83)*(OFFSET($F52,-I$48,0)-$F$83),"") -> 37036019 | J55: =IF($H55>J$48,($F52-$F$83)*(OFFSET($F52,-J$48,0)-$F$83),"") -> 1.5051781e+08 | K55: =IF($H55>K$48,($F52-$F$83)*(OFFSET($F52,-K$48,0)-$F$83),"") -> 1.821451e+08 | L55: =IF($H55>L$48,($F52-$F$83)*(OFFSET($F52,-L$48,0)-$F$83),"") -> 1.0048203e+08 | M55: =IF($H55>M$48,($F52-$F$83)*(OFFSET($F52,-M$48,0)-$F$83),"") -> 1.0510808e+08 | N55: =IF($H55>N$48,($F52-$F$83)*(OFFSET($F52,-N$48,0)-$F$83),"") | O55: =IF($H55>O$48,($F52-$F$83)*(OFFSET($F52,-O$48,0)-$F$83),"") | P55: =IF($H55>P$48,($F52-$F$83)*(OFFSET($F52,-P$48,0)-$F$83),"") | ... AQ55: =IF($H55>AQ$48,($F52-$F$83)*(OFFSET($F52,-AQ$48,0)-$F$83),"")
E56: 45261 | F56: {=INDEX('Silver (Aggregated)'!$N$6:$N$41,MATCH(E15,'Silver (Aggregated)'!$M$6:$M$41,0))} -> 101606 | H56: 7 | I56: =IF($H56>I$48,($F53-$F$83)*(OFFSET($F53,-I$48,0)-$F$83),"") -> 99386662 | J56: =IF($H56>J$48,($F53-$F$83)*(OFFSET($F53,-J$48,0)-$F$83),"") -> 32546951 | K56: =IF($H56>K$48,($F53-$F$83)*(OFFSET($F53,-K$48,0)-$F$83),"") -> 1.3227382e+08 | L56: =IF($H56>L$48,($F53-$F$83)*(OFFSET($F53,-L$48,0)-$F$83),"") -> 1.6006763e+08 | M56: =IF($H56>M$48,($F53-$F$83)*(OFFSET($F53,-M$48,0)-$F$83),"") -> 88302784 | N56: =IF($H56>N$48,($F53-$F$83)*(OFFSET($F53,-N$48,0)-$F$83),"") -> 92368119 | O56: =IF($H56>O$48,($F53-$F$83)*(OFFSET($F53,-O$48,0)-$F$83),"") | P56: =IF($H56>P$48,($F53-$F$83)*(OFFSET($F53,-P$48,0)-$F$83),"") | ... AQ56: =IF($H56>AQ$48,($F53-$F$83)*(OFFSET($F53,-AQ$48,0)-$F$83),"")
E57: 45231 | F57: {=INDEX('Silver (Aggregated)'!$N$6:$N$41,MATCH(E16,'Silver (Aggregated)'!$M$6:$M$41,0))} -> 85614 | H57: 8 | I57: =IF($H57>I$48,($F54-$F$83)*(OFFSET($F54,-I$48,0)-$F$83),"") -> -86455211 | J57: =IF($H57>J$48,($F54-$F$83)*(OFFSET($F54,-J$48,0)-$F$83),"") -> -98379625 | K57: =IF($H57>K$48,($F54-$F$83)*(OFFSET($F54,-K$48,0)-$F$83),"") -> -32217168 | L57: =IF($H57>L$48,($F54-$F$83)*(OFFSET($F54,-L$48,0)-$F$83),"") -> -1.3093355e+08 | M57: =IF($H57>M$48,($F54-$F$83)*(OFFSET($F54,-M$48,0)-$F$83),"") -> -1.5844574e+08 | N57: =IF($H57>N$48,($F54-$F$83)*(OFFSET($F54,-N$48,0)-$F$83),"") -> -87408054 | O57: =IF($H57>O$48,($F54-$F$83)*(OFFSET($F54,-O$48,0)-$F$83),"") -> -91432197 | P57: =IF($H57>P$48,($F54-$F$83)*(OFFSET($F54,-P$48,0)-$F$83),"") | ... AQ57: =IF($H57>AQ$48,($F54-$F$83)*(OFFSET($F54,-AQ$48,0)-$F$83),"")
E58: 45200 | F58: {=INDEX('Silver (Aggregated)'!$N$6:$N$41,MATCH(E17,'Silver (Aggregated)'!$M$6:$M$41,0))} -> 66299 | H58: 9 | I58: =IF($H58>I$48,($F55-$F$83)*(OFFSET($F55,-I$48,0)-$F$83),"") -> 4.3464352e+08 | J58: =IF($H58>J$48,($F55-$F$83)*(OFFSET($F55,-J$48,0)-$F$83),"") -> -4.3909263e+08 | K58: =IF($H58>K$48,($F55-$F$83)*(OFFSET($F55,-K$48,0)-$F$83),"") -> -4.9965488e+08 | L58: =IF($H58>L$48,($F55-$F$83)*(OFFSET($F55,-L$48,0)-$F$83),"") -> -1.6362601e+08 | M58: =IF($H58>M$48,($F55-$F$83)*(OFFSET($F55,-M$48,0)-$F$83),"") -> -6.6499124e+08 | N58: =IF($H58>N$48,($F55-$F$83)*(OFFSET($F55,-N$48,0)-$F$83),"") -> -8.0472136e+08 | O58: =IF($H58>O$48,($F55-$F$83)*(OFFSET($F55,-O$48,0)-$F$83),"") -> -4.4393197e+08 | P58: =IF($H58>P$48,($F55-$F$83)*(OFFSET($F55,-P$48,0)-$F$83),"") -> -4.6436997e+08 | ... AQ58: =IF($H58>AQ$48,($F55-$F$83)*(OFFSET($F55,-AQ$48,0)-$F$83),"")
E59: 45170 | F59: {=INDEX('Silver (Aggregated)'!$N$6:$N$41,MATCH(E18,'Silver (Aggregated)'!$M$6:$M$41,0))} -> 63171 | H59: 10 | I59: =IF($H59>I$48,($F56-$F$83)*(OFFSET($F56,-I$48,0)-$F$83),"") -> 1.5982703e+09 | J59: =IF($H59>J$48,($F56-$F$83)*(OFFSET($F56,-J$48,0)-$F$83),"") -> 3.1469169e+08 | K59: =IF($H59>K$48,($F56-$F$83)*(OFFSET($F56,-K$48,0)-$F$83),"") -> -3.1791294e+08 | L59: =IF($H59>L$48,($F56-$F$83)*(OFFSET($F56,-L$48,0)-$F$83),"") -> -3.6176138e+08 | M59: =IF($H59>M$48,($F56-$F$83)*(OFFSET($F56,-M$48,0)-$F$83),"") -> -1.1846891e+08 | N59: =IF($H59>N$48,($F56-$F$83)*(OFFSET($F56,-N$48,0)-$F$83),"") -> -4.8146862e+08 | O59: =IF($H59>O$48,($F56-$F$83)*(OFFSET($F56,-O$48,0)-$F$83),"") -> -5.8263637e+08 | P59: =IF($H59>P$48,($F56-$F$83)*(OFFSET($F56,-P$48,0)-$F$83),"") -> -3.2141674e+08 | ... AQ59: =IF($H59>AQ$48,($F56-$F$83)*(OFFSET($F56,-AQ$48,0)-$F$83),"")
E60: 45139 | F60: {=INDEX('Silver (Aggregated)'!$N$6:$N$41,MATCH(E19,'Silver (Aggregated)'!$M$6:$M$41,0))} -> 55306 | H60: 11 | I60: =IF($H60>I$48,($F57-$F$83)*(OFFSET($F57,-I$48,0)-$F$83),"") -> 6.1317739e+08 | J60: =IF($H60>J$48,($F57-$F$83)*(OFFSET($F57,-J$48,0)-$F$83),"") -> 8.4690377e+08 | K60: =IF($H60>K$48,($F57-$F$83)*(OFFSET($F57,-K$48,0)-$F$83),"") -> 1.6675125e+08 | L60: =IF($H60>L$48,($F57-$F$83)*(OFFSET($F57,-L$48,0)-$F$83),"") -> -1.6845815e+08 | M60: =IF($H60>M$48,($F57-$F$83)*(OFFSET($F57,-M$48,0)-$F$83),"") -> -1.916929e+08 | N60: =IF($H60>N$48,($F57-$F$83)*(OFFSET($F57,-N$48,0)-$F$83),"") -> -62775218 | O60: =IF($H60>O$48,($F57-$F$83)*(OFFSET($F57,-O$48,0)-$F$83),"") -> -2.5512429e+08 | P60: =IF($H60>P$48,($F57-$F$83)*(OFFSET($F57,-P$48,0)-$F$83),"") -> -3.0873184e+08 | ... AQ60: =IF($H60>AQ$48,($F57-$F$83)*(OFFSET($F57,-AQ$48,0)-$F$83),"")
E61: 45108 | F61: {=INDEX('Silver (Aggregated)'!$N$6:$N$41,MATCH(E20,'Silver (Aggregated)'!$M$6:$M$41,0))} -> 43882 | H61: 12 | I61: =IF($H61>I$48,($F58-$F$83)*(OFFSET($F58,-I$48,0)-$F$83),"") -> -23245509 | J61: =IF($H61>J$48,($F58-$F$83)*(OFFSET($F58,-J$48,0)-$F$83),"") -> -43868748 | K61: =IF($H61>K$48,($F58-$F$83)*(OFFSET($F58,-K$48,0)-$F$83),"") -> -60590311 | L61: =IF($H61>L$48,($F58-$F$83)*(OFFSET($F58,-L$48,0)-$F$83),"") -> -11929939 | M61: =IF($H61>M$48,($F58-$F$83)*(OFFSET($F58,-M$48,0)-$F$83),"") -> 12052056 | N61: =IF($H61>N$48,($F58-$F$83)*(OFFSET($F58,-N$48,0)-$F$83),"") -> 13714347 | O61: =IF($H61>O$48,($F58-$F$83)*(OFFSET($F58,-O$48,0)-$F$83),"") -> 4491147.7 | P61: =IF($H61>P$48,($F58-$F$83)*(OFFSET($F58,-P$48,0)-$F$83),"") -> 18252440 | ... AQ61: =IF($H61>AQ$48,($F58-$F$83)*(OFFSET($F58,-AQ$48,0)-$F$83),"")
... E82: 44470 | F82: {=INDEX('Silver (Aggregated)'!$N$6:$N$41,MATCH(E41,'Silver (Aggregated)'!$M$6:$M$41,0))} -> 58854 | H82: 33 | I82: =IF($H82>I$48,($F79-$F$83)*(OFFSET($F79,-I$48,0)-$F$83),"") -> -1.1156149e+08 | J82: =IF($H82>J$48,($F79-$F$83)*(OFFSET($F79,-J$48,0)-$F$83),"") -> -2.2584331e+08 | K82: =IF($H82>K$48,($F79-$F$83)*(OFFSET($F79,-K$48,0)-$F$83),"") -> -4.7376363e+08 | L82: =IF($H82>L$48,($F79-$F$83)*(OFFSET($F79,-L$48,0)-$F$83),"") -> -2.6693109e+08 | M82: =IF($H82>M$48,($F79-$F$83)*(OFFSET($F79,-M$48,0)-$F$83),"") -> -3.5553305e+08 | N82: =IF($H82>N$48,($F79-$F$83)*(OFFSET($F79,-N$48,0)-$F$83),"") -> -6.4797373e+08 | O82: =IF($H82>O$48,($F79-$F$83)*(OFFSET($F79,-O$48,0)-$F$83),"") -> -4.0645401e+08 | P82: =IF($H82>P$48,($F79-$F$83)*(OFFSET($F79,-P$48,0)-$F$83),"") -> -1.8127134e+08 | ... AQ82: =IF($H82>AQ$48,($F79-$F$83)*(OFFSET($F79,-AQ$48,0)-$F$83),"")
E83: Mean | F83: =AVERAGE(F47:F82) -> 67588.597 | H83: 34 | I83: =IF($H83>I$48,($F80-$F$83)*(OFFSET($F80,-I$48,0)-$F$83),"") -> 9.016057e+08 | J83: =IF($H83>J$48,($F80-$F$83)*(OFFSET($F80,-J$48,0)-$F$83),"") -> -1.5100519e+08 | K83: =IF($H83>K$48,($F80-$F$83)*(OFFSET($F80,-K$48,0)-$F$83),"") -> -3.0569251e+08 | L83: =IF($H83>L$48,($F80-$F$83)*(OFFSET($F80,-L$48,0)-$F$83),"") -> -6.4126758e+08 | M83: =IF($H83>M$48,($F80-$F$83)*(OFFSET($F80,-M$48,0)-$F$83),"") -> -3.6130729e+08 | N83: =IF($H83>N$48,($F80-$F$83)*(OFFSET($F80,-N$48,0)-$F$83),"") -> -4.8123537e+08 | O83: =IF($H83>O$48,($F80-$F$83)*(OFFSET($F80,-O$48,0)-$F$83),"") -> -8.7707143e+08 | P83: =IF($H83>P$48,($F80-$F$83)*(OFFSET($F80,-P$48,0)-$F$83),"") -> -5.5015996e+08 | ... AQ83: =IF($H83>AQ$48,($F80-$F$83)*(OFFSET($F80,-AQ$48,0)-$F$83),"")
H84: 35 | I84: =IF($H84>I$48,($F81-$F$83)*(OFFSET($F81,-I$48,0)-$F$83),"") -> 5.5184747e+08 | J84: =IF($H84>J$48,($F81-$F$83)*(OFFSET($F81,-J$48,0)-$F$83),"") -> 4.0770073e+08 | K84: =IF($H84>K$48,($F81-$F$83)*(OFFSET($F81,-K$48,0)-$F$83),"") -> -68283648 | L84: =IF($H84>L$48,($F81-$F$83)*(OFFSET($F81,-L$48,0)-$F$83),"") -> -1.3823233e+08 | M84: =IF($H84>M$48,($F81-$F$83)*(OFFSET($F81,-M$48,0)-$F$83),"") -> -2.8997738e+08 | N84: =IF($H84>N$48,($F81-$F$83)*(OFFSET($F81,-N$48,0)-$F$83),"") -> -1.63381e+08 | O84: =IF($H84>O$48,($F81-$F$83)*(OFFSET($F81,-O$48,0)-$F$83),"") -> -2.1761177e+08 | P84: =IF($H84>P$48,($F81-$F$83)*(OFFSET($F81,-P$48,0)-$F$83),"") -> -3.9660648e+08 | ... AQ84: =IF($H84>AQ$48,($F81-$F$83)*(OFFSET($F81,-AQ$48,0)-$F$83),"")
H85: 36 | I85: =IF($H85>I$48,($F82-$F$83)*(OFFSET($F82,-I$48,0)-$F$83),"") -> -1.3797958e+08 | J85: =IF($H85>J$48,($F82-$F$83)*(OFFSET($F82,-J$48,0)-$F$83),"") -> -3.0513357e+08 | K85: =IF($H85>K$48,($F82-$F$83)*(OFFSET($F82,-K$48,0)-$F$83),"") -> -2.2543037e+08 | L85: =IF($H85>L$48,($F82-$F$83)*(OFFSET($F82,-L$48,0)-$F$83),"") -> 37756146 | M85: =IF($H85>M$48,($F82-$F$83)*(OFFSET($F82,-M$48,0)-$F$83),"") -> 76432942 | N85: =IF($H85>N$48,($F82-$F$83)*(OFFSET($F82,-N$48,0)-$F$83),"") -> 1.6033748e+08 | O85: =IF($H85>O$48,($F82-$F$83)*(OFFSET($F82,-O$48,0)-$F$83),"") -> 90338421 | P85: =IF($H85>P$48,($F82-$F$83)*(OFFSET($F82,-P$48,0)-$F$83),"") -> 1.2032429e+08 | ... AQ85: =IF($H85>AQ$48,($F82-$F$83)*(OFFSET($F82,-AQ$48,0)-$F$83),"") -> 86329241
E86: Monthly Sales WH1000-MX5 Aggregated
E87: Month | F87: Monthly Sales | H87: Cross Correlation | I87: =CORREL(OFFSET($F$88,0,0,37-I$89),OFFSET($F$88,I$89,0,37-I$89)) -> 0.68854963 | J87: =CORREL(OFFSET($F$88,0,0,37-J$89),OFFSET($F$88,J$89,0,37-J$89)) -> 0.24079109 | K87: =CORREL(OFFSET($F$88,0,0,37-K$89),OFFSET($F$88,K$89,0,37-K$89)) -> -0.098339256 | L87: =CORREL(OFFSET($F$88,0,0,37-L$89),OFFSET($F$88,L$89,0,37-L$89)) -> -0.34834142 | M87: =CORREL(OFFSET($F$88,0,0,37-M$89),OFFSET($F$88,M$89,0,37-M$89)) -> -0.52974463 | N87: =CORREL(OFFSET($F$88,0,0,37-N$89),OFFSET($F$88,N$89,0,37-N$89)) -> -0.60676963 | O87: =CORREL(OFFSET($F$88,0,0,37-O$89),OFFSET($F$88,O$89,0,37-O$89)) -> -0.60913618 | P87: =CORREL(OFFSET($F$88,0,0,37-P$89),OFFSET($F$88,P$89,0,37-P$89)) -> -0.44990589 | ... AQ87: =CORREL(OFFSET($F$88,0,0,37-AQ$89),OFFSET($F$88,AQ$89,0,37-AQ$89)) -> -1
E88: 45536 | F88: {=INDEX('Total Sales'!$J$6:$J$41,MATCH(E6,'Total Sales'!$G$6:$G$41,0))} -> 170577 | H88: ACF value | I88: =SUM(OFFSET(I91,I89,0,36-I89,1))/DEVSQ($F$88:$F$123) -> 0.68710535 | J88: =SUM(OFFSET(J91,J89,0,36-J89,1))/DEVSQ($F$88:$F$123) -> 0.23785636 | K88: =SUM(OFFSET(K91,K89,0,36-K89,1))/DEVSQ($F$88:$F$123) -> -0.095344333 | L88: =SUM(OFFSET(L91,L89,0,36-L89,1))/DEVSQ($F$88:$F$123) -> -0.31770305 | M88: =SUM(OFFSET(M91,M89,0,36-M89,1))/DEVSQ($F$88:$F$123) -> -0.4693212 | N88: =SUM(OFFSET(N91,N89,0,36-N89,1))/DEVSQ($F$88:$F$123) -> -0.53391647 | O88: =SUM(OFFSET(O91,O89,0,36-O89,1))/DEVSQ($F$88:$F$123) -> -0.53540289 | P88: =SUM(OFFSET(P91,P89,0,36-P89,1))/DEVSQ($F$88:$F$123) -> -0.38911187 | ... AQ88: =SUM(OFFSET(AQ91,AQ89,0,36-AQ89,1))/DEVSQ($F$88:$F$123) -> 0.0051708957
E89: 45505 | F89: {=INDEX('Total Sales'!$J$6:$J$41,MATCH(E7,'Total Sales'!$G$6:$G$41,0))} -> 149026 | H89: Lag | I89: 1 | J89: 2 | K89: 3 | L89: 4 | M89: 5 | N89: 6 | O89: 7 | P89: 8 | Q89: 9 | R89: 10 | S89: 11 | T89: 12 | U89: 13 | V89: 14 | W89: 15 | X89: 16 | Y89: 17 | Z89: 18 | AA89: 19 | AB89: 20 | AC89: 21 | AD89: 22 | AE89: 23 | AF89: 24 | AG89: 25 | AH89: 26 | AI89: 27 | AJ89: 28 | AK89: 29 | AL89: 30 | AM89: 31 | AN89: 32 | AO89: 33 | AP89: 34 | AQ89: 35
E90: 45474 | F90: {=INDEX('Total Sales'!$J$6:$J$41,MATCH(E8,'Total Sales'!$G$6:$G$41,0))} -> 139177 | H90: Counter
E91: 45444 | F91: {=INDEX('Total Sales'!$J$6:$J$41,MATCH(E9,'Total Sales'!$G$6:$G$41,0))} -> 154104 | H91: 1 | I91: =IF($H91>I$89,($F88-$F$124)*(OFFSET($F88,-I$89,0)-$F$124),"") | J91: =IF($H91>J$89,($F88-$F$124)*(OFFSET($F88,-J$89,0)-$F$124),"") | K91: =IF($H91>K$89,($F88-$F$124)*(OFFSET($F88,-K$89,0)-$F$124),"") | L91: =IF($H91>L$89,($F88-$F$124)*(OFFSET($F88,-L$89,0)-$F$124),"") | M91: =IF($H91>M$89,($F88-$F$124)*(OFFSET($F88,-M$89,0)-$F$124),"") | N91: =IF($H91>N$89,($F88-$F$124)*(OFFSET($F88,-N$89,0)-$F$124),"") | O91: =IF($H91>O$89,($F88-$F$124)*(OFFSET($F88,-O$89,0)-$F$124),"") | P91: =IF($H91>P$89,($F88-$F$124)*(OFFSET($F88,-P$89,0)-$F$124),"") | ... AQ91: =IF($H91>AQ$89,($F88-$F$124)*(OFFSET($F88,-AQ$89,0)-$F$124),"")
E92: 45413 | F92: {=INDEX('Total Sales'!$J$6:$J$41,MATCH(E10,'Total Sales'!$G$6:$G$41,0))} -> 180578 | H92: 2 | I92: =IF($H92>I$89,($F89-$F$124)*(OFFSET($F89,-I$89,0)-$F$124),"") -> 9.4479212e+08 | J92: =IF($H92>J$89,($F89-$F$124)*(OFFSET($F89,-J$89,0)-$F$124),"") | K92: =IF($H92>K$89,($F89-$F$124)*(OFFSET($F89,-K$89,0)-$F$124),"") | L92: =IF($H92>L$89,($F89-$F$124)*(OFFSET($F89,-L$89,0)-$F$124),"") | M92: =IF($H92>M$89,($F89-$F$124)*(OFFSET($F89,-M$89,0)-$F$124),"") | N92: =IF($H92>N$89,($F89-$F$124)*(OFFSET($F89,-N$89,0)-$F$124),"") | O92: =IF($H92>O$89,($F89-$F$124)*(OFFSET($F89,-O$89,0)-$F$124),"") | P92: =IF($H92>P$89,($F89-$F$124)*(OFFSET($F89,-P$89,0)-$F$124),"") | ... AQ92: =IF($H92>AQ$89,($F89-$F$124)*(OFFSET($F89,-AQ$89,0)-$F$124),"")
E93: 45383 | F93: {=INDEX('Total Sales'!$J$6:$J$41,MATCH(E11,'Total Sales'!$G$6:$G$41,0))} -> 162943 | H93: 3 | I93: =IF($H93>I$89,($F90-$F$124)*(OFFSET($F90,-I$89,0)-$F$124),"") -> 2.3058884e+09 | J93: =IF($H93>J$89,($F90-$F$124)*(OFFSET($F90,-J$89,0)-$F$124),"") -> 1.1594611e+09 | K93: =IF($H93>K$89,($F90-$F$124)*(OFFSET($F90,-K$89,0)-$F$124),"") | L93: =IF($H93>L$89,($F90-$F$124)*(OFFSET($F90,-L$89,0)-$F$124),"") | M93: =IF($H93>M$89,($F90-$F$124)*(OFFSET($F90,-M$89,0)-$F$124),"") | N93: =IF($H93>N$89,($F90-$F$124)*(OFFSET($F90,-N$89,0)-$F$124),"") | O93: =IF($H93>O$89,($F90-$F$124)*(OFFSET($F90,-O$89,0)-$F$124),"") | P93: =IF($H93>P$89,($F90-$F$124)*(OFFSET($F90,-P$89,0)-$F$124),"") | ... AQ93: =IF($H93>AQ$89,($F90-$F$124)*(OFFSET($F90,-AQ$89,0)-$F$124),"")
E94: 45352 | F94: {=INDEX('Total Sales'!$J$6:$J$41,MATCH(E12,'Total Sales'!$G$6:$G$41,0))} -> 181870 | H94: 4 | I94: =IF($H94>I$89,($F91-$F$124)*(OFFSET($F91,-I$89,0)-$F$124),"") -> 2.035759e+09 | J94: =IF($H94>J$89,($F91-$F$124)*(OFFSET($F91,-J$89,0)-$F$124),"") -> 1.6588475e+09 | K94: =IF($H94>K$89,($F91-$F$124)*(OFFSET($F91,-K$89,0)-$F$124),"") -> 8.3411196e+08 | L94: =IF($H94>L$89,($F91-$F$124)*(OFFSET($F91,-L$89,0)-$F$124),"") | M94: =IF($H94>M$89,($F91-$F$124)*(OFFSET($F91,-M$89,0)-$F$124),"") | N94: =IF($H94>N$89,($F91-$F$124)*(OFFSET($F91,-N$89,0)-$F$124),"") | O94: =IF($H94>O$89,($F91-$F$124)*(OFFSET($F91,-O$89,0)-$F$124),"") | P94: =IF($H94>P$89,($F91-$F$124)*(OFFSET($F91,-P$89,0)-$F$124),"") | ... AQ94: =IF($H94>AQ$89,($F91-$F$124)*(OFFSET($F91,-AQ$89,0)-$F$124),"")
E95: 45323 | F95: {=INDEX('Total Sales'!$J$6:$J$41,MATCH(E13,'Total Sales'!$G$6:$G$41,0))} -> 211019.5 | H95: 5 | I95: =IF($H95>I$89,($F92-$F$124)*(OFFSET($F92,-I$89,0)-$F$124),"") -> 4.5138355e+08 | J95: =IF($H95>J$89,($F92-$F$124)*(OFFSET($F92,-J$89,0)-$F$124),"") -> 6.2744772e+08 | K95: =IF($H95>K$89,($F92-$F$124)*(OFFSET($F92,-K$89,0)-$F$124),"") -> 5.1127863e+08 | L95: =IF($H95>L$89,($F92-$F$124)*(OFFSET($F92,-L$89,0)-$F$124),"") -> 2.5708429e+08 | M95: =IF($H95>M$89,($F92-$F$124)*(OFFSET($F92,-M$89,0)-$F$124),"") | N95: =IF($H95>N$89,($F92-$F$124)*(OFFSET($F92,-N$89,0)-$F$124),"") | O95: =IF($H95>O$89,($F92-$F$124)*(OFFSET($F92,-O$89,0)-$F$124),"") | P95: =IF($H95>P$89,($F92-$F$124)*(OFFSET($F92,-P$89,0)-$F$124),"") | ... AQ95: =IF($H95>AQ$89,($F92-$F$124)*(OFFSET($F92,-AQ$89,0)-$F$124),"")
E96: 45292 | F96: {=INDEX('Total Sales'!$J$6:$J$41,MATCH(E14,'Total Sales'!$G$6:$G$41,0))} -> 319780.5 | H96: 6 | I96: =IF($H96>I$89,($F93-$F$124)*(OFFSET($F93,-I$89,0)-$F$124),"") -> 3.4712742e+08 | J96: =IF($H96>J$89,($F93-$F$124)*(OFFSET($F93,-J$89,0)-$F$124),"") -> 1.1262576e+09 | K96: =IF($H96>K$89,($F93-$F$124)*(OFFSET($F93,-K$89,0)-$F$124),"") -> 1.5655594e+09 | L96: =IF($H96>L$89,($F93-$F$124)*(OFFSET($F93,-L$89,0)-$F$124),"") -> 1.2757032e+09 | M96: =IF($H96>M$89,($F93-$F$124)*(OFFSET($F93,-M$89,0)-$F$124),"") -> 6.4145699e+08 | N96: =IF($H96>N$89,($F93-$F$124)*(OFFSET($F93,-N$89,0)-$F$124),"") | O96: =IF($H96>O$89,($F93-$F$124)*(OFFSET($F93,-O$89,0)-$F$124),"") | P96: =IF($H96>P$89,($F93-$F$124)*(OFFSET($F93,-P$89,0)-$F$124),"") | ... AQ96: =IF($H96>AQ$89,($F93-$F$124)*(OFFSET($F93,-AQ$89,0)-$F$124),"")
E97: 45261 | F97: {=INDEX('Total Sales'!$J$6:$J$41,MATCH(E15,'Total Sales'!$G$6:$G$41,0))} -> 307644 | H97: 7 | I97: =IF($H97>I$89,($F94-$F$124)*(OFFSET($F94,-I$89,0)-$F$124),"") -> 3.0910384e+08 | J97: =IF($H97>J$89,($F94-$F$124)*(OFFSET($F94,-J$89,0)-$F$124),"") -> 1.2388319e+08 | K97: =IF($H97>K$89,($F94-$F$124)*(OFFSET($F94,-K$89,0)-$F$124),"") -> 4.0193998e+08 | L97: =IF($H97>L$89,($F94-$F$124)*(OFFSET($F94,-L$89,0)-$F$124),"") -> 5.5871847e+08 | M97: =IF($H97>M$89,($F94-$F$124)*(OFFSET($F94,-M$89,0)-$F$124),"") -> 4.5527429e+08 | N97: =IF($H97>N$89,($F94-$F$124)*(OFFSET($F94,-N$89,0)-$F$124),"") -> 2.2892384e+08 | O97: =IF($H97>O$89,($F94-$F$124)*(OFFSET($F94,-O$89,0)-$F$124),"") | P97: =IF($H97>P$89,($F94-$F$124)*(OFFSET($F94,-P$89,0)-$F$124),"") | ... AQ97: =IF($H97>AQ$89,($F94-$F$124)*(OFFSET($F94,-AQ$89,0)-$F$124),"")
E98: 45231 | F98: {=INDEX('Total Sales'!$J$6:$J$41,MATCH(E16,'Total Sales'!$G$6:$G$41,0))} -> 248927 | H98: 8 | I98: =IF($H98>I$89,($F95-$F$124)*(OFFSET($F95,-I$89,0)-$F$124),"") -> -1.958443e+08 | J98: =IF($H98>J$89,($F95-$F$124)*(OFFSET($F95,-J$89,0)-$F$124),"") -> -5.4876635e+08 | K98: =IF($H98>K$89,($F95-$F$124)*(OFFSET($F95,-K$89,0)-$F$124),"") -> -2.1993556e+08 | L98: =IF($H98>L$89,($F95-$F$124)*(OFFSET($F95,-L$89,0)-$F$124),"") -> -7.1358264e+08 | M98: =IF($H98>M$89,($F95-$F$124)*(OFFSET($F95,-M$89,0)-$F$124),"") -> -9.9191873e+08 | N98: =IF($H98>N$89,($F95-$F$124)*(OFFSET($F95,-N$89,0)-$F$124),"") -> -8.0826949e+08 | O98: =IF($H98>O$89,($F95-$F$124)*(OFFSET($F95,-O$89,0)-$F$124),"") -> -4.0641907e+08 | P98: =IF($H98>P$89,($F95-$F$124)*(OFFSET($F95,-P$89,0)-$F$124),"") | ... AQ98: =IF($H98>AQ$89,($F95-$F$124)*(OFFSET($F95,-AQ$89,0)-$F$124),"")
E99: 45200 | F99: {=INDEX('Total Sales'!$J$6:$J$41,MATCH(E17,'Total Sales'!$G$6:$G$41,0))} -> 194555 | H99: 9 | I99: =IF($H99>I$89,($F96-$F$124)*(OFFSET($F96,-I$89,0)-$F$124),"") -> 2.3757019e+09 | J99: =IF($H99>J$89,($F96-$F$124)*(OFFSET($F96,-J$89,0)-$F$124),"") -> -1.3381626e+09 | K99: =IF($H99>K$89,($F96-$F$124)*(OFFSET($F96,-K$89,0)-$F$124),"") -> -3.7496041e+09 | L99: =IF($H99>L$89,($F96-$F$124)*(OFFSET($F96,-L$89,0)-$F$124),"") -> -1.5027731e+09 | M99: =IF($H99>M$89,($F96-$F$124)*(OFFSET($F96,-M$89,0)-$F$124),"") -> -4.8757589e+09 | N99: =IF($H99>N$89,($F96-$F$124)*(OFFSET($F96,-N$89,0)-$F$124),"") -> -6.7775704e+09 | O99: =IF($H99>O$89,($F96-$F$124)*(OFFSET($F96,-O$89,0)-$F$124),"") -> -5.5227341e+09 | P99: =IF($H99>P$89,($F96-$F$124)*(OFFSET($F96,-P$89,0)-$F$124),"") -> -2.7769753e+09 | ... AQ99: =IF($H99>AQ$89,($F96-$F$124)*(OFFSET($F96,-AQ$89,0)-$F$124),"")
E100: 45170 | F100: {=INDEX('Total Sales'!$J$6:$J$41,MATCH(E18,'Total Sales'!$G$6:$G$41,0))} -> 174735 | H100: 10 | I100: =IF($H100>I$89,($F97-$F$124)*(OFFSET($F97,-I$89,0)-$F$124),"") -> 1.4686387e+10 | J100: =IF($H100>J$89,($F97-$F$124)*(OFFSET($F97,-J$89,0)-$F$124),"") -> 2.1493988e+09 | K100: =IF($H100>K$89,($F97-$F$124)*(OFFSET($F97,-K$89,0)-$F$124),"") -> -1.2106928e+09 | L100: =IF($H100>L$89,($F97-$F$124)*(OFFSET($F97,-L$89,0)-$F$124),"") -> -3.3924267e+09 | M100: =IF($H100>M$89,($F97-$F$124)*(OFFSET($F97,-M$89,0)-$F$124),"") -> -1.3596229e+09 | N100: =IF($H100>N$89,($F97-$F$124)*(OFFSET($F97,-N$89,0)-$F$124),"") -> -4.411307e+09 | O100: =IF($H100>O$89,($F97-$F$124)*(OFFSET($F97,-O$89,0)-$F$124),"") -> -6.131957e+09 | P100: =IF($H100>P$89,($F97-$F$124)*(OFFSET($F97,-P$89,0)-$F$124),"") -> -4.996653e+09 | ... AQ100: =IF($H100>AQ$89,($F97-$F$124)*(OFFSET($F97,-AQ$89,0)-$F$124),"")
E101: 45139 | F101: {=INDEX('Total Sales'!$J$6:$J$41,MATCH(E19,'Total Sales'!$G$6:$G$41,0))} -> 142076 | H101: 11 | I101: =IF($H101>I$89,($F98-$F$124)*(OFFSET($F98,-I$89,0)-$F$124),"") -> 6.5190337e+09 | J101: =IF($H101>J$89,($F98-$F$124)*(OFFSET($F98,-J$89,0)-$F$124),"") -> 7.2054012e+09 | K101: =IF($H101>K$89,($F98-$F$124)*(OFFSET($F98,-K$89,0)-$F$124),"") -> 1.0545331e+09 | L101: =IF($H101>L$89,($F98-$F$124)*(OFFSET($F98,-L$89,0)-$F$124),"") -> -5.939873e+08 | M101: =IF($H101>M$89,($F98-$F$124)*(OFFSET($F98,-M$89,0)-$F$124),"") -> -1.6643846e+09 | N101: =IF($H101>N$89,($F98-$F$124)*(OFFSET($F98,-N$89,0)-$F$124),"") -> -6.6705505e+08 | O101: =IF($H101>O$89,($F98-$F$124)*(OFFSET($F98,-O$89,0)-$F$124),"") -> -2.1642653e+09 | P101: =IF($H101>P$89,($F98-$F$124)*(OFFSET($F98,-P$89,0)-$F$124),"") -> -3.0084466e+09 | ... AQ101: =IF($H101>AQ$89,($F98-$F$124)*(OFFSET($F98,-AQ$89,0)-$F$124),"")
E102: 45108 | F102: {=INDEX('Total Sales'!$J$6:$J$41,MATCH(E20,'Total Sales'!$G$6:$G$41,0))} -> 117214 | H102: 12 | I102: =IF($H102>I$89,($F99-$F$124)*(OFFSET($F99,-I$89,0)-$F$124),"") -> 1.2340001e+08 | J102: =IF($H102>J$89,($F99-$F$124)*(OFFSET($F99,-J$89,0)-$F$124),"") -> 2.5151969e+08 | K102: =IF($H102>K$89,($F99-$F$124)*(OFFSET($F99,-K$89,0)-$F$124),"") -> 2.7800137e+08 | L102: =IF($H102>L$89,($F99-$F$124)*(OFFSET($F99,-L$89,0)-$F$124),"") -> 40686374 | M102: =IF($H102>M$89,($F99-$F$124)*(OFFSET($F99,-M$89,0)-$F$124),"") -> -22917430 | N102: =IF($H102>N$89,($F99-$F$124)*(OFFSET($F99,-N$89,0)-$F$124),"") -> -64215882 | O102: =IF($H102>O$89,($F99-$F$124)*(OFFSET($F99,-O$89,0)-$F$124),"") -> -25736556 | P102: =IF($H102>P$89,($F99-$F$124)*(OFFSET($F99,-P$89,0)-$F$124),"") -> -83502457 | ... AQ102: =IF($H102>AQ$89,($F99-$F$124)*(OFFSET($F99,-AQ$89,0)-$F$124),"")
... E123: 44470 | F123: {=INDEX('Total Sales'!$J$6:$J$41,MATCH(E41,'Total Sales'!$G$6:$G$41,0))} -> 164732 | H123: 33 | I123: =IF($H123>I$89,($F120-$F$124)*(OFFSET($F120,-I$89,0)-$F$124),"") -> -1.2059431e+09 | J123: =IF($H123>J$89,($F120-$F$124)*(OFFSET($F120,-J$89,0)-$F$124),"") -> -7.8290682e+08 | K123: =IF($H123>K$89,($F120-$F$124)*(OFFSET($F120,-K$89,0)-$F$124),"") -> -3.9317114e+09 | L123: =IF($H123>L$89,($F120-$F$124)*(OFFSET($F120,-L$89,0)-$F$124),"") -> -2.7715381e+09 | M123: =IF($H123>M$89,($F120-$F$124)*(OFFSET($F120,-M$89,0)-$F$124),"") -> -2.8671905e+09 | N123: =IF($H123>N$89,($F120-$F$124)*(OFFSET($F120,-N$89,0)-$F$124),"") -> -5.4396985e+09 | O123: =IF($H123>O$89,($F120-$F$124)*(OFFSET($F120,-O$89,0)-$F$124),"") -> -4.0680793e+09 | P123: =IF($H123>P$89,($F120-$F$124)*(OFFSET($F120,-P$89,0)-$F$124),"") -> -1.4049722e+09 | ... AQ123: =IF($H123>AQ$89,($F120-$F$124)*(OFFSET($F120,-AQ$89,0)-$F$124),"")
E124: Mean | F124: =AVERAGE(F88:F123) -> 192373.01 | H124: 34 | I124: =IF($H124>I$89,($F121-$F$124)*(OFFSET($F121,-I$89,0)-$F$124),"") -> 8.4549848e+09 | J124: =IF($H124>J$89,($F121-$F$124)*(OFFSET($F121,-J$89,0)-$F$124),"") -> -1.9564993e+09 | K124: =IF($H124>K$89,($F121-$F$124)*(OFFSET($F121,-K$89,0)-$F$124),"") -> -1.2701733e+09 | L124: =IF($H124>L$89,($F121-$F$124)*(OFFSET($F121,-L$89,0)-$F$124),"") -> -6.3787347e+09 | M124: =IF($H124>M$89,($F121-$F$124)*(OFFSET($F121,-M$89,0)-$F$124),"") -> -4.4964913e+09 | N124: =IF($H124>N$89,($F121-$F$124)*(OFFSET($F121,-N$89,0)-$F$124),"") -> -4.651676e+09 | O124: =IF($H124>O$89,($F121-$F$124)*(OFFSET($F121,-O$89,0)-$F$124),"") -> -8.8252645e+09 | P124: =IF($H124>P$89,($F121-$F$124)*(OFFSET($F121,-P$89,0)-$F$124),"") -> -6.5999753e+09 | ... AQ124: =IF($H124>AQ$89,($F121-$F$124)*(OFFSET($F121,-AQ$89,0)-$F$124),"")
H125: 35 | I125: =IF($H125>I$89,($F122-$F$124)*(OFFSET($F122,-I$89,0)-$F$124),"") -> 4.3813001e+09 | J125: =IF($H125>J$89,($F122-$F$124)*(OFFSET($F122,-J$89,0)-$F$124),"") -> 2.7005368e+09 | K125: =IF($H125>K$89,($F122-$F$124)*(OFFSET($F122,-K$89,0)-$F$124),"") -> -6.2490928e+08 | L125: =IF($H125>L$89,($F122-$F$124)*(OFFSET($F122,-L$89,0)-$F$124),"") -> -4.0569555e+08 | M125: =IF($H125>M$89,($F122-$F$124)*(OFFSET($F122,-M$89,0)-$F$124),"") -> -2.0373789e+09 | N125: =IF($H125>N$89,($F122-$F$124)*(OFFSET($F122,-N$89,0)-$F$124),"") -> -1.4361871e+09 | O125: =IF($H125>O$89,($F122-$F$124)*(OFFSET($F122,-O$89,0)-$F$124),"") -> -1.4857534e+09 | P125: =IF($H125>P$89,($F122-$F$124)*(OFFSET($F122,-P$89,0)-$F$124),"") -> -2.8188048e+09 | ... AQ125: =IF($H125>AQ$89,($F122-$F$124)*(OFFSET($F122,-AQ$89,0)-$F$124),"")
H126: 36 | I126: =IF($H126>I$89,($F123-$F$124)*(OFFSET($F123,-I$89,0)-$F$124),"") -> -1.0340085e+09 | J126: =IF($H126>J$89,($F123-$F$124)*(OFFSET($F123,-J$89,0)-$F$124),"") -> -3.237329e+09 | K126: =IF($H126>K$89,($F123-$F$124)*(OFFSET($F123,-K$89,0)-$F$124),"") -> -1.9954182e+09 | L126: =IF($H126>L$89,($F123-$F$124)*(OFFSET($F123,-L$89,0)-$F$124),"") -> 4.6174352e+08 | M126: =IF($H126>M$89,($F123-$F$124)*(OFFSET($F123,-M$89,0)-$F$124),"") -> 2.9976718e+08 | N126: =IF($H126>N$89,($F123-$F$124)*(OFFSET($F123,-N$89,0)-$F$124),"") -> 1.5054129e+09 | O126: =IF($H126>O$89,($F123-$F$124)*(OFFSET($F123,-O$89,0)-$F$124),"") -> 1.0611942e+09 | P126: =IF($H126>P$89,($F123-$F$124)*(OFFSET($F123,-P$89,0)-$F$124),"") -> 1.0978185e+09 | ... AQ126: =IF($H126>AQ$89,($F123-$F$124)*(OFFSET($F123,-AQ$89,0)-$F$124),"") -> 6.0246392e+08

Sheet Forecast Validation
A1: Assumptions
C2: Forecast Initialisation and Model Validation
X3: w_-2 | Y3: 0.15 | Z3: alpha | AA3: 0
X4: w_-1 | Y4: 0.35 | Z4: beta | AA4: 0.0015768938
X5: w_0 | Y5: 0.5 | Z5: gamma | AA5: 0.8
Z8: base initial | AA8: trend initial
Z9: =X24 -> 196358.41 | AA9: =T12 -> 788.99923
P10: Holt's Linear Trend Model | S10: [a;m] Forecast Initialisation | AG10: Model for forecast validation (cycle 3) | AL10: Actual forecasting and model validation (cycle 3) | AT10: Plots of ACF vs CC, Cycling Moving Average, and Forecast Initialisation
I11: Month | J11: Monthly Sales WH1000-MX5 Total | K11: Lag | L11: Cross Correlation | M11: Autocorrelation Function | N11: MA Basic | O11: MA Centered | P11: Level | Q11: Trend | R11: Seasonality | S11: Cycle (c) | T11: Trend Initial (T0) | U11: Cycle Avg (Yc) | V11: Deseasonalised Sales (Ỹ) | W11: Seasonality Initial (S0) | X11: Base Initial (B0) | Y11: Weighted S0 (Sw) | Z11: Base (B') | AA11: Trend (T') | AB11: Seasonality (S') | AC11: Forecast (F') | AD11: APE' | AE11: MAPE' (whole data h = 1) | AG11: Base | AH11: Trend | AI11: Seasonality | AJ11: Calendar Month | AL11: Conseq. month # | AM11: Month | AN11: Monthly Sales WH1000-MX5 | AO11: Forecast F_t | AP11: h | AQ11: APE
I12: ='Total Sales'!G41 -> 44470 | J12: ='Total Sales'!J41 -> 164732 | K12: ='(ACF Helper)'!H9 -> 1 | L12: {=TRANSPOSE('(ACF Helper)'!I87:AQ87)} -> 0.68854963 | M12: {=TRANSPOSE('(ACF Helper)'!I88:AQ88)} -> 0.68710535 | P12: =AVERAGE(J12:J47) -> 192373.01 | Q12: -167 | R12: =P12+Q12 -> 192206.01 | S12: 12 | T12: =SLOPE(O18:O41,K18:K41) -> 788.99923 | U12: =AVERAGE(J12:J23) -> 183022.21 | V12: =$U$12+$T$12*(K12-1-11/2) -> 178682.71 | W12: =J12/V12 -> 0.92192467 | Z12: =$AA$3*J12/Y36 + (1-$AA$4)*(Z9+AA9) -> 196836.53 | AA12: =$AA$4*(Z12-Z9)+(1-$AA$4)*AA9 -> 788.509 | AB12: =$AA$5*J12/Z12+(1-$AA$5)*Y36 -> 0.86087451 | AC12: =(Z9+AA9)*Y36 -> 188627.21 | AD12: =ABS((J12-AC12)/J12) -> 0.14505506 | AE12: =AVERAGE(AD12:AD47) -> 0.061067596 | AG12: =Z36 -> 207940.17 | AH12: =AA36 -> 776.39438 | AI12: =AVERAGE(AB12,AB24,AB36) -> 0.8818105 | AJ12: =MONTH(I12) -> 10 | AL12: 1 | AM12: 44470 | AN12: =J12 -> 164732 | AO12: =AC12 -> 188627.21 | AP12: 1 | AQ12: =ABS((AN12-AO12)/AN12) -> 0.14505506 | AR12: Model training h = 1
I13: ='Total Sales'!G40 -> 44501 | J13: ='Total Sales'!J40 -> 229781.5 | K13: ='(ACF Helper)'!H10 -> 2 | L13: 0.24079109 | M13: 0.23785636 | P13: =$P$3*J13+(1-$P$3)*(P12+Q12) -> 192206.01 | Q13: =$P$4*(P13-P12)+(1-$P$4)*Q12 -> -167 | R13: =P13+Q13 -> 192039.01 | V13: =$U$12+$T$12*(K13-1-11/2) -> 179471.71 | W13: =J13/V13 -> 1.2803215 | Z13: =$AA$3*J13/IF(Y37=0,AB1,Y37) + (1-$AA$4)*(Z12+AA12) -> 197313.41 | AA13: =$AA$4*(Z13-Z12)+(1-$AA$4)*AA12 -> 788.01759 | AB13: =$AA$5*J13/Z13+(1-$AA$5)*IF(Y37=0,AB1,Y37) -> 1.1861494 | AC13: =(Z12+AA12)*IF(Y37=0,AB1,Y37) -> 251486.42 | AD13: =ABS((J13-AC13)/J13) -> 0.094458962 | AI13: =AVERAGE(AB13,AB25,AB37) -> 1.1936782 | AJ13: =MONTH(I13) -> 11 | AL13: 2 | AM13: 44501 | AN13: =J13 -> 229781.5 | AO13: =AC13 -> 251486.42 | AP13: 1 | AQ13: =ABS((AN13-AO13)/AN13) -> 0.094458962
I14: ='Total Sales'!G39 -> 44531 | J14: ='Total Sales'!J39 -> 309493.5 | K14: ='(ACF Helper)'!H11 -> 3 | L14: -0.098339256 | M14: -0.095344333 | P14: =$P$3*J14+(1-$P$3)*(P13+Q13) -> 192039.01 | Q14: =$P$4*(P14-P13)+(1-$P$4)*Q13 -> -167 | R14: =P14+Q14 -> 191872.01 | V14: =$U$12+$T$12*(K14-1-11/2) -> 180260.71 | W14: =J14/V14 -> 1.7169216 | Z14: =$AA$3*J14/IF(Y38=0,AB2,Y38) + (1-$AA$4)*(Z13+AA13) -> 197789.04 | AA14: =$AA$4*(Z14-Z13)+(1-$AA$4)*AA13 -> 787.52499 | AB14: =$AA$5*J14/Z14+(1-$AA$5)*IF(Y38=0,AB2,Y38) -> 1.5694475 | AC14: =(Z13+AA13)*IF(Y38=0,AB2,Y38) -> 314619.64 | AD14: =ABS((J14-AC14)/J14) -> 0.016563012 | AI14: =AVERAGE(AB14,AB26,AB38) -> 1.5166872 | AJ14: =MONTH(I14) -> 12 | AL14: 3 | AM14: 44531 | AN14: =J14 -> 309493.5 | AO14: =AC14 -> 314619.64 | AP14: 1 | AQ14: =ABS((AN14-AO14)/AN14) -> 0.016563012
I15: ='Total Sales'!G38 -> 44562 | J15: ='Total Sales'!J38 -> 264563.5 | K15: ='(ACF Helper)'!H12 -> 4 | L15: -0.34834142 | M15: -0.31770305 | P15: =$P$3*J15+(1-$P$3)*(P14+Q14) -> 191872.01 | Q15: =$P$4*(P15-P14)+(1-$P$4)*Q14 -> -167 | R15: =P15+Q15 -> 191705.01 | V15: =$U$12+$T$12*(K15-1-11/2) -> 181049.71 | W15: =J15/V15 -> 1.4612755 | Z15: =$AA$3*J15/IF(Y39=0,AB3,Y39) + (1-$AA$4)*(Z14+AA14) -> 198263.43 | AA15: =$AA$4*(Z15-Z14)+(1-$AA$4)*AA14 -> 787.03121 | AB15: =$AA$5*J15/Z15+(1-$AA$5)*IF(Y39=0,AB3,Y39) -> 1.3804764 | AC15: =(Z14+AA14)*IF(Y39=0,AB3,Y39) -> 310725.92 | AD15: =ABS((J15-AC15)/J15) -> 0.1744852 | AI15: =AVERAGE(AB15,AB27,AB39) -> 1.4435262 | AJ15: =MONTH(I15) -> 1 | AL15: 4 | AM15: 44562 | AN15: =J15 -> 264563.5 | AO15: =AC15 -> 310725.92 | AP15: 1 | AQ15: =ABS((AN15-AO15)/AN15) -> 0.1744852
I16: ='Total Sales'!G37 -> 44593 | J16: ='Total Sales'!J37 -> 175668 | K16: ='(ACF Helper)'!H13 -> 5 | L16: -0.52974463 | M16: -0.4693212 | P16: =$P$3*J16+(1-$P$3)*(P15+Q15) -> 191705.01 | Q16: =$P$4*(P16-P15)+(1-$P$4)*Q15 -> -167 | R16: =P16+Q16 -> 191538.01 | V16: =$U$12+$T$12*(K16-1-11/2) -> 181838.71 | W16: =J16/V16 -> 0.96606493 | Z16: =$AA$3*J16/IF(Y40=0,AB4,Y40) + (1-$AA$4)*(Z15+AA15) -> 198736.58 | AA16: =$AA$4*(Z16-Z15)+(1-$AA$4)*AA15 -> 786.53626 | AB16: =$AA$5*J16/Z16+(1-$AA$5)*IF(Y40=0,AB4,Y40) -> 0.91575924 | AC16: =(Z15+AA15)*IF(Y40=0,AB4,Y40) -> 207629.71 | AD16: =ABS((J16-AC16)/J16) -> 0.18194384 | AI16: =AVERAGE(AB16,AB28,AB40) -> 0.96512191 | AJ16: =MONTH(I16) -> 2 | AL16: 5 | AM16: 44593 | AN16: =J16 -> 175668 | AO16: =AC16 -> 207629.71 | AP16: 1 | AQ16: =ABS((AN16-AO16)/AN16) -> 0.18194384
I17: ='Total Sales'!G36 -> 44621 | J17: ='Total Sales'!J36 -> 181528 | K17: ='(ACF Helper)'!H14 -> 6 | L17: -0.60676963 | M17: -0.53391647 | P17: =$P$3*J17+(1-$P$3)*(P16+Q16) -> 191538.01 | Q17: =$P$4*(P17-P16)+(1-$P$4)*Q16 -> -167 | R17: =P17+Q17 -> 191371.01 | V17: =$U$12+$T$12*(K17-1-11/2) -> 182627.71 | W17: =J17/V17 -> 0.99397841 | Z17: =$AA$3*J17/IF(Y41=0,AB5,Y41) + (1-$AA$4)*(Z16+AA16) -> 199208.49 | AA17: =$AA$4*(Z17-Z16)+(1-$AA$4)*AA16 -> 786.04012 | AB17: =$AA$5*J17/Z17+(1-$AA$5)*IF(Y41=0,AB5,Y41) -> 0.91631546 | AC17: =(Z16+AA16)*IF(Y41=0,AB5,Y41) -> 186871.77 | AD17: =ABS((J17-AC17)/J17) -> 0.029437741 | AI17: =AVERAGE(AB17,AB29,AB41) -> 0.89734286 | AJ17: =MONTH(I17) -> 3 | AL17: 6 | AM17: 44621 | AN17: =J17 -> 181528 | AO17: =AC17 -> 186871.77 | AP17: 1 | AQ17: =ABS((AN17-AO17)/AN17) -> 0.029437741
I18: ='Total Sales'!G35 -> 44652 | J18: ='Total Sales'!J35 -> 137910 | K18: ='(ACF Helper)'!H15 -> 7 | L18: -0.60913618 | M18: -0.53540289 | N18: =SUM(J12:J23)/12 -> 183022.21 | O18: =(J12/24) + (J24/24) + SUM(J13:J23)/12 -> 183447.58 | P18: =$P$3*J18+(1-$P$3)*(P17+Q17) -> 191371.01 | Q18: =$P$4*(P18-P17)+(1-$P$4)*Q17 -> -167 | R18: =P18+Q18 -> 191204.01 | V18: =$U$12+$T$12*(K18-1-11/2) -> 183416.71 | W18: =J18/V18 -> 0.75189442 | Z18: =$AA$3*J18/IF(Y42=0,AB6,Y42) + (1-$AA$4)*(Z17+AA17) -> 199679.16 | AA18: =$AA$4*(Z18-Z17)+(1-$AA$4)*AA17 -> 785.54282 | AB18: =$AA$5*J18/Z18+(1-$AA$5)*IF(Y42=0,AB6,Y42) -> 0.70577542 | AC18: =(Z17+AA17)*IF(Y42=0,AB6,Y42) -> 153244.86 | AD18: =ABS((J18-AC18)/J18) -> 0.11119472 | AI18: =AVERAGE(AB18,AB30,AB42) -> 0.71302425 | AJ18: =MONTH(I18) -> 4 | AL18: 7 | AM18: 44652 | AN18: =J18 -> 137910 | AO18: =AC18 -> 153244.86 | AP18: 1 | AQ18: =ABS((AN18-AO18)/AN18) -> 0.11119472
I19: ='Total Sales'!G34 -> 44682 | J19: ='Total Sales'!J34 -> 153981 | K19: ='(ACF Helper)'!H16 -> 8 | L19: -0.44990589 | M19: -0.38911187 | N19: =SUM(J13:J24)/12 -> 183872.96 | O19: =(J13/24) + (J25/24) + SUM(J14:J24)/12 -> 184468.4 | P19: =$P$3*J19+(1-$P$3)*(P18+Q18) -> 191204.01 | Q19: =$P$4*(P19-P18)+(1-$P$4)*Q18 -> -167 | R19: =P19+Q19 -> 191037.01 | V19: =$U$12+$T$12*(K19-1-11/2) -> 184205.71 | W19: =J19/V19 -> 0.83591873 | Z19: =$AA$3*J19/IF(Y43=0,AB7,Y43) + (1-$AA$4)*(Z18+AA18) -> 200148.59 | AA19: =$AA$4*(Z19-Z18)+(1-$AA$4)*AA18 -> 785.04434 | AB19: =$AA$5*J19/Z19+(1-$AA$5)*IF(Y43=0,AB7,Y43) -> 0.79160378 | AC19: =(Z18+AA18)*IF(Y43=0,AB7,Y43) -> 176546.3 | AD19: =ABS((J19-AC19)/J19) -> 0.14654598 | AI19: =AVERAGE(AB19,AB31,AB43) -> 0.82233655 | AJ19: =MONTH(I19) -> 5 | AL19: 8 | AM19: 44682 | AN19: =J19 -> 153981 | AO19: =AC19 -> 176546.3 | AP19: 1 | AQ19: =ABS((AN19-AO19)/AN19) -> 0.14654598
I20: ='Total Sales'!G33 -> 44713 | J20: ='Total Sales'!J33 -> 152656 | K20: ='(ACF Helper)'!H17 -> 9 | L20: -0.18893006 | M20: -0.14937355 | N20: =SUM(J14:J25)/12 -> 185063.83 | O20: =(J14/24) + (J26/24) + SUM(J15:J25)/12 -> 184752.08 | P20: =$P$3*J20+(1-$P$3)*(P19+Q19) -> 191037.01 | Q20: =$P$4*(P20-P19)+(1-$P$4)*Q19 -> -167 | R20: =P20+Q20 -> 190870.01 | V20: =$U$12+$T$12*(K20-1-11/2) -> 184994.71 | W20: =J20/V20 -> 0.82519118 | Z20: =$AA$3*J20/IF(Y44=0,AB8,Y44) + (1-$AA$4)*(Z19+AA19) -> 200616.78 | AA20: =$AA$4*(Z20-Z19)+(1-$AA$4)*AA19 -> 784.5447 | AB20: =$AA$5*J20/Z20+(1-$AA$5)*IF(Y44=0,AB8,Y44) -> 0.76696393 | AC20: =(Z19+AA19)*IF(Y44=0,AB8,Y44) -> 158955.84 | AD20: =ABS((J20-AC20)/J20) -> 0.041268237 | AI20: =AVERAGE(AB20,AB32,AB44) -> 0.7604584 | AJ20: =MONTH(I20) -> 6 | AL20: 9 | AM20: 44713 | AN20: =J20 -> 152656 | AO20: =AC20 -> 158955.84 | AP20: 1 | AQ20: =ABS((AN20-AO20)/AN20) -> 0.041268237
I21: ='Total Sales'!G32 -> 44743 | J21: ='Total Sales'!J32 -> 117021 | K21: ='(ACF Helper)'!H18 -> 10 | L21: 0.17992116 | M21: 0.12992058 | N21: =SUM(J15:J26)/12 -> 184440.33 | O21: =(J15/24) + (J27/24) + SUM(J16:J26)/12 -> 185772.08 | P21: =$P$3*J21+(1-$P$3)*(P20+Q20) -> 190870.01 | Q21: =$P$4*(P21-P20)+(1-$P$4)*Q20 -> -167 | R21: =P21+Q21 -> 190703.01 | V21: =$U$12+$T$12*(K21-1-11/2) -> 185783.71 | W21: =J21/V21 -> 0.62987763 | Z21: =$AA$3*J21/IF(Y45=0,AB9,Y45) + (1-$AA$4)*(Z20+AA20) -> 201083.74 | AA21: =$AA$4*(Z21-Z20)+(1-$AA$4)*AA20 -> 784.0439 | AB21: =$AA$5*J21/Z21+(1-$AA$5)*IF(Y45=0,AB9,Y45) -> 0.59457225 | AC21: =(Z20+AA20)*IF(Y45=0,AB9,Y45) -> 129914.92 | AD21: =ABS((J21-AC21)/J21) -> 0.11018471 | AI21: =AVERAGE(AB21,AB33,AB45) -> 0.6024458 | AJ21: =MONTH(I21) -> 7 | AL21: 10 | AM21: 44743 | AN21: =J21 -> 117021 | AO21: =AC21 -> 129914.92 | AP21: 1 | AQ21: =ABS((AN21-AO21)/AN21) -> 0.11018471
I22: ='Total Sales'!G31 -> 44774 | J22: ='Total Sales'!J31 -> 136021 | K22: ='(ACF Helper)'!H19 -> 11 | L22: 0.64207178 | M22: 0.43483821 | N22: =SUM(J16:J27)/12 -> 187103.83 | O22: =(J16/24) + (J28/24) + SUM(J17:J27)/12 -> 188252.12 | P22: =$P$3*J22+(1-$P$3)*(P21+Q21) -> 190703.01 | Q22: =$P$4*(P22-P21)+(1-$P$4)*Q21 -> -167 | R22: =P22+Q22 -> 190536.01 | V22: =$U$12+$T$12*(K22-1-11/2) -> 186572.7 | W22: =J22/V22 -> 0.72905091 | Z22: =$AA$3*J22/IF(Y46=0,AB10,Y46) + (1-$AA$4)*(Z21+AA21) -> 201549.46 | AA22: =$AA$4*(Z22-Z21)+(1-$AA$4)*AA21 -> 783.54194 | AB22: =$AA$5*J22/Z22+(1-$AA$5)*IF(Y46=0,AB10,Y46) -> 0.68513628 | AC22: =(Z21+AA21)*IF(Y46=0,AB10,Y46) -> 146591.39 | AD22: =ABS((J22-AC22)/J22) -> 0.077711488 | AI22: =AVERAGE(AB22,AB34,AB46) -> 0.6899177 | AJ22: =MONTH(I22) -> 8 | AL22: 11 | AM22: 44774 | AN22: =J22 -> 136021 | AO22: =AC22 -> 146591.39 | AP22: 1 | AQ22: =ABS((AN22-AO22)/AN22) -> 0.077711488
I23: ='Total Sales'!G30 -> 44805 | J23: ='Total Sales'!J30 -> 172911 | K23: ='(ACF Helper)'!H20 -> 12 | L23: 0.97711038 | M23: 0.6460316 | N23: =SUM(J17:J28)/12 -> 189400.42 | O23: =(J17/24) + (J29/24) + SUM(J18:J28)/12 -> 189511.38 | P23: =$P$3*J23+(1-$P$3)*(P22+Q22) -> 190536.01 | Q23: =$P$4*(P23-P22)+(1-$P$4)*Q22 -> -167 | R23: =P23+Q23 -> 190369.01 | V23: =$U$12+$T$12*(K23-1-11/2) -> 187361.7 | W23: =J23/V23 -> 0.92287269 | Z23: =$AA$3*J23/IF(Y47=0,AB11,Y47) + (1-$AA$4)*(Z22+AA22) -> 202013.94 | AA23: =$AA$4*(Z23-Z22)+(1-$AA$4)*AA22 -> 783.03882 | AB23: =$AA$5*J23/Z23+(1-$AA$5)*IF(Y47=0,AB11,Y47) -> 0.85739666 | AC23: =(Z22+AA22)*IF(Y47=0,AB11,Y47) -> 174661.83 | AD23: =ABS((J23-AC23)/J23) -> 0.010125622 | AI23: =AVERAGE(AB23,AB35,AB47) -> 0.83763496 | AJ23: =MONTH(I23) -> 9 | AL23: 12 | AM23: 44805 | AN23: =J23 -> 172911 | AO23: =AC23 -> 174661.83 | AP23: 1 | AQ23: =ABS((AN23-AO23)/AN23) -> 0.010125622
I24: ='Total Sales'!G29 -> 44835 | J24: ='Total Sales'!J29 -> 174941 | K24: ='(ACF Helper)'!H21 -> 13 | L24: 0.71866152 | M24: 0.47174563 | N24: =SUM(J18:J29)/12 -> 189622.33 | O24: =(J18/24) + (J30/24) + SUM(J19:J29)/12 -> 189621.12 | P24: =$P$3*J24+(1-$P$3)*(P23+Q23) -> 190369.01 | Q24: =$P$4*(P24-P23)+(1-$P$4)*Q23 -> -167 | R24: =P24+Q24 -> 190202.01 | U24: =AVERAGE(J24:J35) -> 192413.42 | V24: =$U$24+$T$12*(K24-13-11/2) -> 188073.92 | W24: =J24/V24 -> 0.93017149 | X24: =U24+((S12-2)/2)*T12 -> 196358.41 | Z24: =$AA$3*J24/IF(Y48=0,AB12,Y48) + (1-$AA$4)*(Z23+AA23) -> 202477.19 | AA24: =$AA$4*(Z24-Z23)+(1-$AA$4)*AA23 -> 782.53454 | AB24: =$AA$5*J24/Z24+(1-$AA$5)*IF(Y48=0,AB12,Y48) -> 0.86337769 | AC24: =(Z23+AA23)*IF(Y48=0,AB12,Y48) -> 174582.75 | AD24: =ABS((J24-AC24)/J24) -> 0.0020478112 | AL24: 13 | AM24: 44835 | AN24: =J24 -> 174941 | AO24: =AC24 -> 174582.75 | AP24: 1 | AQ24: =ABS((AN24-AO24)/AN24) -> 0.0020478112
I25: ='Total Sales'!G28 -> 44866 | J25: ='Total Sales'!J28 -> 244072 | K25: ='(ACF Helper)'!H22 -> 14 | L25: 0.27970477 | M25: 0.17957773 | N25: =SUM(J19:J30)/12 -> 189619.92 | O25: =(J19/24) + (J31/24) + SUM(J20:J30)/12 -> 190354.04 | P25: =$P$3*J25+(1-$P$3)*(P24+Q24) -> 190202.01 | Q25: =$P$4*(P25-P24)+(1-$P$4)*Q24 -> -167 | R25: =P25+Q25 -> 190035.01 | V25: =$U$24+$T$12*(K25-13-11/2) -> 188862.92 | W25: =J25/V25 -> 1.2923236 | Z25: =$AA$3*J25/IF(Y49=0,AB13,Y49) + (1-$AA$4)*(Z24+AA24) -> 202939.21 | AA25: =$AA$4*(Z25-Z24)+(1-$AA$4)*AA24 -> 782.02912 | AB25: =$AA$5*J25/Z25+(1-$AA$5)*IF(Y49=0,AB13,Y49) -> 1.1993781 | AC25: =(Z24+AA24)*IF(Y49=0,AB13,Y49) -> 241096.4 | AD25: =ABS((J25-AC25)/J25) -> 0.012191498 | AG25: Results of forecast validation (cycle 3) | AL25: 14 | AM25: 44866 | AN25: =J25 -> 244072 | AO25: =AC25 -> 241096.4 | AP25: 1 | AQ25: =ABS((AN25-AO25)/AN25) -> 0.012191498
I26: ='Total Sales'!G27 -> 44896 | J26: ='Total Sales'!J27 -> 302011.5 | K26: ='(ACF Helper)'!H23 -> 15 | L26: -0.08995227 | M26: -0.05438453 | N26: =SUM(J20:J31)/12 -> 191088.17 | O26: =(J20/24) + (J32/24) + SUM(J21:J31)/12 -> 191414.46 | P26: =$P$3*J26+(1-$P$3)*(P25+Q25) -> 190035.01 | Q26: =$P$4*(P26-P25)+(1-$P$4)*Q25 -> -167 | R26: =P26+Q26 -> 189868.01 | V26: =$U$24+$T$12*(K26-13-11/2) -> 189651.92 | W26: =J26/V26 -> 1.5924516 | Z26: =$AA$3*J26/IF(Y50=0,AB14,Y50) + (1-$AA$4)*(Z25+AA25) -> 203399.99 | AA26: =$AA$4*(Z26-Z25)+(1-$AA$4)*AA25 -> 781.52255 | AB26: =$AA$5*J26/Z26+(1-$AA$5)*IF(Y50=0,AB14,Y50) -> 1.501742 | AC26: =(Z25+AA25)*IF(Y50=0,AB14,Y50) -> 319729.78 | AD26: =ABS((J26-AC26)/J26) -> 0.058667565 | AG26: MAPE on validation | AI26: =AVERAGE(AQ36:AQ47) -> 0.042476496 | AL26: 15 | AM26: 44896 | AN26: =J26 -> 302011.5 | AO26: =AC26 -> 319729.78 | AP26: 1 | AQ26: =ABS((AN26-AO26)/AN26) -> 0.058667565
I27: ='Total Sales'!G26 -> 44927 | J27: ='Total Sales'!J26 -> 296525.5 | K27: ='(ACF Helper)'!H24 -> 16 | L27: -0.29747714 | M27: -0.16767186 | N27: =SUM(J21:J32)/12 -> 191740.75 | O27: =(J21/24) + (J33/24) + SUM(J22:J32)/12 -> 191748.79 | P27: =$P$3*J27+(1-$P$3)*(P26+Q26) -> 189868.01 | Q27: =$P$4*(P27-P26)+(1-$P$4)*Q26 -> -167 | R27: =P27+Q27 -> 189701.01 | V27: =$U$24+$T$12*(K27-13-11/2) -> 190440.92 | W27: =J27/V27 -> 1.5570472 | Z27: =$AA$3*J27/IF(Y51=0,AB15,Y51) + (1-$AA$4)*(Z26+AA26) -> 203859.54 | AA27: =$AA$4*(Z27-Z26)+(1-$AA$4)*AA26 -> 781.01483 | AB27: =$AA$5*J27/Z27+(1-$AA$5)*IF(Y51=0,AB15,Y51) -> 1.4397416 | AC27: =(Z26+AA26)*IF(Y51=0,AB15,Y51) -> 281867.76 | AD27: =ABS((J27-AC27)/J27) -> 0.049431627 | AG27: Shifted MAPE | AI27: =AVERAGE(AQ31:AQ42) -> 0.035106978 | AL27: 16 | AM27: 44927 | AN27: =J27 -> 296525.5 | AO27: =AC27 -> 281867.76 | AP27: 1 | AQ27: =ABS((AN27-AO27)/AN27) -> 0.049431627
I28: ='Total Sales'!G25 -> 44958 | J28: ='Total Sales'!J25 -> 203227 | K28: ='(ACF Helper)'!H25 -> 17 | L28: -0.46586734 | M28: -0.24028995 | N28: =SUM(J22:J33)/12 -> 191756.83 | O28: =(J22/24) + (J34/24) + SUM(J23:J33)/12 -> 192009.12 | P28: =$P$3*J28+(1-$P$3)*(P27+Q27) -> 189701.01 | Q28: =$P$4*(P28-P27)+(1-$P$4)*Q27 -> -167 | R28: =P28+Q28 -> 189534.01 | V28: =$U$24+$T$12*(K28-13-11/2) -> 191229.92 | W28: =J28/V28 -> 1.0627364 | Z28: =$AA$3*J28/IF(Y52=0,AB16,Y52) + (1-$AA$4)*(Z27+AA27) -> 204317.86 | AA28: =$AA$4*(Z28-Z27)+(1-$AA$4)*AA27 -> 780.50597 | AB28: =$AA$5*J28/Z28+(1-$AA$5)*IF(Y52=0,AB16,Y52) -> 0.97888062 | AC28: =(Z27+AA27)*IF(Y52=0,AB16,Y52) -> 187401.48 | AD28: =ABS((J28-AC28)/J28) -> 0.077871144 | AI28: =AVERAGE(AQ32:AQ43) -> 0.033033186 | AL28: 17 | AM28: 44958 | AN28: =J28 -> 203227 | AO28: =AC28 -> 187401.48 | AP28: 1 | AQ28: =ABS((AN28-AO28)/AN28) -> 0.077871144
I29: ='Total Sales'!G24 -> 44986 | J29: ='Total Sales'!J24 -> 184191 | K29: ='(ACF Helper)'!H26 -> 18 | L29: -0.5920779 | M29: -0.29902755 | N29: =SUM(J23:J34)/12 -> 192261.42 | O29: =(J23/24) + (J35/24) + SUM(J24:J34)/12 -> 192337.42 | P29: =$P$3*J29+(1-$P$3)*(P28+Q28) -> 189534.01 | Q29: =$P$4*(P29-P28)+(1-$P$4)*Q28 -> -167 | R29: =P29+Q29 -> 189367.01 | V29: =$U$24+$T$12*(K29-13-11/2) -> 192018.92 | W29: =J29/V29 -> 0.95923362 | Z29: =$AA$3*J29/IF(Y53=0,AB17,Y53) + (1-$AA$4)*(Z28+AA28) -> 204774.95 | AA29: =$AA$4*(Z29-Z28)+(1-$AA$4)*AA28 -> 779.99598 | AB29: =$AA$5*J29/Z29+(1-$AA$5)*IF(Y53=0,AB17,Y53) -> 0.90284721 | AC29: =(Z28+AA28)*IF(Y53=0,AB17,Y53) -> 187934.8 | AD29: =ABS((J29-AC29)/J29) -> 0.020325664 | AI29: =AVERAGE(AQ33:AQ44) -> 0.036974412 | AL29: 18 | AM29: 44986 | AN29: =J29 -> 184191 | AO29: =AC29 -> 187934.8 | AP29: 1 | AQ29: =ABS((AN29-AO29)/AN29) -> 0.020325664
I30: ='Total Sales'!G23 -> 45017 | J30: ='Total Sales'!J23 -> 137881 | K30: ='(ACF Helper)'!H27 -> 19 | L30: -0.6467849 | M30: -0.32566987 | N30: =SUM(J24:J35)/12 -> 192413.42 | O30: =(J24/24) + (J36/24) + SUM(J25:J35)/12 -> 193230.67 | P30: =$P$3*J30+(1-$P$3)*(P29+Q29) -> 189367.01 | Q30: =$P$4*(P30-P29)+(1-$P$4)*Q29 -> -167 | R30: =P30+Q30 -> 189200.01 | V30: =$U$24+$T$12*(K30-13-11/2) -> 192807.92 | W30: =J30/V30 -> 0.71512105 | Z30: =$AA$3*J30/IF(Y54=0,AB18,Y54) + (1-$AA$4)*(Z29+AA29) -> 205230.81 | AA30: =$AA$4*(Z30-Z29)+(1-$AA$4)*AA29 -> 779.48484 | AB30: =$AA$5*J30/Z30+(1-$AA$5)*IF(Y54=0,AB18,Y54) -> 0.67862216 | AC30: =(Z29+AA29)*IF(Y54=0,AB18,Y54) -> 145075.63 | AD30: =ABS((J30-AC30)/J30) -> 0.052179972 | AI30: =AVERAGE(AQ34:AQ45) -> 0.038366176 | AL30: 19 | AM30: 45017 | AN30: =J30 -> 137881 | AO30: =AC30 -> 145075.63 | AP30: 1 | AQ30: =ABS((AN30-AO30)/AN30) -> 0.052179972
I31: ='Total Sales'!G22 -> 45047 | J31: ='Total Sales'!J22 -> 171600 | K31: ='(ACF Helper)'!H28 -> 20 | L31: -0.49252616 | M31: -0.24101159 | N31: =SUM(J25:J36)/12 -> 194047.92 | O31: =(J25/24) + (J37/24) + SUM(J26:J36)/12 -> 194250.21 | P31: =$P$3*J31+(1-$P$3)*(P30+Q30) -> 189200.01 | Q31: =$P$4*(P31-P30)+(1-$P$4)*Q30 -> -167 | R31: =P31+Q31 -> 189033.01 | V31: =$U$24+$T$12*(K31-13-11/2) -> 193596.92 | W31: =J31/V31 -> 0.88637776 | Z31: =$AA$3*J31/IF(Y55=0,AB19,Y55) + (1-$AA$4)*(Z30+AA30) -> 205685.43 | AA31: =$AA$4*(Z31-Z30)+(1-$AA$4)*AA30 -> 778.97258 | AB31: =$AA$5*J31/Z31+(1-$AA$5)*IF(Y55=0,AB19,Y55) -> 0.8257477 | AC31: =(Z30+AA30)*IF(Y55=0,AB19,Y55) -> 163078.52 | AD31: =ABS((J31-AC31)/J31) -> 0.049658951 | AI31: =AVERAGE(AQ35:AQ46) -> 0.038549435 | AL31: 20 | AM31: 45047 | AN31: =J31 -> 171600 | AO31: =AC31 -> 163078.52 | AP31: 1 | AQ31: =ABS((AN31-AO31)/AN31) -> 0.049658951
I32: ='Total Sales'!G21 -> 45078 | J32: ='Total Sales'!J21 -> 160487 | K32: ='(ACF Helper)'!H29 -> 21 | L32: -0.21809642 | M32: -0.096310429 | N32: =SUM(J26:J37)/12 -> 194452.5 | O32: =(J26/24) + (J38/24) + SUM(J27:J37)/12 -> 194687.19 | P32: =$P$3*J32+(1-$P$3)*(P31+Q31) -> 189033.01 | Q32: =$P$4*(P32-P31)+(1-$P$4)*Q31 -> -167 | R32: =P32+Q32 -> 188866.01 | V32: =$U$24+$T$12*(K32-13-11/2) -> 194385.91 | W32: =J32/V32 -> 0.82561023 | Z32: =$AA$3*J32/IF(Y56=0,AB20,Y56) + (1-$AA$4)*(Z31+AA31) -> 206138.83 | AA32: =$AA$4*(Z32-Z31)+(1-$AA$4)*AA31 -> 778.45919 | AB32: =$AA$5*J32/Z32+(1-$AA$5)*IF(Y56=0,AB20,Y56) -> 0.77622351 | AC32: =(Z31+AA31)*IF(Y56=0,AB20,Y56) -> 158350.75 | AD32: =ABS((J32-AC32)/J32) -> 0.013311028 | AI32: =AVERAGE(AQ36:AQ47) -> 0.042476496 | AL32: 21 | AM32: 45078 | AN32: =J32 -> 160487 | AO32: =AC32 -> 158350.75 | AP32: 1 | AQ32: =ABS((AN32-AO32)/AN32) -> 0.013311028
I33: ='Total Sales'!G20 -> 45108 | J33: ='Total Sales'!J20 -> 117214 | K33: ='(ACF Helper)'!H30 -> 22 | L33: 0.13326622 | M33: 0.051731748 | N33: =SUM(J27:J38)/12 -> 194921.88 | O33: =(J27/24) + (J39/24) + SUM(J28:J38)/12 -> 195890.83 | P33: =$P$3*J33+(1-$P$3)*(P32+Q32) -> 188866.01 | Q33: =$P$4*(P33-P32)+(1-$P$4)*Q32 -> -167 | R33: =P33+Q33 -> 188699.01 | V33: =$U$24+$T$12*(K33-13-11/2) -> 195174.91 | W33: =J33/V33 -> 0.60055874 | Z33: =$AA$3*J33/IF(Y57=0,AB21,Y57) + (1-$AA$4)*(Z32+AA32) -> 206591.01 | AA33: =$AA$4*(Z33-Z32)+(1-$AA$4)*AA32 -> 777.94467 | AB33: =$AA$5*J33/Z33+(1-$AA$5)*IF(Y57=0,AB21,Y57) -> 0.57281223 | AC33: =(Z32+AA32)*IF(Y57=0,AB21,Y57) -> 123027.28 | AD33: =ABS((J33-AC33)/J33) -> 0.049595452 | AG33: New Target | AI33: =AVERAGE(AI27:AI32) -> 0.037417781 | AL33: 22 | AM33: 45108 | AN33: =J33 -> 117214 | AO33: =AC33 -> 123027.28 | AP33: 1 | AQ33: =ABS((AN33-AO33)/AN33) -> 0.049595452
I34: ='Total Sales'!G19 -> 45139 | J34: ='Total Sales'!J19 -> 142076 | K34: ='(ACF Helper)'!H31 -> 23 | L34: 0.57879836 | M34: 0.19276344 | N34: =SUM(J28:J39)/12 -> 196859.79 | O34: =(J28/24) + (J40/24) + SUM(J29:J39)/12 -> 197184.48 | P34: =$P$3*J34+(1-$P$3)*(P33+Q33) -> 188699.01 | Q34: =$P$4*(P34-P33)+(1-$P$4)*Q33 -> -167 | R34: =P34+Q34 -> 188532.01 | V34: =$U$24+$T$12*(K34-13-11/2) -> 195963.91 | W34: =J34/V34 -> 0.72501104 | Z34: =$AA$3*J34/IF(Y58=0,AB22,Y58) + (1-$AA$4)*(Z33+AA33) -> 207041.95 | AA34: =$AA$4*(Z34-Z33)+(1-$AA$4)*AA33 -> 777.42902 | AB34: =$AA$5*J34/Z34+(1-$AA$5)*IF(Y58=0,AB22,Y58) -> 0.68600199 | AC34: =(Z33+AA33)*IF(Y58=0,AB22,Y58) -> 142075.99 | AD34: =ABS((J34-AC34)/J34) -> 5.9320752e-08 | AL34: 23 | AM34: 45139 | AN34: =J34 -> 142076 | AO34: =AC34 -> 142075.99 | AP34: 1 | AQ34: =ABS((AN34-AO34)/AN34) -> 5.9320752e-08
I35: ='Total Sales'!G18 -> 45170 | J35: ='Total Sales'!J18 -> 174735 | K35: ='(ACF Helper)'!H32 -> 24 | L35: 0.94148474 | M35: 0.30046059 | N35: =SUM(J29:J40)/12 -> 197509.17 | O35: =(J29/24) + (J41/24) + SUM(J30:J40)/12 -> 197412.46 | P35: =$P$3*J35+(1-$P$3)*(P34+Q34) -> 188532.01 | Q35: =$P$4*(P35-P34)+(1-$P$4)*Q34 -> -167 | R35: =P35+Q35 -> 188365.01 | V35: =$U$24+$T$12*(K35-13-11/2) -> 196752.91 | W35: =J35/V35 -> 0.88809359 | Z35: =$AA$3*J35/IF(Y59=0,AB23,Y59) + (1-$AA$4)*(Z34+AA34) -> 207491.67 | AA35: =$AA$4*(Z35-Z34)+(1-$AA$4)*AA34 -> 776.91226 | AB35: =$AA$5*J35/Z35+(1-$AA$5)*IF(Y59=0,AB23,Y59) -> 0.84518348 | AC35: =(Z34+AA34)*IF(Y59=0,AB23,Y59) -> 178183.64 | AD35: =ABS((J35-AC35)/J35) -> 0.019736424 | AL35: 24 | AM35: 45170 | AN35: =J35 -> 174735 | AO35: =AC35 -> 178183.64 | AP35: 1 | AQ35: =ABS((AN35-AO35)/AN35) -> 0.019736424
I36: ='Total Sales'!G17 -> 45200 | J36: ='Total Sales'!J17 -> 194555 | K36: ='(ACF Helper)'!H33 -> 25 | L36: 0.77251304 | M36: 0.2423007 | N36: =SUM(J30:J41)/12 -> 197315.75 | O36: =(J30/24) + (J42/24) + SUM(J31:J41)/12 -> 198360 | P36: =$P$3*J36+(1-$P$3)*(P35+Q35) -> 188365.01 | Q36: =$P$4*(P36-P35)+(1-$P$4)*Q35 -> -167 | R36: =P36+Q36 -> 188198.01 | U36: =AVERAGE(J36:J47) -> 201683.42 | V36: =$U$36+$T$12*(K36-25-11/2) -> 197343.92 | W36: =J36/V36 -> 0.98586771 | Y36: =W12*$Y$3+W24*$Y$4+W36*$Y$5 -> 0.95678258 | Z36: =$AA$3*J36/IF(Y60=0,AB24,Y60) + (1-$AA$4)*(Z35+AA35) -> 207940.17 | AA36: =$AA$4*(Z36-Z35)+(1-$AA$4)*AA35 -> 776.39438 | AB36: =$AA$5*J36/Z36+(1-$AA$5)*IF(Y60=0,AB24,Y60) -> 0.92117931 | AC36: =(Z35+AA35)*IF(Y60=0,AB24,Y60) -> 179814.45 | AD36: =ABS((J36-AC36)/J36) -> 0.075765472 | AL36: 25 | AM36: 45200 | AN36: =J36 -> 194555 | AO36: =($AG$12+AP36*$AH$12)*INDEX($AI$12:$AI$23,MATCH(MONTH(AM36),$AJ$12:$AJ$23,0)) -> 184048.46 | AP36: 1 | AQ36: =ABS((AN36-AO36)/AN36) -> 0.05400295 | AR36: Validation (h varying)
I37: ='Total Sales'!G16 -> 45231 | J37: ='Total Sales'!J16 -> 248927 | K37: ='(ACF Helper)'!H34 -> 26 | L37: 0.31665331 | M37: 0.095404778 | N37: =SUM(J31:J42)/12 -> 199404.25 | O37: =(J31/24) + (J43/24) + SUM(J32:J42)/12 -> 199778.33 | P37: =$P$3*J37+(1-$P$3)*(P36+Q36) -> 188198.01 | Q37: =$P$4*(P37-P36)+(1-$P$4)*Q36 -> -167 | R37: =P37+Q37 -> 188031.01 | V37: =$U$36+$T$12*(K37-25-11/2) -> 198132.92 | W37: =J37/V37 -> 1.2563637 | Y37: =W13*$Y$3+W25*$Y$4+W37*$Y$5 -> 1.2725433 | Z37: =$AA$3*J37/IF(Y61=0,AB25,Y61) + (1-$AA$4)*(Z36+AA36) -> 208387.44 | AA37: =$AA$4*(Z37-Z36)+(1-$AA$4)*AA36 -> 775.87539 | AB37: =$AA$5*J37/Z37+(1-$AA$5)*IF(Y61=0,AB25,Y61) -> 1.1955071 | AC37: =(Z36+AA36)*IF(Y61=0,AB25,Y61) -> 250330.07 | AD37: =ABS((J37-AC37)/J37) -> 0.0056364809 | AL37: 26 | AM37: 45231 | AN37: =J37 -> 248927 | AO37: =($AG$12+AP37*$AH$12)*INDEX($AI$12:$AI$23,MATCH(MONTH(AM37),$AJ$12:$AJ$23,0)) -> 250067.17 | AP37: 2 | AQ37: =ABS((AN37-AO37)/AN37) -> 0.0045803505
I38: ='Total Sales'!G15 -> 45261 | J38: ='Total Sales'!J15 -> 307644 | K38: ='(ACF Helper)'!H35 -> 27 | L38: -0.010828155 | M38: -0.0011989432 | N38: =SUM(J32:J43)/12 -> 200152.42 | O38: =(J32/24) + (J44/24) + SUM(J33:J43)/12 -> 199886.46 | P38: =$P$3*J38+(1-$P$3)*(P37+Q37) -> 188031.01 | Q38: =$P$4*(P38-P37)+(1-$P$4)*Q37 -> -167 | R38: =P38+Q38 -> 187864.01 | V38: =$U$36+$T$12*(K38-25-11/2) -> 198921.92 | W38: =J38/V38 -> 1.5465566 | Y38: =W14*$Y$3+W26*$Y$4+W38*$Y$5 -> 1.5881746 | Z38: =$AA$3*J38/IF(Y62=0,AB26,Y62) + (1-$AA$4)*(Z37+AA37) -> 208833.48 | AA38: =$AA$4*(Z38-Z37)+(1-$AA$4)*AA37 -> 775.35529 | AB38: =$AA$5*J38/Z38+(1-$AA$5)*IF(Y62=0,AB26,Y62) -> 1.4788721 | AC38: =(Z37+AA37)*IF(Y62=0,AB26,Y62) -> 314109.34 | AD38: =ABS((J38-AC38)/J38) -> 0.021015661 | AL38: 27 | AM38: 45261 | AN38: =J38 -> 307644 | AO38: =($AG$12+AP38*$AH$12)*INDEX($AI$12:$AI$23,MATCH(MONTH(AM38),$AJ$12:$AJ$23,0)) -> 318912.83 | AP38: 3 | AQ38: =ABS((AN38-AO38)/AN38) -> 0.036629446
I39: ='Total Sales'!G14 -> 45292 | J39: ='Total Sales'!J14 -> 319780.5 | K39: ='(ACF Helper)'!H36 -> 28 | L39: -0.010111362 | M39: -0.0068050243 | N39: =SUM(J33:J44)/12 -> 199620.5 | O39: =(J33/24) + (J45/24) + SUM(J34:J44)/12 -> 200535.62 | P39: =$P$3*J39+(1-$P$3)*(P38+Q38) -> 187864.01 | Q39: =$P$4*(P39-P38)+(1-$P$4)*Q38 -> -167 | R39: =P39+Q39 -> 187697.01 | V39: =$U$36+$T$12*(K39-25-11/2) -> 199710.92 | W39: =J39/V39 -> 1.6012169 | Y39: =W15*$Y$3+W27*$Y$4+W39*$Y$5 -> 1.5647663 | Z39: =$AA$3*J39/IF(Y63=0,AB27,Y63) + (1-$AA$4)*(Z38+AA38) -> 209278.31 | AA39: =$AA$4*(Z39-Z38)+(1-$AA$4)*AA38 -> 774.83407 | AB39: =$AA$5*J39/Z39+(1-$AA$5)*IF(Y63=0,AB27,Y63) -> 1.5103607 | AC39: =(Z38+AA38)*IF(Y63=0,AB27,Y63) -> 301782.56 | AD39: =ABS((J39-AC39)/J39) -> 0.056282165 | AL39: 28 | AM39: 45292 | AN39: =J39 -> 319780.5 | AO39: =($AG$12+AP39*$AH$12)*INDEX($AI$12:$AI$23,MATCH(MONTH(AM39),$AJ$12:$AJ$23,0)) -> 304650.07 | AP39: 4 | AQ39: =ABS((AN39-AO39)/AN39) -> 0.047315055
I40: ='Total Sales'!G13 -> 45323 | J40: ='Total Sales'!J13 -> 211019.5 | K40: ='(ACF Helper)'!H37 -> 29 | L40: 0.040467309 | M40: -0.020675372 | N40: =SUM(J34:J45)/12 -> 201450.75 | O40: =(J34/24) + (J46/24) + SUM(J35:J45)/12 -> 201740.33 | P40: =$P$3*J40+(1-$P$3)*(P39+Q39) -> 187697.01 | Q40: =$P$4*(P40-P39)+(1-$P$4)*Q39 -> -167 | R40: =P40+Q40 -> 187530.01 | V40: =$U$36+$T$12*(K40-25-11/2) -> 200499.92 | W40: =J40/V40 -> 1.0524668 | Y40: =W16*$Y$3+W28*$Y$4+W40*$Y$5 -> 1.0431009 | Z40: =$AA$3*J40/IF(Y64=0,AB28,Y64) + (1-$AA$4)*(Z39+AA39) -> 209721.91 | AA40: =$AA$4*(Z40-Z39)+(1-$AA$4)*AA39 -> 774.31176 | AB40: =$AA$5*J40/Z40+(1-$AA$5)*IF(Y64=0,AB28,Y64) -> 1.0007259 | AC40: =(Z39+AA39)*IF(Y64=0,AB28,Y64) -> 205616.95 | AD40: =ABS((J40-AC40)/J40) -> 0.02560213 | AL40: 29 | AM40: 45323 | AN40: =J40 -> 211019.5 | AO40: =($AG$12+AP40*$AH$12)*INDEX($AI$12:$AI$23,MATCH(MONTH(AM40),$AJ$12:$AJ$23,0)) -> 204434.19 | AP40: 5 | AQ40: =ABS((AN40-AO40)/AN40) -> 0.031207126
I41: ='Total Sales'!G12 -> 45352 | J41: ='Total Sales'!J12 -> 181870 | K41: ='(ACF Helper)'!H38 -> 30 | L41: -0.36251675 | M41: -0.059991126 | N41: =SUM(J35:J46)/12 -> 202029.92 | O41: =(J35/24) + (J47/24) + SUM(J36:J46)/12 -> 201856.67 | P41: =$P$3*J41+(1-$P$3)*(P40+Q40) -> 187530.01 | Q41: =$P$4*(P41-P40)+(1-$P$4)*Q40 -> -167 | R41: =P41+Q41 -> 187363.01 | V41: =$U$36+$T$12*(K41-25-11/2) -> 201288.92 | W41: =J41/V41 -> 0.90352714 | Y41: =W17*$Y$3+W29*$Y$4+W41*$Y$5 -> 0.9365921 | Z41: =$AA$3*J41/IF(Y65=0,AB29,Y65) + (1-$AA$4)*(Z40+AA40) -> 210164.29 | AA41: =$AA$4*(Z41-Z40)+(1-$AA$4)*AA40 -> 773.78834 | AB41: =$AA$5*J41/Z41+(1-$AA$5)*IF(Y65=0,AB29,Y65) -> 0.87286592 | AC41: =(Z40+AA40)*IF(Y65=0,AB29,Y65) -> 190045.93 | AD41: =ABS((J41-AC41)/J41) -> 0.044954792 | AL41: 30 | AM41: 45352 | AN41: =J41 -> 181870 | AO41: =($AG$12+AP41*$AH$12)*INDEX($AI$12:$AI$23,MATCH(MONTH(AM41),$AJ$12:$AJ$23,0)) -> 190773.78 | AP41: 6 | AQ41: =ABS((AN41-AO41)/AN41) -> 0.048956821
I42: ='Total Sales'!G11 -> 45383 | J42: ='Total Sales'!J11 -> 162943 | K42: ='(ACF Helper)'!H39 -> 31 | L42: -0.96631677 | M42: -0.08669637 | N42: =SUM(J36:J47)/12 -> 201683.42 | V42: =$U$36+$T$12*(K42-25-11/2) -> 202077.92 | W42: =J42/V42 -> 0.80633749 | Y42: =W18*$Y$3+W30*$Y$4+W42*$Y$5 -> 0.76624528 | Z42: =$AA$3*J42/IF(Y66=0,AB30,Y66) + (1-$AA$4)*(Z41+AA41) -> 210605.45 | AA42: =$AA$4*(Z42-Z41)+(1-$AA$4)*AA41 -> 773.26382 | AB42: =$AA$5*J42/Z42+(1-$AA$5)*IF(Y66=0,AB30,Y66) -> 0.75467516 | AC42: =(Z41+AA41)*IF(Y66=0,AB30,Y66) -> 143147.26 | AD42: =ABS((J42-AC42)/J42) -> 0.12148877 | AL42: 31 | AM42: 45383 | AN42: =J42 -> 162943 | AO42: =($AG$12+AP42*$AH$12)*INDEX($AI$12:$AI$23,MATCH(MONTH(AM42),$AJ$12:$AJ$23,0)) -> 152141.5 | AP42: 7 | AQ42: =ABS((AN42-AO42)/AN42) -> 0.066290071
I43: ='Total Sales'!G10 -> 45413 | J43: ='Total Sales'!J10 -> 180578 | K43: ='(ACF Helper)'!H40 -> 32 | L43: -0.2289416 | M43: -0.065079737 | V43: =$U$36+$T$12*(K43-25-11/2) -> 202866.92 | W43: =J43/V43 -> 0.89013036 | Y43: =W19*$Y$3+W31*$Y$4+W43*$Y$5 -> 0.8806852 | Z43: =$AA$3*J43/IF(Y67=0,AB31,Y67) + (1-$AA$4)*(Z42+AA42) -> 211045.4 | AA43: =$AA$4*(Z43-Z42)+(1-$AA$4)*AA42 -> 772.73821 | AB43: =$AA$5*J43/Z43+(1-$AA$5)*IF(Y67=0,AB31,Y67) -> 0.84965819 | AC43: =(Z42+AA42)*IF(Y67=0,AB31,Y67) -> 174545.49 | AD43: =ABS((J43-AC43)/J43) -> 0.033406672 | AL43: 32 | AM43: 45413 | AN43: =J43 -> 180578 | AO43: =($AG$12+AP43*$AH$12)*INDEX($AI$12:$AI$23,MATCH(MONTH(AM43),$AJ$12:$AJ$23,0)) -> 176104.46 | AP43: 8 | AQ43: =ABS((AN43-AO43)/AN43) -> 0.024773446
I44: ='Total Sales'!G9 -> 45444 | J44: ='Total Sales'!J9 -> 154104 | K44: ='(ACF Helper)'!H41 -> 33 | L44: 0.91461549 | M44: -0.023207461 | V44: =$U$36+$T$12*(K44-25-11/2) -> 203655.91 | W44: =J44/V44 -> 0.75668806 | Y44: =W20*$Y$3+W32*$Y$4+W44*$Y$5 -> 0.79108629 | Z44: =$AA$3*J44/IF(Y68=0,AB32,Y68) + (1-$AA$4)*(Z43+AA43) -> 211484.12 | AA44: =$AA$4*(Z44-Z43)+(1-$AA$4)*AA43 -> 772.2115 | AB44: =$AA$5*J44/Z44+(1-$AA$5)*IF(Y68=0,AB32,Y68) -> 0.73818776 | AC44: =(Z43+AA43)*IF(Y68=0,AB32,Y68) -> 164418.22 | AD44: =ABS((J44-AC44)/J44) -> 0.066930235 | AL44: 33 | AM44: 45444 | AN44: =J44 -> 154104 | AO44: =($AG$12+AP44*$AH$12)*INDEX($AI$12:$AI$23,MATCH(MONTH(AM44),$AJ$12:$AJ$23,0)) -> 163443.59 | AP44: 9 | AQ44: =ABS((AN44-AO44)/AN44) -> 0.060605747
I45: ='Total Sales'!G8 -> 45474 | J45: ='Total Sales'!J8 -> 139177 | K45: ='(ACF Helper)'!H42 -> 34 | L45: 0.73251378 | M45: 0.0032855353 | V45: =$U$36+$T$12*(K45-25-11/2) -> 204444.91 | W45: =J45/V45 -> 0.6807555 | Y45: =W21*$Y$3+W33*$Y$4+W45*$Y$5 -> 0.64505495 | Z45: =$AA$3*J45/IF(Y69=0,AB33,Y69) + (1-$AA$4)*(Z44+AA44) -> 211921.63 | AA45: =$AA$4*(Z45-Z44)+(1-$AA$4)*AA44 -> 771.68371 | AB45: =$AA$5*J45/Z45+(1-$AA$5)*IF(Y69=0,AB33,Y69) -> 0.6399529 | AC45: =(Z44+AA44)*IF(Y69=0,AB33,Y69) -> 121583.02 | AD45: =ABS((J45-AC45)/J45) -> 0.1264144 | AL45: 34 | AM45: 45474 | AN45: =J45 -> 139177 | AO45: =($AG$12+AP45*$AH$12)*INDEX($AI$12:$AI$23,MATCH(MONTH(AM45),$AJ$12:$AJ$23,0)) -> 129950.04 | AP45: 10 | AQ45: =ABS((AN45-AO45)/AN45) -> 0.066296621
I46: ='Total Sales'!G7 -> 45505 | J46: ='Total Sales'!J7 -> 149026 | K46: ='(ACF Helper)'!H43 -> 35 | L46: -1 | M46: 0.0051708957 | V46: =$U$36+$T$12*(K46-25-11/2) -> 205233.91 | W46: =J46/V46 -> 0.72612756 | Y46: =W22*$Y$3+W34*$Y$4+W46*$Y$5 -> 0.72617528 | Z46: =$AA$3*J46/IF(Y70=0,AB34,Y70) + (1-$AA$4)*(Z45+AA45) -> 212357.91 | AA46: =$AA$4*(Z46-Z45)+(1-$AA$4)*AA45 -> 771.15482 | AB46: =$AA$5*J46/Z46+(1-$AA$5)*IF(Y70=0,AB34,Y70) -> 0.69861484 | AC46: =(Z45+AA45)*IF(Y70=0,AB34,Y70) -> 145908.03 | AD46: =ABS((J46-AC46)/J46) -> 0.020922303 | AL46: 35 | AM46: 45505 | AN46: =J46 -> 149026 | AO46: =($AG$12+AP46*$AH$12)*INDEX($AI$12:$AI$23,MATCH(MONTH(AM46),$AJ$12:$AJ$23,0)) -> 149353.73 | AP46: 11 | AQ46: =ABS((AN46-AO46)/AN46) -> 0.0021991635
I47: ='Total Sales'!G6 -> 45536 | J47: ='Total Sales'!J6 -> 170577 | K47: ='(ACF Helper)'!H44 -> 36 | V47: =$U$36+$T$12*(K47-25-11/2) -> 206022.91 | W47: =J47/V47 -> 0.8279516 | Y47: =W23*$Y$3+W35*$Y$4+W47*$Y$5 -> 0.86323946 | Z47: =$AA$3*J47/IF(Y71=0,AB35,Y71) + (1-$AA$4)*(Z46+AA46) -> 212792.99 | AA47: =$AA$4*(Z47-Z46)+(1-$AA$4)*AA46 -> 770.62486 | AB47: =$AA$5*J47/Z47+(1-$AA$5)*IF(Y71=0,AB35,Y71) -> 0.81032474 | AC47: =(Z46+AA46)*IF(Y71=0,AB35,Y71) -> 180133.17 | AD47: =ABS((J47-AC47)/J47) -> 0.056022609 | AL47: 36 | AM47: 45536 | AN47: =J47 -> 170577 | AO47: =($AG$12+AP47*$AH$12)*INDEX($AI$12:$AI$23,MATCH(MONTH(AM47),$AJ$12:$AJ$23,0)) -> 181981.97 | AP47: 12 | AQ47: =ABS((AN47-AO47)/AN47) -> 0.066861153
AL48: 37 | AM48: 45566 | AO48: =($AG$12+AP48*$AH$12)*INDEX($AI$12:$AI$23,MATCH(MONTH(AM48),$AJ$12:$AJ$23,0)) -> 192264.05 | AP48: 13 | AR48: Prediction for next 18 months
AL49: 38 | AM49: 45597 | AO49: =($AG$12+AP49*$AH$12)*INDEX($AI$12:$AI$23,MATCH(MONTH(AM49),$AJ$12:$AJ$23,0)) -> 261188.35 | AP49: 14
AL50: 39 | AM50: 45627 | AO50: =($AG$12+AP50*$AH$12)*INDEX($AI$12:$AI$23,MATCH(MONTH(AM50),$AJ$12:$AJ$23,0)) -> 333043.4 | AP50: 15
AL51: 40 | AM51: 45658 | AO51: =($AG$12+AP51*$AH$12)*INDEX($AI$12:$AI$23,MATCH(MONTH(AM51),$AJ$12:$AJ$23,0)) -> 318099.02 | AP51: 16
AL52: 41 | AM52: 45689 | AO52: =($AG$12+AP52*$AH$12)*INDEX($AI$12:$AI$23,MATCH(MONTH(AM52),$AJ$12:$AJ$23,0)) -> 213425.97 | AP52: 17
AL53: 42 | AM53: 45717 | AO53: =($AG$12+AP53*$AH$12)*INDEX($AI$12:$AI$23,MATCH(MONTH(AM53),$AJ$12:$AJ$23,0)) -> 199134.08 | AP53: 18
AL54: 43 | AM54: 45748 | AO54: =($AG$12+AP54*$AH$12)*INDEX($AI$12:$AI$23,MATCH(MONTH(AM54),$AJ$12:$AJ$23,0)) -> 158784.55 | AP54: 19
AL55: 44 | AM55: 45778 | AO55: =($AG$12+AP55*$AH$12)*INDEX($AI$12:$AI$23,MATCH(MONTH(AM55),$AJ$12:$AJ$23,0)) -> 183765.95 | AP55: 20
AL56: 45 | AM56: 45809 | AO56: =($AG$12+AP56*$AH$12)*INDEX($AI$12:$AI$23,MATCH(MONTH(AM56),$AJ$12:$AJ$23,0)) -> 170528.58 | AP56: 21
AL57: 46 | AM57: 45839 | AO57: =($AG$12+AP57*$AH$12)*INDEX($AI$12:$AI$23,MATCH(MONTH(AM57),$AJ$12:$AJ$23,0)) -> 135562.86 | AP57: 22
AL58: 47 | AM58: 45870 | AO58: =($AG$12+AP58*$AH$12)*INDEX($AI$12:$AI$23,MATCH(MONTH(AM58),$AJ$12:$AJ$23,0)) -> 155781.51 | AP58: 23
AL59: 48 | AM59: 45901 | AO59: =($AG$12+AP59*$AH$12)*INDEX($AI$12:$AI$23,MATCH(MONTH(AM59),$AJ$12:$AJ$23,0)) -> 189786 | AP59: 24
AL60: 49 | AM60: 45931 | AO60: =($AG$12+AP60*$AH$12)*INDEX($AI$12:$AI$23,MATCH(MONTH(AM60),$AJ$12:$AJ$23,0)) -> 200479.64 | AP60: 25
... AL65: 54 | AM65: 46082 | AO65: =($AG$12+AP65*$AH$12)*INDEX($AI$12:$AI$23,MATCH(MONTH(AM65),$AJ$12:$AJ$23,0)) -> 207494.38 | AP65: 30
J66: Initial forecast plot

Sheet Parameters Optimisation
A1: Assumptions
C2: Parameters Optimization for Alpha and Beta | AF2: Optimized model
C5: Cycle # | D5: Month # | E5: Month | F5: Monthly Sales WH1000-MX5 | G5: Moving MAPE Calculation (Forecast Initialisation) | AF5: Cycle # | AG5: Month # | AH5: Month | AI5: Base (B) | AJ5: Trend (T) | AK5: Seasonality (S) | AL5: Forecast (F) | AM5: h | AN5: APE | AQ5: Optimised Values
C6: 1 | D6: 1 | E6: 44470 | F6: ='Forecast Validation'!J12 -> 164732 | AF6: 1 | AG6: 1 | AH6: 44470 | AI6: =$AR$8*F6/'Forecast Validation'!$Y36+(1-$AR$8)*(AR6+AR7) -> 197122.44 | AJ6: =$AR$9*(AI6-$AR$6)+(1-$AR$9)*$AR$7 -> 788.92431 | AK6: =$AR$10*F6/AI6+(1-$AR$10)*'Forecast Validation'!Y36 -> 0.85990344 | AL6: =(AI6+AM6*AJ6)*AK6 -> 170184.66 | AM6: 1 | AN6: =ABS((F6-AL6)/F6) -> 0.033100196 | AO6: Model training with h = 1 (from Forecast Validation) | AQ6: Initial Base | AR6: ='Forecast Validation'!X24 -> 196358.41
D7: 2 | E7: 44501 | F7: ='Forecast Validation'!J13 -> 229781.5 | AG7: 2 | AH7: 44501 | AI7: =$AR$8*F7/'Forecast Validation'!$Y37+(1-$AR$8)*(AI6+AJ6) -> 197894.02 | AJ7: =$AR$9*(AI7-AI6)+(1-$AR$9)*AJ6 -> 788.87228 | AK7: =$AR$10*F7/AI7+(1-$AR$10)*'Forecast Validation'!Y37 -> 1.183416 | AL7: =(AI7+AM7*AJ7)*AK7 -> 235124.51 | AM7: 1 | AN7: =ABS((F7-AL7)/F7) -> 0.02325255 | AQ7: Initial Trend | AR7: ='Forecast Validation'!T12 -> 788.99923
D8: 3 | E8: 44531 | F8: ='Forecast Validation'!J14 -> 309493.5 | M8: MAPE' | N8: ='Forecast Validation'!AI33 -> 0.037417781 | AG8: 3 | AH8: 44531 | AI8: =$AR$8*F8/'Forecast Validation'!$Y38+(1-$AR$8)*(AI7+AJ7) -> 198679.08 | AJ8: =$AR$9*(AI8-AI7)+(1-$AR$9)*AJ7 -> 788.86085 | AK8: =$AR$10*F8/AI8+(1-$AR$10)*'Forecast Validation'!Y38 -> 1.5638396 | AL8: =(AI8+AM8*AJ8)*AK8 -> 311935.87 | AM8: 1 | AN8: =ABS((F8-AL8)/F8) -> 0.0078914906 | AQ8: alpha | AR8: 0.001
D9: 4 | E9: 44562 | F9: ='Forecast Validation'!J15 -> 264563.5 | M9: MAPE minimum | N9: =_xlfn.MINIFS(N12:AD28, N12:AD28, "<10%") -> 0.037805006 | AG9: 4 | AH9: 44562 | AI9: =$AR$8*F9/'Forecast Validation'!$Y39+(1-$AR$8)*(AI8+AJ8) -> 199437.55 | AJ9: =$AR$9*(AI9-AI8)+(1-$AR$9)*AJ8 -> 788.76967 | AK9: =$AR$10*F9/AI9+(1-$AR$10)*'Forecast Validation'!Y39 -> 1.3741917 | AL9: =(AI9+AM9*AJ9)*AK9 -> 275149.35 | AM9: 1 | AN9: =ABS((F9-AL9)/F9) -> 0.04001252 | AQ9: beta | AR9: 0.003
D10: 5 | E10: 44593 | F10: ='Forecast Validation'!J16 -> 175668 | AG10: 5 | AH10: 44593 | AI10: =$AR$8*F10/'Forecast Validation'!$Y40+(1-$AR$8)*(AI9+AJ9) -> 200194.5 | AJ10: =$AR$9*(AI10-AI9)+(1-$AR$9)*AJ9 -> 788.67422 | AK10: =$AR$10*F10/AI10+(1-$AR$10)*'Forecast Validation'!Y40 -> 0.91060948 | AL10: =(AI10+AM10*AJ10)*AK10 -> 183017.19 | AM10: 1 | AN10: =ABS((F10-AL10)/F10) -> 0.041835658 | AQ10: gamma | AR10: 0.8
D11: 6 | E11: 44621 | F11: ='Forecast Validation'!J17 -> 181528 | M11: alpha / beta | N11: 0.001 | O11: 0.002 | P11: 0.003 | Q11: 0.004 | R11: 0.005 | S11: 0.006 | T11: 0.007 | U11: 0.008 | V11: 0.009 | W11: 0.02 | X11: 0.03 | Y11: 0.04 | Z11: 0.05 | AA11: 0.06 | AB11: 0.07 | AC11: 0.08 | AD11: 0.09 | AG11: 6 | AH11: 44621 | AI11: =$AR$8*F11/'Forecast Validation'!$Y41+(1-$AR$8)*(AI10+AJ10) -> 200976.01 | AJ11: =$AR$9*(AI11-AI10)+(1-$AR$9)*AJ10 -> 788.65273 | AK11: =$AR$10*F11/AI11+(1-$AR$10)*'Forecast Validation'!Y41 -> 0.90990416 | AL11: =(AI11+AM11*AJ11)*AK11 -> 183586.51 | AM11: 1 | AN11: =ABS((F11-AL11)/F11) -> 0.011339889
D12: 7 | E12: 44652 | F12: ='Forecast Validation'!J18 -> 137910 | M12: 0.001 | N12: 0.039697873 | O12: 0.038121973 | P12: 0.037805006 | Q12: 0.040533915 | R12: 0.045229671 | S12: 0.051479768 | T12: 0.05975768 | U12: 0.07003193 | V12: 0.080655343 | W12: 0.22648252 | X12: 0.38726509 | Y12: 0.83990642 | Z12: 0.838716 | AA12: 2.7973985 | AB12: 2.2796472 | AC12: 2.8226354 | AD12: 1.7926337 | AG12: 7 | AH12: 44652 | AI12: =$AR$8*F12/'Forecast Validation'!$Y42+(1-$AR$8)*(AI11+AJ11) -> 201742.88 | AJ12: =$AR$9*(AI12-AI11)+(1-$AR$9)*AJ11 -> 788.58738 | AK12: =$AR$10*F12/AI12+(1-$AR$10)*'Forecast Validation'!Y42 -> 0.70012337 | AL12: =(AI12+AM12*AJ12)*AK12 -> 141797.01 | AM12: 1 | AN12: =ABS((F12-AL12)/F12) -> 0.028185153
D13: 8 | E13: 44682 | F13: ='Forecast Validation'!J19 -> 153981 | M13: 0.002 | N13: 0.041572491 | O13: 0.039650824 | P13: 0.038098792 | Q13: 0.037980202 | R13: 0.040822873 | S13: 0.045559244 | T13: 0.052010268 | U13: 0.060461645 | V13: 0.070966243 | W13: 0.21393248 | X13: 0.37253897 | Y13: 0.71914321 | Z13: 0.87080342 | AA13: 1.7373328 | AB13: 18.99322 | AC13: 1.9832928 | AD13: 1.6045479 | AG13: 8 | AH13: 44682 | AI13: =$AR$8*F13/'Forecast Validation'!$Y43+(1-$AR$8)*(AI12+AJ12) -> 202503.78 | AJ13: =$AR$9*(AI13-AI12)+(1-$AR$9)*AJ12 -> 788.50431 | AK13: =$AR$10*F13/AI13+(1-$AR$10)*'Forecast Validation'!Y43 -> 0.78444569 | AL13: =(AI13+AM13*AJ13)*AK13 -> 159471.76 | AM13: 1 | AN13: =ABS((F13-AL13)/F13) -> 0.035658654
D14: 9 | E14: 44713 | F14: ='Forecast Validation'!J20 -> 152656 | M14: 0.003 | N14: 0.043474497 | O14: 0.041528329 | P14: 0.039602968 | Q14: 0.038075459 | R14: 0.038157194 | S14: 0.041112354 | T14: 0.045887681 | U14: 0.052570269 | V14: 0.061312317 | W14: 0.20145247 | X14: 0.35785069 | Y14: 0.55936901 | Z14: 1.027645 | AA14: 4.1408422 | AB14: 2.3316625 | AC14: 2.5298596 | AD14: 2.0017504 | AG14: 9 | AH14: 44713 | AI14: =$AR$8*F14/'Forecast Validation'!$Y44+(1-$AR$8)*(AI13+AJ13) -> 203281.96 | AJ14: =$AR$9*(AI14-AI13)+(1-$AR$9)*AJ13 -> 788.47334 | AK14: =$AR$10*F14/AI14+(1-$AR$10)*'Forecast Validation'!Y44 -> 0.75898281 | AL14: =(AI14+AM14*AJ14)*AK14 -> 154885.95 | AM14: 1 | AN14: =ABS((F14-AL14)/F14) -> 0.014607695
D15: 10 | E15: 44743 | F15: ='Forecast Validation'!J21 -> 117021 | M15: 0.004 | N15: 0.047636439 | O15: 0.043421498 | P15: 0.041483024 | Q15: 0.039554408 | R15: 0.038052034 | S15: 0.038335763 | T15: 0.04140204 | U15: 0.046214675 | V15: 0.053144048 | W15: 0.18904425 | X15: 0.34324428 | Y15: 0.53067117 | Z15: 0.89264881 | AA15: 1.4264253 | AB15: 3.0752804 | AC15: 3.4965531 | AD15: 5.6476312 | AG15: 10 | AH15: 44743 | AI15: =$AR$8*F15/'Forecast Validation'!$Y45+(1-$AR$8)*(AI14+AJ14) -> 204047.78 | AJ15: =$AR$9*(AI15-AI14)+(1-$AR$9)*AJ14 -> 788.40537 | AK15: =$AR$10*F15/AI15+(1-$AR$10)*'Forecast Validation'!Y45 -> 0.58780942 | AL15: =(AI15+AM15*AJ15)*AK15 -> 120404.64 | AM15: 1 | AN15: =ABS((F15-AL15)/F15) -> 0.028914793
D16: 11 | E16: 44774 | F16: ='Forecast Validation'!J22 -> 136021 | M16: 0.005 | N16: 0.055024315 | O16: 0.047589465 | P16: 0.043363133 | Q16: 0.041436681 | R16: 0.039505243 | S16: 0.038028574 | T16: 0.038515694 | U16: 0.041691617 | V16: 0.046539925 | W16: 0.17670862 | X16: 0.32874613 | Y16: 0.51419887 | Z16: 0.74014325 | AA16: 1.6364436 | AB16: 2.5362582 | AC16: 2.1781479 | AD16: 1.881462 | AG16: 11 | AH16: 44774 | AI16: =$AR$8*F16/'Forecast Validation'!$Y46+(1-$AR$8)*(AI15+AJ15) -> 204818.66 | AJ16: =$AR$9*(AI16-AI15)+(1-$AR$9)*AJ15 -> 788.35279 | AK16: =$AR$10*F16/AI16+(1-$AR$10)*'Forecast Validation'!Y46 -> 0.67651869 | AL16: =(AI16+AM16*AJ16)*AK16 -> 139096.98 | AM16: 1 | AN16: =ABS((F16-AL16)/F16) -> 0.022614042
D17: 12 | E17: 44805 | F17: ='Forecast Validation'!J23 -> 172911 | M17: 0.006 | N17: 0.063036721 | O17: 0.055050363 | P17: 0.047528436 | Q17: 0.043302876 | R17: 0.041389405 | S17: 0.03945557 | T17: 0.038005135 | U17: 0.038696771 | V17: 0.041980777 | W17: 0.16444566 | X17: 0.31437167 | Y17: 0.49635591 | Z17: 0.71426477 | AA17: 1.0425395 | AB17: 2.5074994 | AC17: 3.2364024 | AD17: 1.839698 | AG17: 12 | AH17: 44805 | AI17: =$AR$8*F17/'Forecast Validation'!$Y47+(1-$AR$8)*(AI16+AJ16) -> 205601.71 | AJ17: =$AR$9*(AI17-AI16)+(1-$AR$9)*AJ16 -> 788.33689 | AK17: =$AR$10*F17/AI17+(1-$AR$10)*'Forecast Validation'!Y47 -> 0.84544775 | AL17: =(AI17+AM17*AJ17)*AK17 -> 174492 | AM17: 1 | AN17: =ABS((F17-AL17)/F17) -> 0.0091434275
C18: 2 | D18: 13 | E18: 44835 | F18: ='Forecast Validation'!J24 -> 174941 | M18: 0.007 | N18: 0.071032135 | O18: 0.063137753 | P18: 0.055055734 | Q18: 0.047453914 | R18: 0.043257457 | S18: 0.041341299 | T18: 0.039405484 | U18: 0.03798177 | V18: 0.038878784 | W18: 0.15225496 | X18: 0.30012933 | Y18: 0.4783763 | Z18: 0.72233353 | AA18: 0.98336045 | AB18: 2.5344536 | AC18: 2.8784315 | AD18: 4.0956092 | AF18: 2 | AG18: 13 | AH18: 44835 | AI18: =$AR$8*F18/AK6+(1-$AR$8)*(AI17+AJ17) -> 206387.1 | AJ18: =$AR$9*(AI18-AI17)+(1-$AR$9)*AJ17 -> 788.32805 | AK18: =$AR$10*F18/AI18+(1-$AR$10)*AK6 -> 0.85008897 | AL18: =(AI18+AM18*AJ18)*AK18 -> 176117.54 | AM18: 1 | AN18: =ABS((F18-AL18)/F18) -> 0.0067253773
D19: 14 | E19: 44866 | F19: ='Forecast Validation'!J25 -> 244072 | M19: 0.008 | N19: 0.079010953 | O19: 0.071206967 | P19: 0.063215628 | Q19: 0.055041163 | R19: 0.047366459 | S19: 0.04321089 | T19: 0.041292461 | U19: 0.039355077 | V19: 0.037958532 | W19: 0.14013567 | X19: 0.28602304 | Y19: 0.46057813 | Z19: 0.71712078 | AA19: 1.3896251 | AB19: 2.1098096 | AC19: 2.3384154 | AD19: 2.2752889 | AG19: 14 | AH19: 44866 | AI19: =$AR$8*F19/AK7+(1-$AR$8)*(AI18+AJ18) -> 207174.49 | AJ19: =$AR$9*(AI19-AI18)+(1-$AR$9)*AJ18 -> 788.32525 | AK19: =$AR$10*F19/AI19+(1-$AR$10)*AK7 -> 1.1791621 | AL19: =(AI19+AM19*AJ19)*AK19 -> 245221.88 | AM19: 1 | AN19: =ABS((F19-AL19)/F19) -> 0.0047112496
D20: 15 | E20: 44896 | F20: ='Forecast Validation'!J26 -> 302011.5 | M20: 0.009 | N20: 0.086973565 | O20: 0.079258441 | P20: 0.071356182 | Q20: 0.063271095 | R20: 0.055007377 | S20: 0.047266626 | T20: 0.043163279 | U20: 0.041242988 | V20: 0.03930444 | W20: 0.12808668 | X20: 0.27205371 | Y20: 0.44306714 | Z20: 0.69665611 | AA20: 0.88707612 | AB20: 2.0153422 | AC20: 14.379418 | AD20: 2.0262556 | AG20: 15 | AH20: 44896 | AI20: =$AR$8*F20/AK8+(1-$AR$8)*(AI19+AJ19) -> 207947.98 | AJ20: =$AR$9*(AI20-AI19)+(1-$AR$9)*AJ19 -> 788.28073 | AK20: =$AR$10*F20/AI20+(1-$AR$10)*AK8 -> 1.4746412 | AL20: =(AI20+AM20*AJ20)*AK20 -> 307811.09 | AM20: 1 | AN20: =ABS((F20-AL20)/F20) -> 0.0192032
D21: 16 | E21: 44927 | F21: ='Forecast Validation'!J27 -> 296525.5 | M21: 0.02 | N21: 0.18804514 | O21: 0.18030573 | P21: 0.1722948 | Q21: 0.16401868 | R21: 0.15548359 | S21: 0.14669564 | T21: 0.13766086 | U21: 0.12838514 | V21: 0.11887427 | W21: 0.038925861 | X21: 0.12662386 | Y21: 0.26978741 | Z21: 0.43489214 | AA21: 0.68396652 | AB21: 1.3141494 | AC21: 1.3756204 | AD21: 2.3287248 | AG21: 16 | AH21: 44927 | AI21: =$AR$8*F21/AK9+(1-$AR$8)*(AI20+AJ20) -> 208743.3 | AJ21: =$AR$9*(AI21-AI20)+(1-$AR$9)*AJ20 -> 788.30186 | AK21: =$AR$10*F21/AI21+(1-$AR$10)*AK9 -> 1.4112599 | AL21: =(AI21+AM21*AJ21)*AK21 -> 295703.56 | AM21: 1 | AN21: =ABS((F21-AL21)/F21) -> 0.0027718925
D22: 17 | E22: 44958 | F22: ='Forecast Validation'!J28 -> 203227 | M22: 0.03 | N22: 0.280713 | O22: 0.27396785 | P22: 0.26694547 | Q22: 0.25965268 | R22: 0.25209623 | S22: 0.24428279 | T22: 0.23621899 | U22: 0.22791134 | V22: 0.21936629 | W22: 0.11145075 | X22: 0.038866069 | Y22: 0.13352961 | Z22: 0.27383869 | AA22: 0.43003172 | AB22: 0.63069942 | AC22: 1.3863004 | AD22: 1.4622474 | AG22: 17 | AH22: 44958 | AI22: =$AR$8*F22/AK10+(1-$AR$8)*(AI21+AJ21) -> 209545.25 | AJ22: =$AR$9*(AI22-AI21)+(1-$AR$9)*AJ21 -> 788.3428 | AK22: =$AR$10*F22/AI22+(1-$AR$10)*AK10 -> 0.95800013 | AL22: =(AI22+AM22*AJ22)*AK22 -> 201499.61 | AM22: 1 | AN22: =ABS((F22-AL22)/F22) -> 0.0084998008
D23: 18 | E23: 44986 | F23: ='Forecast Validation'!J29 -> 184191 | M23: 0.04 | N23: 0.37238525 | O23: 0.36652547 | P23: 0.36037949 | Q23: 0.35395445 | R23: 0.34725745 | S23: 0.34029552 | T23: 0.33307566 | U23: 0.32560477 | V23: 0.31788971 | W23: 0.21879607 | X23: 0.11076488 | Y23: 0.039000375 | Z23: 0.13675328 | AA23: 0.27106142 | AB23: 0.41440102 | AC23: 0.57949304 | AD23: 0.83072127 | AG23: 18 | AH23: 44986 | AI23: =$AR$8*F23/AK11+(1-$AR$8)*(AI22+AJ22) -> 210325.69 | AJ23: =$AR$9*(AI23-AI22)+(1-$AR$9)*AJ22 -> 788.31909 | AK23: =$AR$10*F23/AI23+(1-$AR$10)*AK11 -> 0.88257428 | AL23: =(AI23+AM23*AJ23)*AK23 -> 186323.79 | AM23: 1 | AN23: =ABS((F23-AL23)/F23) -> 0.011579253
D24: 19 | E24: 45017 | F24: ='Forecast Validation'!J30 -> 137881 | M24: 0.05 | N24: 0.46321621 | O24: 0.4581569 | P24: 0.45280037 | Q24: 0.447154 | R24: 0.44122511 | S24: 0.43502099 | T24: 0.42854887 | U24: 0.42181594 | V24: 0.41482931 | W24: 0.32321026 | X24: 0.22142537 | Y24: 0.10799353 | Z24: 0.039176292 | AA24: 0.13651125 | AB24: 0.26264483 | AC24: 0.39157292 | AD24: 0.528004 | AG24: 19 | AH24: 45017 | AI24: =$AR$8*F24/AK12+(1-$AR$8)*(AI23+AJ23) -> 211099.83 | AJ24: =$AR$9*(AI24-AI23)+(1-$AR$9)*AJ23 -> 788.27656 | AK24: =$AR$10*F24/AI24+(1-$AR$10)*AK12 -> 0.66254901 | AL24: =(AI24+AM24*AJ24)*AK24 -> 140386.26 | AM24: 1 | AN24: =ABS((F24-AL24)/F24) -> 0.018169706
D25: 20 | E25: 45047 | F25: ='Forecast Validation'!J31 -> 171600 | M25: 0.06 | N25: 0.55333208 | O25: 0.54900605 | P25: 0.54437049 | Q25: 0.53943296 | R25: 0.53420095 | S25: 0.52868193 | T25: 0.52288332 | U25: 0.51681249 | V25: 0.51047678 | W25: 0.42534248 | X25: 0.32858631 | Y25: 0.21972218 | Z25: 0.10392087 | AA25: 0.039821358 | AB25: 0.13326376 | AC25: 0.2500521 | AD25: 0.36477125 | AG25: 20 | AH25: 45047 | AI25: =$AR$8*F25/AK13+(1-$AR$8)*(AI24+AJ24) -> 211894.97 | AJ25: =$AR$9*(AI25-AI24)+(1-$AR$9)*AJ24 -> 788.29715 | AK25: =$AR$10*F25/AI25+(1-$AR$10)*AK13 -> 0.80475726 | AL25: =(AI25+AM25*AJ25)*AK25 -> 171158.41 | AM25: 1 | AN25: =ABS((F25-AL25)/F25) -> 0.0025733819
D26: 21 | E26: 45078 | F26: ='Forecast Validation'!J32 -> 160487 | K26: Mape(-4) | M26: 0.07 | N26: 0.64283393 | O26: 0.63918712 | P26: 0.63521769 | Q26: 0.6309333 | R26: 0.6263416 | S26: 0.6214502 | T26: 0.61626667 | U26: 0.61079853 | V26: 0.60505328 | W26: 0.52565641 | X26: 0.43306651 | Y26: 0.32762444 | Z26: 0.21482019 | AA26: 0.099174363 | AB26: 0.040307941 | AC26: 0.12764608 | AD26: 0.23480388 | AG26: 21 | AH26: 45078 | AI26: =$AR$8*F26/AK14+(1-$AR$8)*(AI25+AJ25) -> 212682.04 | AJ26: =$AR$9*(AI26-AI25)+(1-$AR$9)*AJ25 -> 788.29345 | AK26: =$AR$10*F26/AI26+(1-$AR$10)*AK14 -> 0.75546578 | AL26: =(AI26+AM26*AJ26)*AK26 -> 161269.53 | AM26: 1 | AN26: =ABS((F26-AL26)/F26) -> 0.0048759776
D27: 22 | E27: 45108 | F27: ='Forecast Validation'!J33 -> 117214 | J27: Mape (-3) | M27: 0.08 | N27: 0.73180237 | O27: 0.72879065 | P27: 0.72544269 | Q27: 0.7217663 | R27: 0.71776922 | S27: 0.71345919 | T27: 0.70884391 | U27: 0.70393103 | V27: 0.69872817 | W27: 0.62449064 | X27: 0.53543473 | Y27: 0.43262562 | Z27: 0.32178477 | AA27: 0.20770612 | AB27: 0.094216299 | AC27: 0.04063661 | AD27: 0.12038797 | AG27: 22 | AH27: 45108 | AI27: =$AR$8*F27/AK15+(1-$AR$8)*(AI26+AJ26) -> 213456.27 | AJ27: =$AR$9*(AI27-AI26)+(1-$AR$9)*AJ26 -> 788.25127 | AK27: =$AR$10*F27/AI27+(1-$AR$10)*AK15 -> 0.55686123 | AL27: =(AI27+AM27*AJ27)*AK27 -> 119304.47 | AM27: 1 | AN27: =ABS((F27-AL27)/F27) -> 0.017834626
D28: 23 | E28: 45139 | F28: ='Forecast Validation'!J34 -> 142076 | I28: Mape (-2) | M28: 0.09 | N28: 0.82030195 | O28: 0.81788875 | P28: 0.81512543 | Q28: 0.81201986 | R28: 0.80857993 | S28: 0.80481346 | T28: 0.80072828 | U28: 0.79633214 | V28: 0.7916328 | W28: 0.72209784 | X28: 0.6360989 | Y28: 0.53535785 | Z28: 0.42578462 | AA28: 0.31238105 | AB28: 0.19919852 | AC28: 0.089348913 | AD28: 0.040841092 | AG28: 23 | AH28: 45139 | AI28: =$AR$8*F28/AK16+(1-$AR$8)*(AI27+AJ27) -> 214240.29 | AJ28: =$AR$9*(AI28-AI27)+(1-$AR$9)*AJ27 -> 788.23857 | AK28: =$AR$10*F28/AI28+(1-$AR$10)*AK16 -> 0.66583327 | AL28: =(AI28+AM28*AJ28)*AK28 -> 143173.15 | AM28: 1 | AN28: =ABS((F28-AL28)/F28) -> 0.0077222541
D29: 24 | E29: 45170 | F29: ='Forecast Validation'!J35 -> 174735 | H29: Mape (-1) | AG29: 24 | AH29: 45170 | AI29: =$AR$8*F29/AK17+(1-$AR$8)*(AI28+AJ28) -> 215020.17 | AJ29: =$AR$9*(AI29-AI28)+(1-$AR$9)*AJ28 -> 788.21351 | AK29: =$AR$10*F29/AI29+(1-$AR$10)*AK17 -> 0.81920529 | AL29: =(AI29+AM29*AJ29)*AK29 -> 176791.37 | AM29: 1 | AN29: =ABS((F29-AL29)/F29) -> 0.011768525
C30: 3 | D30: 25 | E30: 45200 | F30: ='Forecast Validation'!J36 -> 194555 | G30: Mape (0) | AF30: 3 | AG30: 25 | AH30: 45200 | AI30: =$AR$8*F30/AK18+(1-$AR$8)*(AI29+AJ29) -> 215821.44 | AJ30: =$AR$9*(AI30-AI29)+(1-$AR$9)*AJ29 -> 788.25268 | AK30: =$AR$10*F30/AI30+(1-$AR$10)*AK18 -> 0.89118802 | AL30: =(AI30+AM30*AJ30)*AK30 -> 193039.97 | AM30: 1 | AN30: =ABS((F30-AL30)/F30) -> 0.00778717 | AO30: Model training with varying h (from Forecast Validation)
D31: 26 | E31: 45231 | F31: ='Forecast Validation'!J37 -> 248927 | AG31: 26 | AH31: 45231 | AI31: =$AR$8*F31/AK19+(1-$AR$8)*(AI30+AJ30) -> 216604.19 | AJ31: =$AR$9*(AI31-AI30)+(1-$AR$9)*AJ30 -> 788.23617 | AK31: =$AR$10*F31/AI31+(1-$AR$10)*AK19 -> 1.1552126 | AL31: =(AI31+AM31*AJ31)*AK31 -> 252045.05 | AM31: =AM30+1 -> 2 | AN31: =ABS((F31-AL31)/F31) -> 0.012525975
D32: 27 | E32: 45261 | F32: ='Forecast Validation'!J38 -> 307644 | AG32: 27 | AH32: 45261 | AI32: =$AR$8*F32/AK20+(1-$AR$8)*(AI31+AJ31) -> 217383.66 | AJ32: =$AR$9*(AI32-AI31)+(1-$AR$9)*AJ31 -> 788.20986 | AK32: =$AR$10*F32/AI32+(1-$AR$10)*AK20 -> 1.427098 | AL32: =(AI32+AM32*AJ32)*AK32 -> 313602.34 | AM32: =AM31+1 -> 3 | AN32: =ABS((F32-AL32)/F32) -> 0.019367639
D33: 28 | E33: 45292 | F33: ='Forecast Validation'!J39 -> 319780.5 | AG33: 28 | AH33: 45292 | AI33: =$AR$8*F33/AK21+(1-$AR$8)*(AI32+AJ32) -> 218180.29 | AJ33: =$AR$9*(AI33-AI32)+(1-$AR$9)*AJ32 -> 788.23512 | AK33: =$AR$10*F33/AI33+(1-$AR$10)*AK21 -> 1.4547887 | AL33: =(AI33+AM33*AJ33)*AK33 -> 321993.08 | AM33: =AM32+1 -> 4 | AN33: =ABS((F33-AL33)/F33) -> 0.006919067
D34: 29 | E34: 45323 | F34: ='Forecast Validation'!J40 -> 211019.5 | AG34: 29 | AH34: 45323 | AI34: =$AR$8*F34/AK22+(1-$AR$8)*(AI33+AJ33) -> 218969.83 | AJ34: =$AR$9*(AI34-AI33)+(1-$AR$9)*AJ33 -> 788.23902 | AK34: =$AR$10*F34/AI34+(1-$AR$10)*AK22 -> 0.96255374 | AL34: =(AI34+AM34*AJ34)*AK34 -> 214563.84 | AM34: =AM33+1 -> 5 | AN34: =ABS((F34-AL34)/F34) -> 0.016796251
D35: 30 | E35: 45352 | F35: ='Forecast Validation'!J41 -> 181870 | AG35: 30 | AH35: 45352 | AI35: =$AR$8*F35/AK23+(1-$AR$8)*(AI34+AJ34) -> 219744.38 | AJ35: =$AR$9*(AI35-AI34)+(1-$AR$9)*AJ34 -> 788.19795 | AK35: =$AR$10*F35/AI35+(1-$AR$10)*AK23 -> 0.83862964 | AL35: =(AI35+AM35*AJ35)*AK35 -> 188250.18 | AM35: =AM34+1 -> 6 | AN35: =ABS((F35-AL35)/F35) -> 0.035081012
D36: 31 | E36: 45383 | F36: ='Forecast Validation'!J42 -> 162943 | AG36: 31 | AH36: 45383 | AI36: =$AR$8*F36/AK24+(1-$AR$8)*(AI35+AJ35) -> 220557.97 | AJ36: =$AR$9*(AI36-AI35)+(1-$AR$9)*AJ35 -> 788.27416 | AK36: =$AR$10*F36/AI36+(1-$AR$10)*AK24 -> 0.72353083 | AL36: =(AI36+AM36*AJ36)*AK36 -> 163572.88 | AM36: =AM35+1 -> 7 | AN36: =ABS((F36-AL36)/F36) -> 0.003865634
D37: 32 | E37: 45413 | F37: ='Forecast Validation'!J43 -> 180578 | AG37: 32 | AH37: 45413 | AI37: =$AR$8*F37/AK25+(1-$AR$8)*(AI36+AJ36) -> 221349.29 | AJ37: =$AR$9*(AI37-AI36)+(1-$AR$9)*AJ36 -> 788.28328 | AK37: =$AR$10*F37/AI37+(1-$AR$10)*AK25 -> 0.81359597 | AL37: =(AI37+AM37*AJ37)*AK37 -> 185219.64 | AM37: =AM36+1 -> 8 | AN37: =ABS((F37-AL37)/F37) -> 0.025704363
D38: 33 | E38: 45444 | F38: ='Forecast Validation'!J44 -> 154104 | AG38: 33 | AH38: 45444 | AI38: =$AR$8*F38/AK26+(1-$AR$8)*(AI37+AJ37) -> 222119.42 | AJ38: =$AR$9*(AI38-AI37)+(1-$AR$9)*AJ37 -> 788.22883 | AK38: =$AR$10*F38/AI38+(1-$AR$10)*AK26 -> 0.70612432 | AL38: =(AI38+AM38*AJ38)*AK38 -> 161853.21 | AM38: =AM37+1 -> 9 | AN38: =ABS((F38-AL38)/F38) -> 0.050285601
D39: 34 | E39: 45474 | F39: ='Forecast Validation'!J45 -> 139177 | AG39: 34 | AH39: 45474 | AI39: =$AR$8*F39/AK27+(1-$AR$8)*(AI38+AJ38) -> 222934.67 | AJ39: =$AR$9*(AI39-AI38)+(1-$AR$9)*AJ38 -> 788.3099 | AK39: =$AR$10*F39/AI39+(1-$AR$10)*AK27 -> 0.61080824 | AL39: =(AI39+AM39*AJ39)*AK39 -> 140985.4 | AM39: =AM38+1 -> 10 | AN39: =ABS((F39-AL39)/F39) -> 0.012993506
D40: 35 | E40: 45505 | F40: ='Forecast Validation'!J46 -> 149026 | AG40: 35 | AH40: 45505 | AI40: =$AR$8*F40/AK28+(1-$AR$8)*(AI39+AJ39) -> 223723.08 | AJ40: =$AR$9*(AI40-AI39)+(1-$AR$9)*AJ39 -> 788.31018 | AK40: =$AR$10*F40/AI40+(1-$AR$10)*AK28 -> 0.66606116 | AL40: =(AI40+AM40*AJ40)*AK40 -> 154788.94 | AM40: =AM39+1 -> 11 | AN40: =ABS((F40-AL40)/F40) -> 0.038670734
D41: 36 | E41: 45536 | F41: ='Forecast Validation'!J47 -> 170577 | AG41: 36 | AH41: 45536 | AI41: =$AR$8*F41/AK29+(1-$AR$8)*(AI40+AJ40) -> 224495.1 | AJ41: =$AR$9*(AI41-AI40)+(1-$AR$9)*AJ40 -> 788.26132 | AK41: =$AR$10*F41/AI41+(1-$AR$10)*AK29 -> 0.77170109 | AL41: =(AI41+AM41*AJ41)*AK41 -> 180542.74 | AM41: =AM40+1 -> 12 | AN41: =ABS((F41-AL41)/F41) -> 0.058423704
AF42: 4 | AG42: 37 | AH42: 45566 | AI42: =AI30 -> 215821.44 | AJ42: =AJ30 -> 788.25268 | AK42: =AVERAGE(AK6,AK18,AK30) -> 0.86706014 | AL42: =(AI42+AM42*AJ42)*AK42 -> 196015.18 | AM42: =AM41+1 -> 13 | AN42: n/a | AO42: Prediction for the next 18 months
AG43: 38 | AH43: 45597 | AI43: =AI31 -> 216604.19 | AJ43: =AJ31 -> 788.23617 | AK43: =AVERAGE(AK7,AK19,AK31) -> 1.1725969 | AL43: =(AI43+AM43*AJ43)*AK43 -> 266929.37 | AM43: =AM42+1 -> 14
AG44: 39 | AH44: 45627 | AI44: =AI32 -> 217383.66 | AJ44: =AJ32 -> 788.20986 | AK44: =AVERAGE(AK8,AK20,AK32) -> 1.4885263 | AL44: =(AI44+AM44*AJ44)*AK44 -> 341180.35 | AM44: =AM43+1 -> 15
AG45: 40 | AH45: 45658 | AI45: =AI33 -> 218180.29 | AJ45: =AJ33 -> 788.23512 | AK45: =AVERAGE(AK9,AK21,AK33) -> 1.4134135 | AL45: =(AI45+AM45*AJ45)*AK45 -> 326204.59 | AM45: =AM44+1 -> 16
AG46: 41 | AH46: 45689 | AI46: =AI34 -> 218969.83 | AJ46: =AJ34 -> 788.23902 | AK46: =AVERAGE(AK10,AK22,AK34) -> 0.94372111 | AL46: =(AI46+AM46*AJ46)*AK46 -> 219292.37 | AM46: =AM45+1 -> 17
AG47: 42 | AH47: 45717 | AI47: =AI35 -> 219744.38 | AJ47: =AJ35 -> 788.19795 | AK47: =AVERAGE(AK11,AK23,AK35) -> 0.87703603 | AL47: =(AI47+AM47*AJ47)*AK47 -> 205166.74 | AM47: =AM46+1 -> 18
AG48: 43 | AH48: 45748 | AI48: =AI36 -> 220557.97 | AJ48: =AJ36 -> 788.27416 | AK48: =AVERAGE(AK12,AK24,AK36) -> 0.69540107 | AL48: =(AI48+AM48*AJ48)*AK48 -> 163791.42 | AM48: =AM47+1 -> 19
AG49: 44 | AH49: 45778 | AI49: =AI37 -> 221349.29 | AJ49: =AJ37 -> 788.28328 | AK49: =AVERAGE(AK13,AK25,AK37) -> 0.80093297 | AL49: =(AI49+AM49*AJ49)*AK49 -> 189913.19 | AM49: =AM48+1 -> 20
AG50: 45 | AH50: 45809 | AI50: =AI38 -> 222119.42 | AJ50: =AJ38 -> 788.22883 | AK50: =AVERAGE(AK14,AK26,AK38) -> 0.74019097 | AL50: =(AI50+AM50*AJ50)*AK50 -> 176663.03 | AM50: =AM49+1 -> 21
AG51: 46 | AH51: 45839 | AI51: =AI39 -> 222934.67 | AJ51: =AJ39 -> 788.3099 | AK51: =AVERAGE(AK15,AK27,AK39) -> 0.58515963 | AL51: =(AI51+AM51*AJ51)*AK51 -> 140600.69 | AM51: =AM50+1 -> 22
AG52: 47 | AH52: 45870 | AI52: =AI40 -> 223723.08 | AJ52: =AJ40 -> 788.31018 | AK52: =AVERAGE(AK16,AK28,AK40) -> 0.66947104 | AL52: =(AI52+AM52*AJ52)*AK52 -> 161914.39 | AM52: =AM51+1 -> 23
AG53: 48 | AH53: 45901 | AI53: =AI41 -> 224495.1 | AJ53: =AJ41 -> 788.26132 | AK53: =AVERAGE(AK17,AK29,AK41) -> 0.81211804 | AL53: =(AI53+AM53*AJ53)*AK53 -> 197680.39 | AM53: =AM52+1 -> 24
AF54: 5 | AG54: 49 | AH54: 45931 | AI54: =AI42 -> 215821.44 | AJ54: =AJ42 -> 788.25268 | AK54: =AVERAGE(AK6,AK18,AK30,AK42) -> 0.86706014 | AL54: =(AI54+AM54*AJ54)*AK54 -> 204216.73 | AM54: =AM53+1 -> 25
AG55: 50 | AH55: 45962 | AI55: =AI43 -> 216604.19 | AJ55: =AJ43 -> 788.23617 | AK55: =AVERAGE(AK7,AK19,AK31,AK43) -> 1.1725969 | AL55: =(AI55+AM55*AJ55)*AK55 -> 278020.77 | AM55: =AM54+1 -> 26
AG56: 51 | AH56: 45992 | AI56: =AI44 -> 217383.66 | AJ56: =AJ44 -> 788.20986 | AK56: =AVERAGE(AK8,AK20,AK32,AK44) -> 1.4885263 | AL56: =(AI56+AM56*AJ56)*AK56 -> 355259.6 | AM56: =AM55+1 -> 27
AG57: 52 | AH57: 46023 | AI57: =AI45 -> 218180.29 | AJ57: =AJ45 -> 788.23512 | AK57: =AVERAGE(AK9,AK21,AK33,AK45) -> 1.4134135 | AL57: =(AI57+AM57*AJ57)*AK57 -> 339573.82 | AM57: =AM56+1 -> 28
AG58: 53 | AH58: 46054 | AI58: =AI46 -> 218969.83 | AJ58: =AJ46 -> 788.23902 | AK58: =AVERAGE(AK10,AK22,AK34,AK46) -> 0.94372111 | AL58: =(AI58+AM58*AJ58)*AK58 -> 228218.91 | AM58: =AM57+1 -> 29
AG59: 54 | AH59: 46082 | AI59: =AI47 -> 219744.38 | AJ59: =AJ47 -> 788.19795 | AK59: =AVERAGE(AK11,AK23,AK35,AK47) -> 0.87703603 | AL59: =(AI59+AM59*AJ59)*AK59 -> 213462.07 | AM59: =AM58+1 -> 30

Sheet Aggregate Planning
A1: Assumptions
H2: 1 | I2: Aggregate Planning
P3: Hybrid | R3: Level | T3: Chase
L4: Costs | O4: Per Unit | P4: Units | Q4: Total | R4: Units | S4: Total | T4: Units | U4: Total
L5: Regular Time Labor Cost | O5: 5 | P5: =SUM(J28:V28) -> 2925000 | Q5: =$O5*P5 -> 14625000 | R5: =SUM(J44:V44) -> 3185000 | S5: =$O5*R5 -> 15925000 | T5: =SUM(J61:V61) -> 2822677 | U5: =$O5*T5 -> 14113385
L6: Overtime/Subcontracting | O6: 9 | P6: =SUM(J29:V29) -> 0 | Q6: =$O6*P6 -> 0 | R6: =SUM(J45:V45) -> 0 | S6: =$O6*R6 -> 0 | T6: =SUM(J62:V62) -> 0 | U6: =$O6*T6 -> 0
I7: Beginning Inventory | J7: =AVERAGE('Parameters Optimisation'!AL30:AL41) -> 205871.44 | L7: Inventory Holding Cost | O7: 5 | P7: =SUM(J21:V21) -> 2649921.2 | Q7: =$O7*P7 -> 13249606 | R7: =SUM(J37:V37) -> 1204152.2 | S7: =$O7*R7 -> 6020760.8 | T7: =SUM(J54:V54) -> 2676311.2 | U7: =$O7*T7 -> 13381556
I8: Beginning Workforce | J8: 2150 | L8: Backorders | O8: 10 | P8: =SUM(J22:V22) -> 0 | Q8: =$O8*P8 -> 0 | R8: =SUM(J38:V38) -> 213372.45 | S8: =$O8*R8 -> 2133724.5 | T8: =SUM(J55:V55) -> 0 | U8: =$O8*T8 -> 0
I9: Labor Standard (units/worker) | J9: 100 | L9: Hiring | O9: 500 | P9: =SUM(J25:V25) -> 400 | Q9: =$O9*P9 -> 200000 | R9: =SUM(J41:V41) -> 300 | S9: =$O9*R9 -> 150000 | T9: =SUM(J58:V58) -> 2159.18 | U9: =$O9*T9 -> 1079590
L10: Layoff | O10: 800 | P10: =SUM(J26:V26) -> 500 | Q10: =$O10*P10 -> 400000 | R10: =SUM(J42:V42) -> 0 | S10: =$O10*R10 -> 0 | T10: =SUM(J59:V59) -> 2267.01 | U10: =$O10*T10 -> 1813608
O11: Total Costs | Q11: =SUM(Q5:Q10) -> 28474606 | R11: Total Costs | S11: =SUM(S5:S10) -> 24229485 | T11: Total Costs | U11: =SUM(U5:U10) -> 30388139
H13: 2 | I13: Period | J13: 45566 | K13: 45597 | L13: 45627 | M13: 45658 | N13: 45689 | O13: 45717 | P13: 45748 | Q13: 45778 | R13: 45809 | S13: 45839 | T13: 45870 | U13: 45901 | V13: 45931
I14: Demand | J14: ='Parameters Optimisation'!AL42 -> 196015.18 | K14: ='Parameters Optimisation'!AL43 -> 266929.37 | L14: ='Parameters Optimisation'!AL44 -> 341180.35 | M14: ='Parameters Optimisation'!AL45 -> 326204.59 | N14: ='Parameters Optimisation'!AL46 -> 219292.37 | O14: ='Parameters Optimisation'!AL46 -> 219292.37 | P14: ='Parameters Optimisation'!AL48 -> 163791.42 | Q14: ='Parameters Optimisation'!AL49 -> 189913.19 | R14: ='Parameters Optimisation'!AL50 -> 176663.03 | S14: ='Parameters Optimisation'!AL51 -> 140600.69 | T14: ='Parameters Optimisation'!AL52 -> 161914.39 | U14: ='Parameters Optimisation'!AL53 -> 197680.39 | V14: ='Parameters Optimisation'!AL54 -> 204216.73
I15: Cumulative Demand | J15: =J14 -> 196015.18 | K15: =J15+K14 -> 462944.56 | L15: =K15+L14 -> 804124.91 | M15: =L15+M14 -> 1130329.5 | N15: =M15+N14 -> 1349621.9 | O15: =N15+O14 -> 1568914.2 | P15: =O15+P14 -> 1732705.7 | Q15: =P15+Q14 -> 1922618.8 | R15: =Q15+R14 -> 2099281.9 | ... V15: =U15+V14 -> 2803694.1
I16: Net Cumulative Demand | J16: =J15-$J$7 -> -9856.2548 | K16: =K15-$J$7 -> 257073.12 | L16: =L15-$J$7 -> 598253.47 | M16: =M15-$J$7 -> 924458.06 | N16: =N15-$J$7 -> 1143750.4 | O16: =O15-$J$7 -> 1363042.8 | P16: =P15-$J$7 -> 1526834.2 | Q16: =Q15-$J$7 -> 1716747.4 | ... V16: =V15-$J$7 -> 2597822.6
H18: 3H | I18: Production/Inventory Planning | J18: Oct | K18: Nov | L18: Dec | M18: Jan | N18: Feb | O18: Mar | P18: Apr | Q18: May | R18: Jun | S18: Jul | T18: Aug | U18: Sep | V18: Oct | W18: Hybrid
I19: Production | J19: =J28 -> 215000 | K19: =K28 -> 255000 | L19: =L28 -> 255000 | M19: =M28 -> 255000 | N19: =N28 -> 255000 | O19: =O28 -> 255000 | P19: =P28 -> 205000 | Q19: =Q28 -> 205000 | ... V19: =V28 -> 205000
I20: Cumulative Production | J20: =J19 -> 215000 | K20: =J20+K19 -> 470000 | L20: =K20+L19 -> 725000 | M20: =L20+M19 -> 980000 | N20: =M20+N19 -> 1235000 | O20: =N20+O19 -> 1490000 | P20: =O20+P19 -> 1695000 | Q20: =P20+Q19 -> 1900000 | R20: =Q20+R19 -> 2105000 | ... V20: =U20+V19 -> 2925000
I21: Inventory (Excess Units) | J21: =MAX(0,J20-J$16) -> 224856.25 | K21: =MAX(0,K20-K$16) -> 212926.88 | L21: =MAX(0,L20-L$16) -> 126746.53 | M21: =MAX(0,M20-M$16) -> 55541.943 | N21: =MAX(0,N20-N$16) -> 91249.572 | O21: =MAX(0,O20-O$16) -> 126957.2 | P21: =MAX(0,P20-P$16) -> 168165.78 | Q21: =MAX(0,Q20-Q$16) -> 183252.6 | ... V21: =MAX(0,V20-V$16) -> 327177.36
I22: Backorders (Units Short) | J22: =MAX(0,J$16-J20) -> 0 | K22: =MAX(0,K$16-K20) -> 0 | L22: =MAX(0,L$16-L20) -> 0 | M22: =MAX(0,M$16-M20) -> 0 | N22: =MAX(0,N$16-N20) -> 0 | O22: =MAX(0,O$16-O20) -> 0 | P22: =MAX(0,P$16-P20) -> 0 | Q22: =MAX(0,Q$16-Q20) -> 0 | ... V22: =MAX(0,V$16-V20) -> 0
H24: 4H | I24: Capacity Planning | J24: Oct | K24: Nov | L24: Dec | M24: Jan | N24: Feb | O24: Mar | P24: Apr | Q24: May | R24: Jun | S24: Jul | T24: Aug | U24: Sep | V24: Oct
I25: Workers Hired | K25: 400
I26: Workers Layed Off | P26: 500
I27: Workforce Available | J27: =$J$8+J25-J26 -> 2150 | K27: =J27+K25-K26 -> 2550 | L27: =K27+L25-L26 -> 2550 | M27: =L27+M25-M26 -> 2550 | N27: =M27+N25-N26 -> 2550 | O27: =N27+O25-O26 -> 2550 | P27: =O27+P25-P26 -> 2050 | Q27: =P27+Q25-Q26 -> 2050 | R27: =Q27+R25-R26 -> 2050 | ... V27: =U27+V25-V26 -> 2050
I28: Regular Time Capacity (units) | J28: =$J$9*J27 -> 215000 | K28: =$J$9*K27 -> 255000 | L28: =$J$9*L27 -> 255000 | M28: =$J$9*M27 -> 255000 | N28: =$J$9*N27 -> 255000 | O28: =$J$9*O27 -> 255000 | P28: =$J$9*P27 -> 205000 | Q28: =$J$9*Q27 -> 205000 | ... V28: =$J$9*V27 -> 205000
I29: Overtime/Subcontracting (units) | J29: =MAX(0,J19-J28) -> 0 | K29: =MAX(0,K19-K28) -> 0 | L29: =MAX(0,L19-L28) -> 0 | M29: =MAX(0,M19-M28) -> 0 | N29: =MAX(0,N19-N28) -> 0 | O29: =MAX(0,O19-O28) -> 0 | P29: =MAX(0,P19-P28) -> 0 | Q29: =MAX(0,Q19-Q28) -> 0 | ... V29: =MAX(0,V19-V28) -> 0
I30: Total Production Capacity (units) | J30: =J28+J29 -> 215000 | K30: =K28+K29 -> 255000 | L30: =L28+L29 -> 255000 | M30: =M28+M29 -> 255000 | N30: =N28+N29 -> 255000 | O30: =O28+O29 -> 255000 | P30: =P28+P29 -> 205000 | Q30: =Q28+Q29 -> 205000 | ... V30: =V28+V29 -> 205000
I31: Total Monthly Costs | J31: =J28*$O$5+J29*$O$6+J25*$O$9+J26*$O$10+J22*$O$8 -> 1075000 | K31: =K28*$O$5+K29*$O$6+K25*$O$9+K26*$O$10+K22*$O$8 -> 1475000 | L31: =L28*$O$5+L29*$O$6+L25*$O$9+L26*$O$10+L22*$O$8 -> 1275000 | M31: =M28*$O$5+M29*$O$6+M25*$O$9+M26*$O$10+M22*$O$8 -> 1275000 | N31: =N28*$O$5+N29*$O$6+N25*$O$9+N26*$O$10+N22*$O$8 -> 1275000 | O31: =O28*$O$5+O29*$O$6+O25*$O$9+O26*$O$10+O22*$O$8 -> 1275000 | P31: =P28*$O$5+P29*$O$6+P25*$O$9+P26*$O$10+P22*$O$8 -> 1425000 | Q31: =Q28*$O$5+Q29*$O$6+Q25*$O$9+Q26*$O$10+Q22*$O$8 -> 1025000 | ... V31: =V28*$O$5+V29*$O$6+V25*$O$9+V26*$O$10+V22*$O$8 -> 1025000
I32: Cumulative Costs | J32: =J31 -> 1075000 | K32: =K31+J32 -> 2550000 | L32: =L31+K32 -> 3825000 | M32: =M31+L32 -> 5100000 | N32: =N31+M32 -> 6375000 | O32: =O31+N32 -> 7650000 | P32: =P31+O32 -> 9075000 | Q32: =Q31+P32 -> 10100000 | R32: =R31+Q32 -> 11125000 | ... V32: =V31+U32 -> 15225000
H34: 3L | I34: Production/Inventory Planning | J34: Oct | K34: Nov | L34: Dec | M34: Jan | N34: Feb | O34: Mar | P34: Apr | Q34: May | R34: Jun | S34: Jul | T34: Aug | U34: Sep | V34: Oct | W34: Level
I35: Production | J35: =AVERAGE($J$14:$V$14) -> 215668.78 | K35: =AVERAGE($J$14:$V$14) -> 215668.78 | L35: =AVERAGE($J$14:$V$14) -> 215668.78 | M35: =AVERAGE($J$14:$V$14) -> 215668.78 | N35: =AVERAGE($J$14:$V$14) -> 215668.78 | O35: =AVERAGE($J$14:$V$14) -> 215668.78 | P35: =AVERAGE($J$14:$V$14) -> 215668.78 | Q35: =AVERAGE($J$14:$V$14) -> 215668.78 | ... V35: =AVERAGE($J$14:$V$14) -> 215668.78
I36: Cumulative Production | J36: =J35 -> 215668.78 | K36: =J36+K35 -> 431337.55 | L36: =K36+L35 -> 647006.33 | M36: =L36+M35 -> 862675.1 | N36: =M36+N35 -> 1078343.9 | O36: =N36+O35 -> 1294012.7 | P36: =O36+P35 -> 1509681.4 | Q36: =P36+Q35 -> 1725350.2 | R36: =Q36+R35 -> 1941019 | ... V36: =U36+V35 -> 2803694.1
I37: Inventory (Excess Units) | J37: =MAX(0,J36-J$16) -> 225525.03 | K37: =MAX(0,K36-K$16) -> 174264.43 | L37: =MAX(0,L36-L$16) -> 48752.86 | M37: =MAX(0,M36-M$16) -> 0 | N37: =MAX(0,N36-N$16) -> 0 | O37: =MAX(0,O36-O$16) -> 0 | P37: =MAX(0,P36-P$16) -> 0 | Q37: =MAX(0,Q36-Q$16) -> 8602.7969 | ... V37: =MAX(0,V36-V$16) -> 205871.44
I38: Backorders (Units Short) | J38: =MAX(0,J$16-J36) -> 0 | K38: =MAX(0,K$16-K36) -> 0 | L38: =MAX(0,L$16-L36) -> 0 | M38: =MAX(0,M$16-M36) -> 61782.956 | N38: =MAX(0,N$16-N36) -> 65406.553 | O38: =MAX(0,O$16-O36) -> 69030.149 | P38: =MAX(0,P$16-P36) -> 17152.792 | Q38: =MAX(0,Q$16-Q36) -> 0 | ... V38: =MAX(0,V$16-V36) -> 0
H40: 4L | I40: Capacity Planning | J40: Oct | K40: Nov | L40: Dec | M40: Jan | N40: Feb | O40: Mar | P40: Apr | Q40: May | R40: Jun | S40: Jul | T40: Aug | U40: Sep | V40: Oct
I41: Workers Hired | J41: 300 | K41: 0 | L41: 0 | M41: 0 | N41: 0 | O41: 0 | P41: 0 | Q41: 0 | R41: 0 | S41: 0 | T41: 0 | U41: 0 | V41: 0
I42: Workers Layed Off | J42: 0 | K42: 0 | L42: 0 | M42: 0 | N42: 0 | O42: 0 | P42: 0 | Q42: 0 | R42: 0 | S42: 0 | T42: 0 | U42: 0 | V42: 0
I43: Workforce Available | J43: =$J$8+J41-J42 -> 2450 | K43: =J43+K41-K42 -> 2450 | L43: =K43+L41-L42 -> 2450 | M43: =L43+M41-M42 -> 2450 | N43: =M43+N41-N42 -> 2450 | O43: =N43+O41-O42 -> 2450 | P43: =O43+P41-P42 -> 2450 | Q43: =P43+Q41-Q42 -> 2450 | R43: =Q43+R41-R42 -> 2450 | ... V43: =U43+V41-V42 -> 2450
I44: Regular Time Capacity (units) | J44: =$J$9*J43 -> 245000 | K44: =$J$9*K43 -> 245000 | L44: =$J$9*L43 -> 245000 | M44: =$J$9*M43 -> 245000 | N44: =$J$9*N43 -> 245000 | O44: =$J$9*O43 -> 245000 | P44: =$J$9*P43 -> 245000 | Q44: =$J$9*Q43 -> 245000 | ... V44: =$J$9*V43 -> 245000
I45: Overtime/Subcontracting (units) | J45: =MAX(0,J35-J44) -> 0 | K45: =MAX(0,K35-K44) -> 0 | L45: =MAX(0,L35-L44) -> 0 | M45: =MAX(0,M35-M44) -> 0 | N45: =MAX(0,N35-N44) -> 0 | O45: =MAX(0,O35-O44) -> 0 | P45: =MAX(0,P35-P44) -> 0 | Q45: =MAX(0,Q35-Q44) -> 0 | ... V45: =MAX(0,V35-V44) -> 0
I46: Total Production Capacity (units) | J46: =J44+J45 -> 245000 | K46: =K44+K45 -> 245000 | L46: =L44+L45 -> 245000 | M46: =M44+M45 -> 245000 | N46: =N44+N45 -> 245000 | O46: =O44+O45 -> 245000 | P46: =P44+P45 -> 245000 | Q46: =Q44+Q45 -> 245000 | ... V46: =V44+V45 -> 245000
I47: Total Monthly Costs | J47: =J44*$O$5+J45*$O$6+J41*$O$9+J42*$O$10+J38*$O$8 -> 1375000 | K47: =K44*$O$5+K45*$O$6+K41*$O$9+K42*$O$10+K38*$O$8 -> 1225000 | L47: =L44*$O$5+L45*$O$6+L41*$O$9+L42*$O$10+L38*$O$8 -> 1225000 | M47: =M44*$O$5+M45*$O$6+M41*$O$9+M42*$O$10+M38*$O$8 -> 1842829.6 | N47: =N44*$O$5+N45*$O$6+N41*$O$9+N42*$O$10+N38*$O$8 -> 1879065.5 | O47: =O44*$O$5+O45*$O$6+O41*$O$9+O42*$O$10+O38*$O$8 -> 1915301.5 | P47: =P44*$O$5+P45*$O$6+P41*$O$9+P42*$O$10+P38*$O$8 -> 1396527.9 | Q47: =Q44*$O$5+Q45*$O$6+Q41*$O$9+Q42*$O$10+Q38*$O$8 -> 1225000 | ... V47: =V44*$O$5+V45*$O$6+V41*$O$9+V42*$O$10+V38*$O$8 -> 1225000
I48: Cumulative Costs | J48: =J47 -> 1375000 | K48: =K47+J48 -> 2600000 | L48: =L47+K48 -> 3825000 | M48: =M47+L48 -> 5667829.6 | N48: =N47+M48 -> 7546895.1 | O48: =O47+N48 -> 9462196.6 | P48: =P47+O48 -> 10858725 | Q48: =Q47+P48 -> 12083725 | R48: =R47+Q48 -> 13308725 | ... V48: =V47+U48 -> 18208725
H51: 3C | I51: Production/Inventory Planning | J51: Oct | K51: Nov | L51: Dec | M51: Jan | N51: Feb | O51: Mar | P51: Apr | Q51: May | R51: Jun | S51: Jul | T51: Aug | U51: Sep | V51: Oct | W51: Chase
I52: Production | J52: =ROUND(J14,0) -> 196015 | K52: =ROUND(K14,0) -> 266929 | L52: =ROUND(L14,0) -> 341180 | M52: =ROUND(M14,0) -> 326205 | N52: =ROUND(N14,0) -> 219292 | O52: =ROUND(O14,0) -> 219292 | P52: =ROUND(P14,0) -> 163791 | Q52: =ROUND(Q14,0) -> 189913 | ... V52: =ROUND(V14,0) -> 204217
I53: Cumulative Production | J53: =J52 -> 196015 | K53: =J53+K52 -> 462944 | L53: =K53+L52 -> 804124 | M53: =L53+M52 -> 1130329 | N53: =M53+N52 -> 1349621 | O53: =N53+O52 -> 1568913 | P53: =O53+P52 -> 1732704 | Q53: =P53+Q52 -> 1922617 | R53: =Q53+R52 -> 2099280 | ... V53: =U53+V52 -> 2803692
I54: Inventory (Excess Units) | J54: =MAX(0,J53-J$16) -> 205871.25 | K54: =MAX(0,K53-K$16) -> 205870.88 | L54: =MAX(0,L53-L$16) -> 205870.53 | M54: =MAX(0,M53-M$16) -> 205870.94 | N54: =MAX(0,N53-N$16) -> 205870.57 | O54: =MAX(0,O53-O$16) -> 205870.2 | P54: =MAX(0,P53-P$16) -> 205869.78 | Q54: =MAX(0,Q53-Q$16) -> 205869.6 | ... V54: =MAX(0,V53-V$16) -> 205869.36
I55: Backorders (Units Short) | J55: =MAX(0,J$16-J53) -> 0 | K55: =MAX(0,K$16-K53) -> 0 | L55: =MAX(0,L$16-L53) -> 0 | M55: =MAX(0,M$16-M53) -> 0 | N55: =MAX(0,N$16-N53) -> 0 | O55: =MAX(0,O$16-O53) -> 0 | P55: =MAX(0,P$16-P53) -> 0 | Q55: =MAX(0,Q$16-Q53) -> 0 | ... V55: =MAX(0,V$16-V53) -> 0
H57: 4C | I57: Capacity Planning | J57: Oct | K57: Nov | L57: Dec | M57: Jan | N57: Feb | O57: Mar | P57: Apr | Q57: May | R57: Jun | S57: Jul | T57: Aug | U57: Sep | V57: Oct
I58: Workers Hired | J58: 0 | K58: =MAX(0,(K52-J61)/$J$9) -> 519.29 | L58: =MAX(0,(L52-K61)/$J$9) -> 742.51 | M58: =MAX(0,(M52-L61)/$J$9) -> 0 | N58: =MAX(0,(N52-M61)/$J$9) -> 0 | O58: =MAX(0,(O52-N61)/$J$9) -> 0 | P58: =MAX(0,(P52-O61)/$J$9) -> 0 | Q58: =MAX(0,(Q52-P61)/$J$9) -> 261.22 | R58: =MAX(0,(R52-Q61)/$J$9) -> 0 | ... V58: =MAX(0,(V52-U61)/$J$9) -> 65.37
I59: Workers Layed Off | J59: 0 | K59: =ABS(MIN(0,(K52-J61)/$J$9)) -> 0 | L59: =ABS(MIN(0,(L52-K61)/$J$9)) -> 0 | M59: =ABS(MIN(0,(M52-L61)/$J$9)) -> 149.75 | N59: =ABS(MIN(0,(N52-M61)/$J$9)) -> 1069.13 | O59: =ABS(MIN(0,(O52-N61)/$J$9)) -> 0 | P59: =ABS(MIN(0,(P52-O61)/$J$9)) -> 555.01 | Q59: =ABS(MIN(0,(Q52-P61)/$J$9)) -> 0 | R59: =ABS(MIN(0,(R52-Q61)/$J$9)) -> 132.5 | ... V59: =ABS(MIN(0,(V52-U61)/$J$9)) -> 0
I60: Workforce Available | J60: =$J$8+J58-J59 -> 2150 | K60: =J60+K58-K59 -> 2669.29 | L60: =K60+L58-L59 -> 3411.8 | M60: =L60+M58-M59 -> 3262.05 | N60: =M60+N58-N59 -> 2192.92 | O60: =N60+O58-O59 -> 2192.92 | P60: =O60+P58-P59 -> 1637.91 | Q60: =P60+Q58-Q59 -> 1899.13 | R60: =Q60+R58-R59 -> 1766.63 | ... V60: =U60+V58-V59 -> 2042.17
I61: Regular Time Capacity (units) | J61: =$J$9*J60 -> 215000 | K61: =$J$9*K60 -> 266929 | L61: =$J$9*L60 -> 341180 | M61: =$J$9*M60 -> 326205 | N61: =$J$9*N60 -> 219292 | O61: =$J$9*O60 -> 219292 | P61: =$J$9*P60 -> 163791 | Q61: =$J$9*Q60 -> 189913 | ... V61: =$J$9*V60 -> 204217
I62: Overtime/Subcontracting (units) | J62: =MAX(0,J52-J61) -> 0 | K62: =MAX(0,K52-K61) -> 0 | L62: =MAX(0,L52-L61) -> 0 | M62: =MAX(0,M52-M61) -> 0 | N62: =MAX(0,N52-N61) -> 0 | O62: =MAX(0,O52-O61) -> 0 | P62: =MAX(0,P52-P61) -> 0 | Q62: =MAX(0,Q52-Q61) -> 0 | ... V62: =MAX(0,V52-V61) -> 0
I63: Total Production Capacity (units) | J63: =J61+J62 -> 215000 | K63: =K61+K62 -> 266929 | L63: =L61+L62 -> 341180 | M63: =M61+M62 -> 326205 | N63: =N61+N62 -> 219292 | O63: =O61+O62 -> 219292 | P63: =P61+P62 -> 163791 | Q63: =Q61+Q62 -> 189913 | ... V63: =V61+V62 -> 204217
I64: Total Cost | J64: =J61*$O$5+J62*$O$6+J58*$O$9+J59*$O$10+J55*$O$8 -> 1075000 | K64: =K61*$O$5+K62*$O$6+K58*$O$9+K59*$O$10+K55*$O$8 -> 1594290 | L64: =L61*$O$5+L62*$O$6+L58*$O$9+L59*$O$10+L55*$O$8 -> 2077155 | M64: =M61*$O$5+M62*$O$6+M58*$O$9+M59*$O$10+M55*$O$8 -> 1750825 | N64: =N61*$O$5+N62*$O$6+N58*$O$9+N59*$O$10+N55*$O$8 -> 1951764 | O64: =O61*$O$5+O62*$O$6+O58*$O$9+O59*$O$10+O55*$O$8 -> 1096460 | P64: =P61*$O$5+P62*$O$6+P58*$O$9+P59*$O$10+P55*$O$8 -> 1262963 | Q64: =Q61*$O$5+Q62*$O$6+Q58*$O$9+Q59*$O$10+Q55*$O$8 -> 1080175 | ... V64: =V61*$O$5+V62*$O$6+V58*$O$9+V59*$O$10+V55*$O$8 -> 1053770
I65: Cumulative Costs | J65: =J64 -> 1075000 | K65: =K64+J65 -> 2669290 | L65: =L64+K65 -> 4746445 | M65: =M64+L65 -> 6497270 | N65: =N64+M65 -> 8449034 | O65: =O64+N65 -> 9545494 | P65: =P64+O65 -> 10808457 | Q65: =Q64+P65 -> 11888632 | R65: =R64+Q65 -> 12877947 | ... V65: =V64+U65 -> 17006583

Sheet Initial MPS and RCCP
A1: Assumptions
D3: Initial Inventory | E3: ='Aggregate Planning'!J54 -> 205871.25
D4: Security Inventory | E4: =E3*0.2 -> 41174.251
C7: MPS | D7: Period | E7: Nov | I7: Dec | M7: Jan | Q7: Feb | U7: Mar | Y7: Apr | AC7: May | AG7: Jun | AK7: Jul | AO7: Aug | AS7: Sep | AW7: Oct
D8: Week | E8: 1 | F8: =E8+1 -> 2 | G8: =F8+1 -> 3 | H8: =G8+1 -> 4 | I8: =H8+1 -> 5 | J8: =I8+1 -> 6 | K8: =J8+1 -> 7 | L8: =K8+1 -> 8 | M8: =L8+1 -> 9 | ... AZ8: =AY8+1 -> 48
D9: Allocated Demand | E9: ='Aggregate Planning'!$K$14/4 -> 66732.343 | F9: ='Aggregate Planning'!$K$14/4 -> 66732.343 | G9: ='Aggregate Planning'!$K$14/4 -> 66732.343 | H9: ='Aggregate Planning'!$K$14/4 -> 66732.343 | I9: ='Aggregate Planning'!$L$14/4 -> 85295.087 | J9: ='Aggregate Planning'!$L$14/4 -> 85295.087 | K9: ='Aggregate Planning'!$L$14/4 -> 85295.087 | L9: ='Aggregate Planning'!$L$14/4 -> 85295.087 | M9: ='Aggregate Planning'!$M$14/4 -> 81551.148 | N9: ='Aggregate Planning'!$M$14/4 -> 81551.148 | O9: ='Aggregate Planning'!$M$14/4 -> 81551.148 | P9: ='Aggregate Planning'!$M$14/4 -> 81551.148 | Q9: ='Aggregate Planning'!$N$14/4 -> 54823.093 | R9: ='Aggregate Planning'!$N$14/4 -> 54823.093 | S9: ='Aggregate Planning'!$N$14/4 -> 54823.093 | T9: ='Aggregate Planning'!$N$14/4 -> 54823.093 | U9: ='Aggregate Planning'!$O$14/4 -> 54823.093 | V9: ='Aggregate Planning'!$O$14/4 -> 54823.093 | W9: ='Aggregate Planning'!$O$14/4 -> 54823.093 | X9: ='Aggregate Planning'!$O$14/4 -> 54823.093 | Y9: ='Aggregate Planning'!$P$14/4 -> 40947.854 | Z9: ='Aggregate Planning'!$P$14/4 -> 40947.854 | AA9: ='Aggregate Planning'!$P$14/4 -> 40947.854 | AB9: ='Aggregate Planning'!$P$14/4 -> 40947.854 | AC9: ='Aggregate Planning'!$Q$14/4 -> 47478.297 | AD9: ='Aggregate Planning'!$Q$14/4 -> 47478.297 | AE9: ='Aggregate Planning'!$Q$14/4 -> 47478.297 | AF9: ='Aggregate Planning'!$Q$14/4 -> 47478.297 | AG9: ='Aggregate Planning'!$R$14/4 -> 44165.757 | AH9: ='Aggregate Planning'!$R$14/4 -> 44165.757 | AI9: ='Aggregate Planning'!$R$14/4 -> 44165.757 | AJ9: ='Aggregate Planning'!$R$14/4 -> 44165.757 | AK9: ='Aggregate Planning'!$S$14/4 -> 35150.172 | AL9: ='Aggregate Planning'!$S$14/4 -> 35150.172 | AM9: ='Aggregate Planning'!$S$14/4 -> 35150.172 | AN9: ='Aggregate Planning'!$S$14/4 -> 35150.172 | AO9: ='Aggregate Planning'!$T$14/4 -> 40478.598 | AP9: ='Aggregate Planning'!$T$14/4 -> 40478.598 | AQ9: ='Aggregate Planning'!$T$14/4 -> 40478.598 | AR9: ='Aggregate Planning'!$T$14/4 -> 40478.598 | AS9: ='Aggregate Planning'!$U$14/4 -> 49420.098 | AT9: ='Aggregate Planning'!$U$14/4 -> 49420.098 | AU9: ='Aggregate Planning'!$U$14/4 -> 49420.098 | AV9: ='Aggregate Planning'!$U$14/4 -> 49420.098 | AW9: ='Aggregate Planning'!$V$14/4 -> 51054.184 | AX9: ='Aggregate Planning'!$V$14/4 -> 51054.184 | AY9: ='Aggregate Planning'!$V$14/4 -> 51054.184 | AZ9: ='Aggregate Planning'!$V$14/4 -> 51054.184
D10: Initial MPS | E10: 63000 | F10: 63000 | G10: 63000 | H10: 63000 | I10: 63000 | J10: 63000 | K10: 63000 | L10: 63000 | M10: 63000 | N10: 63000 | O10: 63000 | P10: 63000 | Q10: 63000 | R10: 63000 | S10: 63000 | T10: 63000 | U10: 63000 | V10: 63000 | W10: 63000 | X10: 63000 | Y10: 48000 | Z10: 48000 | AA10: 48000 | AB10: 48000 | AC10: 48000 | AD10: 48000 | AE10: 48000 | AF10: 48000 | AG10: 48000 | AH10: 48000 | AI10: 48000 | AJ10: 48000 | AK10: 48000 | AL10: 48000 | AM10: 48000 | AN10: 48000 | AO10: 48000 | AP10: 48000 | AQ10: 48000 | AR10: 48000 | AS10: 48000 | AT10: 48000 | AU10: 48000 | AV10: 48000 | AW10: 48000 | AX10: 48000 | AY10: 48000 | AZ10: 48000
D11: Projected Available | E11: =$E$3+E10-E9 -> 202138.91 | F11: =E11+F10-F9 -> 198406.57 | G11: =F11+G10-G9 -> 194674.23 | H11: =G11+H10-H9 -> 190941.88 | I11: =H11+I10-I9 -> 168646.8 | J11: =I11+J10-J9 -> 146351.71 | K11: =J11+K10-K9 -> 124056.62 | L11: =K11+L10-L9 -> 101761.53 | M11: =L11+M10-M9 -> 83210.387 | ... AZ11: =AY11+AZ10-AZ9 -> 202192.36
C14: RCCP | D14: Period | E14: Nov | I14: Dec | M14: Jan | Q14: Feb | U14: Mar | Y14: Apr | AC14: May | AG14: Jun | AK14: Jul | AO14: Aug | AS14: Sep | AW14: Oct
D15: Week | E15: 1 | F15: =E15+1 -> 2 | G15: =F15+1 -> 3 | H15: =G15+1 -> 4 | I15: =H15+1 -> 5 | J15: =I15+1 -> 6 | K15: =J15+1 -> 7 | L15: =K15+1 -> 8 | M15: =L15+1 -> 9 | ... AZ15: =AY15+1 -> 48
D16: Available Labour Units | E16: =('Aggregate Planning'!$K27*'Aggregate Planning'!$J$9)/4 -> 63750 | F16: =('Aggregate Planning'!$K27*'Aggregate Planning'!$J$9)/4 -> 63750 | G16: =('Aggregate Planning'!$K27*'Aggregate Planning'!$J$9)/4 -> 63750 | H16: =('Aggregate Planning'!$K27*'Aggregate Planning'!$J$9)/4 -> 63750 | I16: =('Aggregate Planning'!$L27*'Aggregate Planning'!$J$9)/4 -> 63750 | J16: =('Aggregate Planning'!$L27*'Aggregate Planning'!$J$9)/4 -> 63750 | K16: =('Aggregate Planning'!$L27*'Aggregate Planning'!$J$9)/4 -> 63750 | L16: =('Aggregate Planning'!$L27*'Aggregate Planning'!$J$9)/4 -> 63750 | M16: =('Aggregate Planning'!$M27*'Aggregate Planning'!$J$9)/4 -> 63750 | N16: =('Aggregate Planning'!$M27*'Aggregate Planning'!$J$9)/4 -> 63750 | O16: =('Aggregate Planning'!$M27*'Aggregate Planning'!$J$9)/4 -> 63750 | P16: =('Aggregate Planning'!$M27*'Aggregate Planning'!$J$9)/4 -> 63750 | Q16: =('Aggregate Planning'!$N27*'Aggregate Planning'!$J$9)/4 -> 63750 | R16: =('Aggregate Planning'!$N27*'Aggregate Planning'!$J$9)/4 -> 63750 | S16: =('Aggregate Planning'!$N27*'Aggregate Planning'!$J$9)/4 -> 63750 | T16: =('Aggregate Planning'!$N27*'Aggregate Planning'!$J$9)/4 -> 63750 | U16: =('Aggregate Planning'!$O27*'Aggregate Planning'!$J$9)/4 -> 63750 | V16: =('Aggregate Planning'!$O27*'Aggregate Planning'!$J$9)/4 -> 63750 | W16: =('Aggregate Planning'!$O27*'Aggregate Planning'!$J$9)/4 -> 63750 | X16: =('Aggregate Planning'!$O27*'Aggregate Planning'!$J$9)/4 -> 63750 | Y16: =('Aggregate Planning'!$P27*'Aggregate Planning'!$J$9)/4 -> 51250 | Z16: =('Aggregate Planning'!$P27*'Aggregate Planning'!$J$9)/4 -> 51250 | AA16: =('Aggregate Planning'!$P27*'Aggregate Planning'!$J$9)/4 -> 51250 | AB16: =('Aggregate Planning'!$P27*'Aggregate Planning'!$J$9)/4 -> 51250 | AC16: =('Aggregate Planning'!$Q27*'Aggregate Planning'!$J$9)/4 -> 51250 | AD16: =('Aggregate Planning'!$Q27*'Aggregate Planning'!$J$9)/4 -> 51250 | AE16: =('Aggregate Planning'!$Q27*'Aggregate Planning'!$J$9)/4 -> 51250 | AF16: =('Aggregate Planning'!$Q27*'Aggregate Planning'!$J$9)/4 -> 51250 | AG16: =('Aggregate Planning'!$R27*'Aggregate Planning'!$J$9)/4 -> 51250 | AH16: =('Aggregate Planning'!$R27*'Aggregate Planning'!$J$9)/4 -> 51250 | AI16: =('Aggregate Planning'!$R27*'Aggregate Planning'!$J$9)/4 -> 51250 | AJ16: =('Aggregate Planning'!$R27*'Aggregate Planning'!$J$9)/4 -> 51250 | AK16: =('Aggregate Planning'!$S27*'Aggregate Planning'!$J$9)/4 -> 51250 | AL16: =('Aggregate Planning'!$S27*'Aggregate Planning'!$J$9)/4 -> 51250 | AM16: =('Aggregate Planning'!$S27*'Aggregate Planning'!$J$9)/4 -> 51250 | AN16: =('Aggregate Planning'!$S27*'Aggregate Planning'!$J$9)/4 -> 51250 | AO16: =('Aggregate Planning'!$T27*'Aggregate Planning'!$J$9)/4 -> 51250 | AP16: =('Aggregate Planning'!$T27*'Aggregate Planning'!$J$9)/4 -> 51250 | AQ16: =('Aggregate Planning'!$T27*'Aggregate Planning'!$J$9)/4 -> 51250 | AR16: =('Aggregate Planning'!$T27*'Aggregate Planning'!$J$9)/4 -> 51250 | AS16: =('Aggregate Planning'!$U27*'Aggregate Planning'!$J$9)/4 -> 51250 | AT16: =('Aggregate Planning'!$U27*'Aggregate Planning'!$J$9)/4 -> 51250 | AU16: =('Aggregate Planning'!$U27*'Aggregate Planning'!$J$9)/4 -> 51250 | AV16: =('Aggregate Planning'!$U27*'Aggregate Planning'!$J$9)/4 -> 51250 | AW16: =('Aggregate Planning'!$V27*'Aggregate Planning'!$J$9)/4 -> 51250 | AX16: =('Aggregate Planning'!$V27*'Aggregate Planning'!$J$9)/4 -> 51250 | AY16: =('Aggregate Planning'!$V27*'Aggregate Planning'!$J$9)/4 -> 51250 | AZ16: =('Aggregate Planning'!$V27*'Aggregate Planning'!$J$9)/4 -> 51250
D17: Required Labour Units | E17: =E10 -> 63000 | F17: =F10 -> 63000 | G17: =G10 -> 63000 | H17: =H10 -> 63000 | I17: =I10 -> 63000 | J17: =J10 -> 63000 | K17: =K10 -> 63000 | L17: =L10 -> 63000 | ... AZ17: =AZ10 -> 48000
D18: Utilisation Rate (%) | E18: =(E17/E16*100)/100 -> 0.98823529 | F18: =(F17/F16*100)/100 -> 0.98823529 | G18: =(G17/G16*100)/100 -> 0.98823529 | H18: =(H17/H16*100)/100 -> 0.98823529 | I18: =(I17/I16*100)/100 -> 0.98823529 | J18: =(J17/J16*100)/100 -> 0.98823529 | K18: =(K17/K16*100)/100 -> 0.98823529 | L18: =(L17/L16*100)/100 -> 0.98823529 | ... AZ18: =(AZ17/AZ16*100)/100 -> 0.93658537
D19: Cushion Rate (%) | E19: =1-E18 -> 0.011764706 | F19: =1-F18 -> 0.011764706 | G19: =1-G18 -> 0.011764706 | H19: =1-H18 -> 0.011764706 | I19: =1-I18 -> 0.011764706 | J19: =1-J18 -> 0.011764706 | K19: =1-K18 -> 0.011764706 | L19: =1-L18 -> 0.011764706 | ... AZ19: =1-AZ18 -> 0.063414634

Sheet Authorised MPS
A1: Assumptions
D3: Initial Inventory | E3: ='Initial MPS and RCCP'!E3 -> 205871.25
D4: Security Inventory | E4: =E3*0.2 -> 41174.251
C8: Authorised MPS | D8: Period | E8: Nov | I8: Dec | M8: Jan | Q8: Feb | U8: Mar | Y8: Apr | AC8: May | AG8: Jun | AK8: Jul | AO8: Aug | AS8: Sep | AW8: Oct
D9: Week | E9: Nov W1 | F9: Nov W2 | G9: Nov W3 | H9: Nov W4 | I9: Dec W1 | J9: Dec W2 | K9: Dec W3 | L9: Dec W4 | M9: Jan W1 | N9: Jan W2 | O9: Jan W3 | P9: Jan W4 | Q9: Feb W1 | R9: Feb W2 | S9: Feb W3 | T9: Feb W4 | U9: Mar W1 | V9: Mar W2 | W9: Mar W3 | X9: Mar W5 | Y9: Apr W1 | Z9: Apr W2 | AA9: Apr W3 | AB9: Apr W4 | AC9: May W1 | AD9: May W2 | AE9: May W3 | AF9: May W4 | AG9: Jun W1 | AH9: Jun W2 | AI9: Jun W3 | AJ9: Jun W4 | AK9: Jul W1 | AL9: Jul W2 | AM9: Jul W3 | AN9: Jul W4 | AO9: Aug W1 | AP9: Aug W2 | AQ9: Aug W3 | AR9: Aug W4 | AS9: Sep W1 | AT9: Sep W2 | AU9: Sep W3 | AV9: Sep W4 | AW9: Oct W1 | AX9: Oct W2 | AY9: Oct W3 | AZ9: Oct W4
D10: Forecasted Orders | E10: =ROUND('Aggregate Planning'!$K$14/4,0) -> 66732 | F10: =ROUND('Aggregate Planning'!$K$14/4,0) -> 66732 | G10: =ROUND('Aggregate Planning'!$K$14/4,0) -> 66732 | H10: =ROUND('Aggregate Planning'!$K$14/4,0) -> 66732 | I10: =ROUND('Aggregate Planning'!$L$14/4,0) -> 85295 | J10: =ROUND('Aggregate Planning'!$L$14/4,0) -> 85295 | K10: =ROUND('Aggregate Planning'!$L$14/4,0) -> 85295 | L10: =ROUND('Aggregate Planning'!$L$14/4,0) -> 85295 | M10: =ROUND('Aggregate Planning'!$M$14/4,0) -> 81551 | N10: =ROUND('Aggregate Planning'!$M$14/4,0) -> 81551 | O10: =ROUND('Aggregate Planning'!$M$14/4,0) -> 81551 | P10: =ROUND('Aggregate Planning'!$M$14/4,0) -> 81551 | Q10: =ROUND('Aggregate Planning'!$N$14/4,0) -> 54823 | R10: =ROUND('Aggregate Planning'!$N$14/4,0) -> 54823 | S10: =ROUND('Aggregate Planning'!$N$14/4,0) -> 54823 | T10: =ROUND('Aggregate Planning'!$N$14/4,0) -> 54823 | U10: =ROUND('Aggregate Planning'!$O$14/4,0) -> 54823 | V10: =ROUND('Aggregate Planning'!$O$14/4,0) -> 54823 | W10: =ROUND('Aggregate Planning'!$O$14/4,0) -> 54823 | X10: =ROUND('Aggregate Planning'!$O$14/4,0) -> 54823 | Y10: =ROUND('Aggregate Planning'!$P$14/4,0) -> 40948 | Z10: =ROUND('Aggregate Planning'!$P$14/4,0) -> 40948 | AA10: =ROUND('Aggregate Planning'!$P$14/4,0) -> 40948 | AB10: =ROUND('Aggregate Planning'!$P$14/4,0) -> 40948 | AC10: =ROUND('Aggregate Planning'!$Q$14/4,0) -> 47478 | AD10: =ROUND('Aggregate Planning'!$Q$14/4,0) -> 47478 | AE10: =ROUND('Aggregate Planning'!$Q$14/4,0) -> 47478 | AF10: =ROUND('Aggregate Planning'!$Q$14/4,0) -> 47478 | AG10: =ROUND('Aggregate Planning'!$R$14/4,0) -> 44166 | AH10: =ROUND('Aggregate Planning'!$R$14/4,0) -> 44166 | AI10: =ROUND('Aggregate Planning'!$R$14/4,0) -> 44166 | AJ10: =ROUND('Aggregate Planning'!$R$14/4,0) -> 44166 | AK10: =ROUND('Aggregate Planning'!$S$14/4,0) -> 35150 | AL10: =ROUND('Aggregate Planning'!$S$14/4,0) -> 35150 | AM10: =ROUND('Aggregate Planning'!$S$14/4,0) -> 35150 | AN10: =ROUND('Aggregate Planning'!$S$14/4,0) -> 35150 | AO10: =ROUND('Aggregate Planning'!$T$14/4,0) -> 40479 | AP10: =ROUND('Aggregate Planning'!$T$14/4,0) -> 40479 | AQ10: =ROUND('Aggregate Planning'!$T$14/4,0) -> 40479 | AR10: =ROUND('Aggregate Planning'!$T$14/4,0) -> 40479 | AS10: =ROUND('Aggregate Planning'!$U$14/4,0) -> 49420 | AT10: =ROUND('Aggregate Planning'!$U$14/4,0) -> 49420 | AU10: =ROUND('Aggregate Planning'!$U$14/4,0) -> 49420 | AV10: =ROUND('Aggregate Planning'!$U$14/4,0) -> 49420 | AW10: =ROUND('Aggregate Planning'!$V$14/4,0) -> 51054 | AX10: =ROUND('Aggregate Planning'!$V$14/4,0) -> 51054 | AY10: =ROUND('Aggregate Planning'!$V$14/4,0) -> 51054 | AZ10: =ROUND('Aggregate Planning'!$V$14/4,0) -> 51054
D11: Customer Orders | F11: 230000 | I11: 312000 | N11: 274000 | U11: 401000
D12: Reallocated Orders | E12: 170000 | F12: 60000 | G12: 63000 | H12: 63000 | I12: 63000 | J12: 63000 | K12: 60000 | L12: 63000 | M12: 63000 | N12: 63000 | O12: 63000 | P12: 22000
D13: Allocation checker | F13: =SUM(E12:F12)=F11 -> TRUE | I13: =SUM(G12:K12)=I11 -> TRUE | N13: =SUM(L12:P12)=N11 -> TRUE | U13: =SUM(Q12:X12)=U11 -> FALSE
D14: Weekly order > forecast | E14: =IF(E12>=E10,"Yes","No") -> Yes | F14: =IF(F12>=F10,"Yes","No") -> No | G14: =IF(G12>=G10,"Yes","No") -> No | H14: =IF(H12>=H10,"Yes","No") -> No | I14: =IF(I12>=I10,"Yes","No") -> No | J14: =IF(J12>=J10,"Yes","No") -> No | K14: =IF(K12>=K10,"Yes","No") -> No | L14: =IF(L12>=L10,"Yes","No") -> No | ... AZ14: =IF(AZ12>=AZ10,"Yes","No") -> No
D15: Projected Available | E15: =$E$3+E17-MAX(E10,E12) -> 98871.255 | F15: =E15+F17-MAX(F12,F10) -> 95139.255 | G15: =F15+G17-MAX(G12,G10) -> 91407.255 | H15: =G15+H17-MAX(H12,H10) -> 87675.255 | I15: =H15+I17-MAX(I12,I10) -> 65380.255 | J15: =I15+J17-MAX(J12,J10) -> 43085.255 | K15: =J15+K17-MAX(K12,K10) -> 20790.255 | L15: =K15+L17-MAX(L12,L10) -> -1504.7452 | M15: =L15+M17-MAX(M12,M10) -> -20055.745 | ... AZ15: =AY15+AZ17-MAX(AZ12,AZ10) -> 98927.255
D16: ATP | E16: =$E$3+E17-E12 -> 98871.255 | F16: =F17-F12 -> 3000 | G16: =G17-G12 -> 0 | H16: =H17-H12 -> 0 | I16: =I17-I12 -> 0 | J16: =J17-J12 -> 0 | K16: =K17-K12 -> 3000 | L16: =L17-L12 -> 0 | M16: =M17-M12 -> 0 | ... AZ16: =AZ17-AZ12 -> 48000
D17: Authorised MPS | E17: 63000 | F17: 63000 | G17: 63000 | H17: 63000 | I17: 63000 | J17: 63000 | K17: 63000 | L17: 63000 | M17: 63000 | N17: 63000 | O17: 63000 | P17: 63000 | Q17: 63000 | R17: 63000 | S17: 63000 | T17: 63000 | U17: 63000 | V17: 63000 | W17: 63000 | X17: 63000 | Y17: 48000 | Z17: 48000 | AA17: 48000 | AB17: 48000 | AC17: 48000 | AD17: 48000 | AE17: 48000 | AF17: 48000 | AG17: 48000 | AH17: 48000 | AI17: 48000 | AJ17: 48000 | AK17: 48000 | AL17: 48000 | AM17: 48000 | AN17: 48000 | AO17: 48000 | AP17: 48000 | AQ17: 48000 | AR17: 48000 | AS17: 48000 | AT17: 48000 | AU17: 48000 | AV17: 48000 | AW17: 48000 | AX17: 48000 | AY17: 48000 | AZ17: 48000
C19: RCCP | D19: Period | E19: Nov | I19: Dec | M19: Jan | Q19: Feb | U19: Mar | Y19: Apr | AC19: May | AG19: Jun | AK19: Jul | AO19: Aug | AS19: Sep | AW19: Oct
D20: Week | E20: 1 | F20: =E20+1 -> 2 | G20: =F20+1 -> 3 | H20: =G20+1 -> 4 | I20: =H20+1 -> 5 | J20: =I20+1 -> 6 | K20: =J20+1 -> 7 | L20: =K20+1 -> 8 | M20: =L20+1 -> 9 | ... AZ20: =AY20+1 -> 48
D21: Available Labour Units | E21: =('Aggregate Planning'!$K27*'Aggregate Planning'!$J$9)/4 -> 63750 | F21: =('Aggregate Planning'!$K27*'Aggregate Planning'!$J$9)/4 -> 63750 | G21: =('Aggregate Planning'!$K27*'Aggregate Planning'!$J$9)/4 -> 63750 | H21: =('Aggregate Planning'!$K27*'Aggregate Planning'!$J$9)/4 -> 63750 | I21: =('Aggregate Planning'!$L27*'Aggregate Planning'!$J$9)/4 -> 63750 | J21: =('Aggregate Planning'!$L27*'Aggregate Planning'!$J$9)/4 -> 63750 | K21: =('Aggregate Planning'!$L27*'Aggregate Planning'!$J$9)/4 -> 63750 | L21: =('Aggregate Planning'!$L27*'Aggregate Planning'!$J$9)/4 -> 63750 | M21: =('Aggregate Planning'!$M27*'Aggregate Planning'!$J$9)/4 -> 63750 | N21: =('Aggregate Planning'!$M27*'Aggregate Planning'!$J$9)/4 -> 63750 | O21: =('Aggregate Planning'!$M27*'Aggregate Planning'!$J$9)/4 -> 63750 | P21: =('Aggregate Planning'!$M27*'Aggregate Planning'!$J$9)/4 -> 63750 | Q21: =('Aggregate Planning'!$N27*'Aggregate Planning'!$J$9)/4 -> 63750 | R21: =('Aggregate Planning'!$N27*'Aggregate Planning'!$J$9)/4 -> 63750 | S21: =('Aggregate Planning'!$N27*'Aggregate Planning'!$J$9)/4 -> 63750 | T21: =('Aggregate Planning'!$N27*'Aggregate Planning'!$J$9)/4 -> 63750 | U21: =('Aggregate Planning'!$O27*'Aggregate Planning'!$J$9)/4 -> 63750 | V21: =('Aggregate Planning'!$O27*'Aggregate Planning'!$J$9)/4 -> 63750 | W21: =('Aggregate Planning'!$O27*'Aggregate Planning'!$J$9)/4 -> 63750 | X21: =('Aggregate Planning'!$O27*'Aggregate Planning'!$J$9)/4 -> 63750 | Y21: =('Aggregate Planning'!$P27*'Aggregate Planning'!$J$9)/4 -> 51250 | Z21: =('Aggregate Planning'!$P27*'Aggregate Planning'!$J$9)/4 -> 51250 | AA21: =('Aggregate Planning'!$P27*'Aggregate Planning'!$J$9)/4 -> 51250 | AB21: =('Aggregate Planning'!$P27*'Aggregate Planning'!$J$9)/4 -> 51250 | AC21: =('Aggregate Planning'!$Q27*'Aggregate Planning'!$J$9)/4 -> 51250 | AD21: =('Aggregate Planning'!$Q27*'Aggregate Planning'!$J$9)/4 -> 51250 | AE21: =('Aggregate Planning'!$Q27*'Aggregate Planning'!$J$9)/4 -> 51250 | AF21: =('Aggregate Planning'!$Q27*'Aggregate Planning'!$J$9)/4 -> 51250 | AG21: =('Aggregate Planning'!$R27*'Aggregate Planning'!$J$9)/4 -> 51250 | AH21: =('Aggregate Planning'!$R27*'Aggregate Planning'!$J$9)/4 -> 51250 | AI21: =('Aggregate Planning'!$R27*'Aggregate Planning'!$J$9)/4 -> 51250 | AJ21: =('Aggregate Planning'!$R27*'Aggregate Planning'!$J$9)/4 -> 51250 | AK21: =('Aggregate Planning'!$S27*'Aggregate Planning'!$J$9)/4 -> 51250 | AL21: =('Aggregate Planning'!$S27*'Aggregate Planning'!$J$9)/4 -> 51250 | AM21: =('Aggregate Planning'!$S27*'Aggregate Planning'!$J$9)/4 -> 51250 | AN21: =('Aggregate Planning'!$S27*'Aggregate Planning'!$J$9)/4 -> 51250 | AO21: =('Aggregate Planning'!$T27*'Aggregate Planning'!$J$9)/4 -> 51250 | AP21: =('Aggregate Planning'!$T27*'Aggregate Planning'!$J$9)/4 -> 51250 | AQ21: =('Aggregate Planning'!$T27*'Aggregate Planning'!$J$9)/4 -> 51250 | AR21: =('Aggregate Planning'!$T27*'Aggregate Planning'!$J$9)/4 -> 51250 | AS21: =('Aggregate Planning'!$U27*'Aggregate Planning'!$J$9)/4 -> 51250 | AT21: =('Aggregate Planning'!$U27*'Aggregate Planning'!$J$9)/4 -> 51250 | AU21: =('Aggregate Planning'!$U27*'Aggregate Planning'!$J$9)/4 -> 51250 | AV21: =('Aggregate Planning'!$U27*'Aggregate Planning'!$J$9)/4 -> 51250 | AW21: =('Aggregate Planning'!$V27*'Aggregate Planning'!$J$9)/4 -> 51250 | AX21: =('Aggregate Planning'!$V27*'Aggregate Planning'!$J$9)/4 -> 51250 | AY21: =('Aggregate Planning'!$V27*'Aggregate Planning'!$J$9)/4 -> 51250 | AZ21: =('Aggregate Planning'!$V27*'Aggregate Planning'!$J$9)/4 -> 51250
D22: Required Labour Units | E22: =E17 -> 63000 | F22: =F17 -> 63000 | G22: =G17 -> 63000 | H22: =H17 -> 63000 | I22: =I17 -> 63000 | J22: =J17 -> 63000 | K22: =K17 -> 63000 | L22: =L17 -> 63000 | ... AZ22: =AZ17 -> 48000
D23: Utilisation Rate (%) | E23: =(E22/E21*100)/100 -> 0.98823529 | F23: =(F22/F21*100)/100 -> 0.98823529 | G23: =(G22/G21*100)/100 -> 0.98823529 | H23: =(H22/H21*100)/100 -> 0.98823529 | I23: =(I22/I21*100)/100 -> 0.98823529 | J23: =(J22/J21*100)/100 -> 0.98823529 | K23: =(K22/K21*100)/100 -> 0.98823529 | L23: =(L22/L21*100)/100 -> 0.98823529 | ... AZ23: =(AZ22/AZ21*100)/100 -> 0.93658537
D24: Cushion Rate (%) | E24: =1-E23 -> 0.011764706 | F24: =1-F23 -> 0.011764706 | G24: =1-G23 -> 0.011764706 | H24: =1-H23 -> 0.011764706 | I24: =1-I23 -> 0.011764706 | J24: =1-J23 -> 0.011764706 | K24: =1-K23 -> 0.011764706 | L24: =1-L23 -> 0.011764706 | ... AZ24: =1-AZ23 -> 0.063414634

Sheet MRP
A1: Assumptions
H2: WH-1000XM5 (Level 0; L4L) | I2: begining inventory | J2: 205871.44
I3: Period | J3: Nov | N3: Dec | R3: Jan | V3: Feb | Z3: Mar | AD3: Apr | AH3: May | AL3: Jun | AP3: Jul | AT3: Aug | AX3: Sep | BB3: Oct
I4: Week | J4: 1 | K4: =J4+1 -> 2 | L4: =K4+1 -> 3 | M4: =L4+1 -> 4 | N4: =M4+1 -> 5 | O4: =N4+1 -> 6 | P4: =O4+1 -> 7 | Q4: =P4+1 -> 8 | R4: =Q4+1 -> 9 | ... BE4: =BD4+1 -> 48
I5: Gross Requirements | J5: ='Authorised MPS'!E17 -> 63000 | K5: ='Authorised MPS'!F17 -> 63000 | L5: ='Authorised MPS'!G17 -> 63000 | M5: ='Authorised MPS'!H17 -> 63000 | N5: ='Authorised MPS'!I17 -> 63000 | O5: ='Authorised MPS'!J17 -> 63000 | P5: ='Authorised MPS'!K17 -> 63000 | Q5: ='Authorised MPS'!L17 -> 63000 | ... BE5: ='Authorised MPS'!AZ17 -> 48000
I6: Planned Orders | J6: =K5 -> 63000 | K6: =L5 -> 63000 | L6: =M5 -> 63000 | M6: =N5 -> 63000 | N6: =O5 -> 63000 | O6: =P5 -> 63000 | P6: =Q5 -> 63000 | Q6: =R5 -> 63000 | ... BE6: =BF5 -> 0
I7: Projected Available | J7: =J2 -> 205871.44 | K7: =J7+J6-K5 -> 205871.44 | L7: =K7+K6-L5 -> 205871.44 | M7: =L7+L6-M5 -> 205871.44 | N7: =M7+M6-N5 -> 205871.44 | O7: =N7+N6-O5 -> 205871.44 | P7: =O7+O6-P5 -> 205871.44 | Q7: =P7+P6-Q5 -> 205871.44 | R7: =Q7+Q6-R5 -> 205871.44 | ... BE7: =BD7+BD6-BE5 -> 205871.44
K9: Needed POQ | L9: Feasible POQ
H10: Battery & Charging System (Level 1; POQ) | I10: begining inventory | J10: 252000 | K10: =2*AVERAGE(J13:BE13) -> 105875 | L10: 107000
I11: Period | J11: Nov | N11: Dec | R11: Jan | V11: Feb | Z11: Mar | AD11: Apr | AH11: May | AL11: Jun | AP11: Jul | AT11: Aug | AX11: Sep | BB11: Oct
I12: Week | J12: 1 | K12: =J12+1 -> 2 | L12: =K12+1 -> 3 | M12: =L12+1 -> 4 | N12: =M12+1 -> 5 | O12: =N12+1 -> 6 | P12: =O12+1 -> 7 | Q12: =P12+1 -> 8 | R12: =Q12+1 -> 9 | ... BE12: =BD12+1 -> 48
I13: Gross Requirements | J13: =J6 -> 63000 | K13: =K6 -> 63000 | L13: =L6 -> 63000 | M13: =M6 -> 63000 | N13: =N6 -> 63000 | O13: =O6 -> 63000 | P13: =P6 -> 63000 | Q13: =Q6 -> 63000 | ... BE13: =BE6 -> 0
I14: Planned Orders | J14: =$L$10 -> 107000 | K14: =0 -> 0 | L14: =$L$10 -> 107000 | M14: =0 -> 0 | N14: =$L$10 -> 107000 | O14: =0 -> 0 | P14: =$L$10 -> 107000 | Q14: =0 -> 0 | R14: =$L$10 -> 107000 | S14: =0 -> 0 | T14: =$L$10 -> 107000 | U14: =0 -> 0 | V14: =$L$10 -> 107000 | W14: =0 -> 0 | X14: =$L$10 -> 107000 | Y14: =0 -> 0 | Z14: =$L$10 -> 107000 | AA14: =0 -> 0 | AB14: =$L$10 -> 107000 | AC14: =0 -> 0 | AD14: =$L$10 -> 107000 | AE14: =0 -> 0 | AF14: =$L$10 -> 107000 | AG14: =0 -> 0 | AH14: =$L$10 -> 107000 | AI14: =0 -> 0 | AJ14: =$L$10 -> 107000 | AK14: =0 -> 0 | AL14: =$L$10 -> 107000 | AM14: =0 -> 0 | AN14: =$L$10 -> 107000 | AO14: =0 -> 0 | AP14: =$L$10 -> 107000 | AQ14: =0 -> 0 | AR14: =$L$10 -> 107000 | AS14: =0 -> 0 | AT14: =$L$10 -> 107000 | AU14: =0 -> 0 | AV14: =$L$10 -> 107000 | AW14: =0 -> 0 | AX14: =$L$10 -> 107000 | AY14: =0 -> 0 | AZ14: =$L$10 -> 107000 | BA14: =0 -> 0 | BB14: =$L$10 -> 107000 | BC14: =0 -> 0 | BD14: =$L$10 -> 107000 | BE14: =0 -> 0
I15: Projected Available | J15: =J10-J13 -> 189000 | K15: =J15+J14-K13 -> 233000 | L15: =K15+K14-L13 -> 170000 | M15: =L15+L14-M13 -> 214000 | N15: =M15+M14-N13 -> 151000 | O15: =N15+N14-O13 -> 195000 | P15: =O15+O14-P13 -> 132000 | Q15: =P15+P14-Q13 -> 176000 | R15: =Q15+Q14-R13 -> 113000 | ... BE15: =BD15+BD14-BE13 -> 279000
H18: Charging Port (Level 2; L4L) | I18: begining inventory | J18: =2*J21 -> 214000
I19: Period | J19: Nov | N19: Dec | R19: Jan | V19: Feb | Z19: Mar | AD19: Apr | AH19: May | AL19: Jun | AP19: Jul | AT19: Aug | AX19: Sep | BB19: Oct
I20: Week | J20: 1 | K20: =J20+1 -> 2 | L20: =K20+1 -> 3 | M20: =L20+1 -> 4 | N20: =M20+1 -> 5 | O20: =N20+1 -> 6 | P20: =O20+1 -> 7 | Q20: =P20+1 -> 8 | R20: =Q20+1 -> 9 | ... BE20: =BD20+1 -> 48
I21: Gross Requirements | J21: =J14 -> 107000 | K21: =K14 -> 0 | L21: =L14 -> 107000 | M21: =M14 -> 0 | N21: =N14 -> 107000 | O21: =O14 -> 0 | P21: =P14 -> 107000 | Q21: =Q14 -> 0 | ... BE21: =BE14 -> 0
I22: Planned Orders | J22: =$L$10 -> 107000 | K22: =0 -> 0 | L22: =$L$10 -> 107000 | M22: =0 -> 0 | N22: =$L$10 -> 107000 | O22: =0 -> 0 | P22: =$L$10 -> 107000 | Q22: =0 -> 0 | R22: =$L$10 -> 107000 | S22: =0 -> 0 | T22: =$L$10 -> 107000 | U22: =0 -> 0 | V22: =$L$10 -> 107000 | W22: =0 -> 0 | X22: =$L$10 -> 107000 | Y22: =0 -> 0 | Z22: =$L$10 -> 107000 | AA22: =0 -> 0 | AB22: =$L$10 -> 107000 | AC22: =0 -> 0 | AD22: =$L$10 -> 107000 | AE22: =0 -> 0 | AF22: =$L$10 -> 107000 | AG22: =0 -> 0 | AH22: =$L$10 -> 107000 | AI22: =0 -> 0 | AJ22: =$L$10 -> 107000 | AK22: =0 -> 0 | AL22: =$L$10 -> 107000 | AM22: =0 -> 0 | AN22: =$L$10 -> 107000 | AO22: =0 -> 0 | AP22: =$L$10 -> 107000 | AQ22: =0 -> 0 | AR22: =$L$10 -> 107000 | AS22: =0 -> 0 | AT22: =$L$10 -> 107000 | AU22: =0 -> 0 | AV22: =$L$10 -> 107000 | AW22: =0 -> 0 | AX22: =$L$10 -> 107000 | AY22: =0 -> 0 | AZ22: =$L$10 -> 107000 | BA22: =0 -> 0 | BB22: =$L$10 -> 107000 | BC22: =0 -> 0 | BD22: =$L$10 -> 107000 | BE22: =0 -> 0
I23: Projected Available | J23: =J18-J21 -> 107000 | K23: =J23-K21 -> 107000 | L23: =K23-L21 -> 0 | M23: =L23+J22-M21 -> 107000 | N23: =M23+K22-N21 -> 0 | O23: =N23+L22-O21 -> 107000 | P23: =O23+M22-P21 -> 0 | Q23: =P23+N22-Q21 -> 107000 | R23: =Q23+O22-R21 -> 0 | S23: =R23+P22-S21 -> 107000 | T23: =S23+Q22-T21 -> 0 | ... BE23: =BD23+BB22-BE21 -> 107000
K25: FOQ
H26: Charging Circuitry x2 (Level 3; FOQ) | I26: begining inventory | J26: 318000 | K26: =10000 -> 10000
I27: Period | J27: Nov | N27: Dec | R27: Jan | V27: Feb | Z27: Mar | AD27: Apr | AH27: May | AL27: Jun | AP27: Jul | AT27: Aug | AX27: Sep | BB27: Oct
I28: Week | J28: 1 | K28: =J28+1 -> 2 | L28: =K28+1 -> 3 | M28: =L28+1 -> 4 | N28: =M28+1 -> 5 | O28: =N28+1 -> 6 | P28: =O28+1 -> 7 | Q28: =P28+1 -> 8 | R28: =Q28+1 -> 9 | ... BE28: =BD28+1 -> 48
I29: Gross Requirements | J29: =2*J22 -> 214000 | K29: =2*K22 -> 0 | L29: =2*L22 -> 214000 | M29: =2*M22 -> 0 | N29: =2*N22 -> 214000 | O29: =2*O22 -> 0 | P29: =2*P22 -> 214000 | Q29: =2*Q22 -> 0 | ... BE29: =2*BE22 -> 0
I30: Planned Orders | J30: =11*$K$26 -> 110000 | K30: =11*$K$26 -> 110000 | L30: =11*$K$26 -> 110000 | M30: =10*$K$26 -> 100000 | N30: =11*$K$26 -> 110000 | O30: =11*$K$26 -> 110000 | P30: =11*$K$26 -> 110000 | Q30: =10*$K$26 -> 100000 | R30: =11*$K$26 -> 110000 | S30: =11*$K$26 -> 110000 | T30: =11*$K$26 -> 110000 | U30: =10*$K$26 -> 100000 | V30: =11*$K$26 -> 110000 | W30: =11*$K$26 -> 110000 | X30: =11*$K$26 -> 110000 | Y30: =10*$K$26 -> 100000 | Z30: =11*$K$26 -> 110000 | AA30: =11*$K$26 -> 110000 | AB30: =11*$K$26 -> 110000 | AC30: =10*$K$26 -> 100000 | AD30: =11*$K$26 -> 110000 | AE30: =11*$K$26 -> 110000 | AF30: =11*$K$26 -> 110000 | AG30: =10*$K$26 -> 100000 | AH30: =11*$K$26 -> 110000 | AI30: =11*$K$26 -> 110000 | AJ30: =11*$K$26 -> 110000 | AK30: =10*$K$26 -> 100000 | AL30: =11*$K$26 -> 110000 | AM30: =11*$K$26 -> 110000 | AN30: =11*$K$26 -> 110000 | AO30: =10*$K$26 -> 100000 | AP30: =11*$K$26 -> 110000 | AQ30: =11*$K$26 -> 110000 | AR30: =11*$K$26 -> 110000 | AS30: =10*$K$26 -> 100000 | AT30: =11*$K$26 -> 110000 | AU30: =11*$K$26 -> 110000 | AV30: =11*$K$26 -> 110000 | AW30: =10*$K$26 -> 100000 | AX30: =11*$K$26 -> 110000 | AY30: =11*$K$26 -> 110000 | AZ30: =11*$K$26 -> 110000 | BA30: =10*$K$26 -> 100000 | BB30: =11*$K$26 -> 110000 | BC30: =11*$K$26 -> 110000 | BD30: =11*$K$26 -> 110000 | BE30: =10*$K$26 -> 100000
I31: Projected Available | J31: =J26-J29 -> 104000 | K31: =J31-K29 -> 104000 | L31: =K31+J30-L29 -> 0 | M31: =L31+K30-M29 -> 110000 | N31: =M31+L30-N29 -> 6000 | O31: =N31+M30-O29 -> 106000 | P31: =O31+N30-P29 -> 2000 | Q31: =P31+O30-Q29 -> 112000 | R31: =Q31+P30-R29 -> 8000 | S31: =R31+Q30-S29 -> 108000 | ... BE31: =BD31+BC30-BE29 -> 132000

Sheet EOQ
A1: Assumptions
I3: WH-1000XM5 | J3: Battery & Charging System | K3: Charging Port | L3: Charging Circuitry x2
H4: Demand (D) | I4: =SUM(MRP!$J$5:$BE$5) -> 2604000 | J4: =SUM(MRP!$J$5:$BE$5) -> 2604000 | K4: =SUM(MRP!$J$5:$BE$5) -> 2604000 | L4: =K4*2 -> 5208000
H5: Lead time | I5: 5 | J5: 5 | K5: 15 | L5: 10
H6: Operation days | I6: 300 | J6: 300 | K6: 300 | L6: 300
H7: % of the watch | I7: 1 | J7: 0.5 | K7: 0.15 | L7: 0.35
H8: Annual holding cost per unit (H) | I8: =I7*'Aggregate Planning'!$O$7 -> 5 | J8: =J7*'Aggregate Planning'!$O$7 -> 2.5 | K8: =K7*'Aggregate Planning'!$O$7 -> 0.75 | L8: =L7*'Aggregate Planning'!$O$7 -> 1.75
H9: Ordering cost (S) | I9: ='Aggregate Planning'!$O$5*50 -> 250 | J9: ='Aggregate Planning'!$O$5*50 -> 250 | K9: ='Aggregate Planning'!$O$5*50 -> 250 | L9: ='Aggregate Planning'!$O$5*50 -> 250
H10: Inventory demand rate per day (d) | I10: =I4/I6 -> 8680 | J10: =J4/J6 -> 8680 | K10: =K4/K6 -> 8680 | L10: =L4/L6 -> 17360
H12: EOQ (Q) | I12: =SQRT(2*I4*I9/I8) -> 16136.914 | J12: =SQRT(2*J4*J9/J8) -> 22821.043 | K12: =SQRT(2*K4*K9/K8) -> 41665.333 | L12: =SQRT(2*L4*L9/L8) -> 38574.603
H13: Reorder Point (R) | I13: =I5*I10 -> 43400 | J13: =J5*J10++'Authorised MPS'!E4 -> 84574.251 | K13: =K5*K10++'Authorised MPS'!E4 -> 171374.25 | L13: =L5*L10++'Authorised MPS'!E4 -> 214774.25
H14: Economic order interval (T*) | I14: =I12/I10 -> 1.8590915 | J14: =J12/J10 -> 2.6291524 | K14: =K12/K10 -> 4.8001536 | L14: =L12/L10 -> 2.2220393
H15: S.S. + EOQ | I15: =I12+'Authorised MPS'!$E$4 -> 57311.165 | J15: =J12+'Authorised MPS'!$E$4 -> 63995.294 | K15: =K12+'Authorised MPS'!$E$4 -> 82839.584 | L15: =L12+'Authorised MPS'!$E$4 -> 79748.854
H16: TC | I16: =I4/I12*I9+I12/2*I8 -> 80684.571 | J16: =J4/J12*J9+J12/2*J8 -> 57052.607 | K16: =K4/K12*K9+K12/2*K8 -> 31249 | L16: =L4/L12*L9+L12/2*L8 -> 67505.555
I17: step size | J17: 3000
G18: WH-1000XM5 | H18: Q* | I18: 5000 | J18: =I18+$J$17 -> 8000 | K18: =J18+$J$17 -> 11000 | L18: =K18+$J$17 -> 14000 | M18: =L18+$J$17 -> 17000 | N18: =M18+$J$17 -> 20000 | O18: =N18+$J$17 -> 23000 | P18: =O18+$J$17 -> 26000 | Q18: =P18+$J$17 -> 29000 | ... AC18: =AB18+$J$17 -> 65000
H19: TC | I19: =SUM(I20:I21) -> 142700 | J19: =SUM(J20:J21) -> 101375 | K19: =SUM(K20:K21) -> 86681.818 | L19: =SUM(L20:L21) -> 81500 | M19: =SUM(M20:M21) -> 80794.118 | N19: =SUM(N20:N21) -> 82550 | O19: =SUM(O20:O21) -> 85804.348 | P19: =SUM(P20:P21) -> 90038.462 | ... AC19: =SUM(AC20:AC21) -> 172515.38
H20: Costs associated with Ordering | I20: =$I$4/I18*$I$9 -> 130200 | J20: =$I$4/J18*$I$9 -> 81375 | K20: =$I$4/K18*$I$9 -> 59181.818 | L20: =$I$4/L18*$I$9 -> 46500 | M20: =$I$4/M18*$I$9 -> 38294.118 | N20: =$I$4/N18*$I$9 -> 32550 | O20: =$I$4/O18*$I$9 -> 28304.348 | P20: =$I$4/P18*$I$9 -> 25038.462 | ... AC20: =$I$4/AC18*$I$9 -> 10015.385
H21: Costs associated with Holding | I21: =I18/2*$I$8 -> 12500 | J21: =J18/2*$I$8 -> 20000 | K21: =K18/2*$I$8 -> 27500 | L21: =L18/2*$I$8 -> 35000 | M21: =M18/2*$I$8 -> 42500 | N21: =N18/2*$I$8 -> 50000 | O21: =O18/2*$I$8 -> 57500 | P21: =P18/2*$I$8 -> 65000 | ... AC21: =AC18/2*$I$8 -> 162500
I24: step size | J24: 3000
G25: Battery & Charging System | H25: Q* | I25: 5000 | J25: =I25+$J$24 -> 8000 | K25: =J25+$J$24 -> 11000 | L25: =K25+$J$24 -> 14000 | M25: =L25+$J$24 -> 17000 | N25: =M25+$J$24 -> 20000 | O25: =N25+$J$24 -> 23000 | P25: =O25+$J$24 -> 26000 | Q25: =P25+$J$24 -> 29000 | ... AC25: =AB25+$J$24 -> 65000
H26: TC | I26: =SUM(I27:I28) -> 136450 | J26: =SUM(J27:J28) -> 91375 | K26: =SUM(K27:K28) -> 72931.818 | L26: =SUM(L27:L28) -> 64000 | M26: =SUM(M27:M28) -> 59544.118 | N26: =SUM(N27:N28) -> 57550 | O26: =SUM(O27:O28) -> 57054.348 | P26: =SUM(P27:P28) -> 57538.462 | ... AC26: =SUM(AC27:AC28) -> 91265.385
H27: Costs associated with Ordering | I27: =$J$4/I25*$J$9 -> 130200 | J27: =$J$4/J25*$J$9 -> 81375 | K27: =$J$4/K25*$J$9 -> 59181.818 | L27: =$J$4/L25*$J$9 -> 46500 | M27: =$J$4/M25*$J$9 -> 38294.118 | N27: =$J$4/N25*$J$9 -> 32550 | O27: =$J$4/O25*$J$9 -> 28304.348 | P27: =$J$4/P25*$J$9 -> 25038.462 | ... AC27: =$J$4/AC25*$J$9 -> 10015.385
H28: Costs associated with Holding | I28: =I25/2*$J$8 -> 6250 | J28: =J25/2*$J$8 -> 10000 | K28: =K25/2*$J$8 -> 13750 | L28: =L25/2*$J$8 -> 17500 | M28: =M25/2*$J$8 -> 21250 | N28: =N25/2*$J$8 -> 25000 | O28: =O25/2*$J$8 -> 28750 | P28: =P25/2*$J$8 -> 32500 | ... AC28: =AC25/2*$J$8 -> 81250
I31: step size | J31: 3000
G32: Charging Port | H32: Q* | I32: 5000 | J32: =I32+$J$31 -> 8000 | K32: =J32+$J$31 -> 11000 | L32: =K32+$J$31 -> 14000 | M32: =L32+$J$31 -> 17000 | N32: =M32+$J$31 -> 20000 | O32: =N32+$J$31 -> 23000 | P32: =O32+$J$31 -> 26000 | Q32: =P32+$J$31 -> 29000 | ... AC32: =AB32+$J$31 -> 65000
H33: TC | I33: =SUM(I34:I35) -> 132075 | J33: =SUM(J34:J35) -> 84375 | K33: =SUM(K34:K35) -> 63306.818 | L33: =SUM(L34:L35) -> 51750 | M33: =SUM(M34:M35) -> 44669.118 | N33: =SUM(N34:N35) -> 40050 | O33: =SUM(O34:O35) -> 36929.348 | P33: =SUM(P34:P35) -> 34788.462 | ... AC33: =SUM(AC34:AC35) -> 34390.385
H34: Costs associated with Ordering | I34: =$K$4/I32*$K$9 -> 130200 | J34: =$K$4/J32*$K$9 -> 81375 | K34: =$K$4/K32*$K$9 -> 59181.818 | L34: =$K$4/L32*$K$9 -> 46500 | M34: =$K$4/M32*$K$9 -> 38294.118 | N34: =$K$4/N32*$K$9 -> 32550 | O34: =$K$4/O32*$K$9 -> 28304.348 | P34: =$K$4/P32*$K$9 -> 25038.462 | ... AC34: =$K$4/AC32*$K$9 -> 10015.385
H35: Costs associated with Holding | I35: =I32/2*$K$8 -> 1875 | J35: =J32/2*$K$8 -> 3000 | K35: =K32/2*$K$8 -> 4125 | L35: =L32/2*$K$8 -> 5250 | M35: =M32/2*$K$8 -> 6375 | N35: =N32/2*$K$8 -> 7500 | O35: =O32/2*$K$8 -> 8625 | P35: =P32/2*$K$8 -> 9750 | ... AC35: =AC32/2*$K$8 -> 24375
I38: step size | J38: 5000
G39: Charging Circuitry x2 | H39: Q* | I39: 10000 | J39: =I39+$J$38 -> 15000 | K39: =J39+$J$38 -> 20000 | L39: =K39+$J$38 -> 25000 | M39: =L39+$J$38 -> 30000 | N39: =M39+$J$38 -> 35000 | O39: =N39+$J$38 -> 40000 | P39: =O39+$J$38 -> 45000 | Q39: =P39+$J$38 -> 50000 | ... AL39: =AK39+$J$38 -> 155000
H40: TC | I40: =SUM(I41:I42) -> 138950 | J40: =SUM(J41:J42) -> 99925 | K40: =SUM(K41:K42) -> 82600 | L40: =SUM(L41:L42) -> 73955 | M40: =SUM(M41:M42) -> 69650 | N40: =SUM(N41:N42) -> 67825 | O40: =SUM(O41:O42) -> 67550 | P40: =SUM(P41:P42) -> 68308.333 | ... AL40: =SUM(AL41:AL42) -> 144025
H41: Costs associated with Ordering | I41: =$L$4/I39*$L$9 -> 130200 | J41: =$L$4/J39*$L$9 -> 86800 | K41: =$L$4/K39*$L$9 -> 65100 | L41: =$L$4/L39*$L$9 -> 52080 | M41: =$L$4/M39*$L$9 -> 43400 | N41: =$L$4/N39*$L$9 -> 37200 | O41: =$L$4/O39*$L$9 -> 32550 | P41: =$L$4/P39*$L$9 -> 28933.333 | ... AL41: =$L$4/AL39*$L$9 -> 8400
H42: Costs associated with Holding | I42: =I39/2*$L$8 -> 8750 | J42: =J39/2*$L$8 -> 13125 | K42: =K39/2*$L$8 -> 17500 | L42: =L39/2*$L$8 -> 21875 | M42: =M39/2*$L$8 -> 26250 | N42: =N39/2*$L$8 -> 30625 | O42: =O39/2*$L$8 -> 35000 | P42: =P39/2*$L$8 -> 39375 | ... AL42: =AL39/2*$L$8 -> 135625

Sheet EPQ
A1: Assumptions
I3: WH-1000XM5 | J3: Battery & Charging System | K3: Charging Port | L3: Charging Circuitry x2
H4: Demand | I4: =EOQ!I4 -> 2604000 | J4: =EOQ!J4 -> 2604000 | K4: =EOQ!K4 -> 2604000 | L4: =EOQ!L4 -> 5208000
H5: Lead time (days - 1 week = 5 days) | I5: 5 | J5: 5 | K5: 15 | L5: 10
H6: Operation days | I6: 300 | J6: 300 | K6: 300 | L6: 300
H7: % of the watch | I7: 1 | J7: 0.5 | K7: 0.25 | L7: 0.25
H8: Annual holding cost per units | I8: =I7*'Aggregate Planning'!$O$7 -> 5 | J8: =J7*'Aggregate Planning'!$O$7 -> 2.5 | K8: =K7*'Aggregate Planning'!$O$7 -> 1.25 | L8: =L7*'Aggregate Planning'!$O$7 -> 1.25
H9: Ordering cost | I9: ='Aggregate Planning'!$O$5*50 -> 250 | J9: ='Aggregate Planning'!$O$5*50 -> 250 | K9: ='Aggregate Planning'!$O$5*50 -> 250 | L9: ='Aggregate Planning'!$O$5*50 -> 250
H10: Inventory demand rate per day (d) | I10: =I4/I6 -> 8680 | J10: =J4/J6 -> 8680 | K10: =K4/K6 -> 8680 | L10: =L4/L6 -> 17360
H11: d | I11: =I4/I6 -> 8680 | J11: =J4/J6 -> 8680 | K11: =K4/K6 -> 8680 | L11: =L4/L6 -> 17360
H12: p | I12: =SUM('Aggregate Planning'!J19:U19)/I6 -> 9066.6667 | J12: =SUM('Aggregate Planning'!J19:U19)/J6 -> 9066.6667 | K12: =SUM('Aggregate Planning'!J19:U19)/K6 -> 9066.6667 | L12: =SUM('Aggregate Planning'!J19:U19)/L6*2 -> 18133.333
H14: EPQ (Q*) | I14: =SQRT(2*I4*I9/(I8*(1-I11/I12))) -> 78140.457 | J14: =SQRT(2*J4*J9/(J8*(1-J11/J12))) -> 110507.29 | K14: =SQRT(2*K4*K9/(K8*(1-K11/K12))) -> 156280.91 | L14: =SQRT(2*L4*L9/(L8*(1-L11/L12))) -> 221014.59
H15: Reoder Point (R) | I15: =I5*I10+'Authorised MPS'!$E$4 -> 84574.251 | J15: =J5*J10+'Authorised MPS'!$E$4 -> 84574.251 | K15: =K5*K10+'Authorised MPS'!$E$4 -> 171374.25 | L15: =L5*L10+'Authorised MPS'!$E$4 -> 214774.25
H16: Economic order interval (T*) | I16: =I14/I10 -> 9.0023568 | J16: =J14/J10 -> 12.731255 | K16: =K14/K10 -> 18.004714 | L16: =L14/L10 -> 12.731255
H17: S.S. + EPQ | I17: =I14+'Authorised MPS'!$E$4 -> 119314.71 | J17: =J14+'Authorised MPS'!$E$4 -> 151681.55 | K17: =K14+'Authorised MPS'!$E$4 -> 197455.17 | L17: =L14+'Authorised MPS'!$E$4 -> 262188.84
H18: TC | I18: =I4/I14*I9+I14*(1-I11/I12)/2*I8 -> 16662.303 | J18: =J4/J14*J9+J14*(1-J11/J12)/2*J8 -> 11782.028 | K18: =K4/K14*K9+K14*(1-K11/K12)/2*K8 -> 8331.1517 | L18: =L4/L14*L9+L14*(1-L11/L12)/2*L8 -> 11782.028
I19: step size | J19: 7000
G20: WH-1000XM5 | H20: Q | I20: 20000 | J20: =I20+$J$19 -> 27000 | K20: =J20+$J$19 -> 34000 | L20: =K20+$J$19 -> 41000 | M20: =L20+$J$19 -> 48000 | N20: =M20+$J$19 -> 55000 | O20: =N20+$J$19 -> 62000 | P20: =O20+$J$19 -> 69000 | Q20: =P20+$J$19 -> 76000 | ... AC20: =AB20+$J$19 -> 160000
H21: TC (Total cost) | I21: =SUM(I22:I23) -> 34682.353 | J21: =SUM(J22:J23) -> 26989.788 | K21: =SUM(K22:K23) -> 22772.059 | L21: =SUM(L22:L23) -> 20249.372 | M21: =SUM(M22:M23) -> 18680.147 | N21: =SUM(N22:N23) -> 17700.334 | O21: =SUM(O22:O23) -> 17110.294 | P21: =SUM(P22:P23) -> 16791.4 | ... AC21: =SUM(AC22:AC23) -> 21127.574
H22: Costs associated with Ordering | I22: =$I$4/I20*$I$9 -> 32550 | J22: =$I$4/J20*$I$9 -> 24111.111 | K22: =$I$4/K20*$I$9 -> 19147.059 | L22: =$I$4/L20*$I$9 -> 15878.049 | M22: =$I$4/M20*$I$9 -> 13562.5 | N22: =$I$4/N20*$I$9 -> 11836.364 | O22: =$I$4/O20*$I$9 -> 10500 | P22: =$I$4/P20*$I$9 -> 9434.7826 | ... AC22: =$I$4/AC20*$I$9 -> 4068.75
H23: Costs associated with Holding | I23: =I20*(1-$I$11/$I$12)/2*$I$8 -> 2132.3529 | J23: =J20*(1-$I$11/$I$12)/2*$I$8 -> 2878.6765 | K23: =K20*(1-$I$11/$I$12)/2*$I$8 -> 3625 | L23: =L20*(1-$I$11/$I$12)/2*$I$8 -> 4371.3235 | M23: =M20*(1-$I$11/$I$12)/2*$I$8 -> 5117.6471 | N23: =N20*(1-$I$11/$I$12)/2*$I$8 -> 5863.9706 | O23: =O20*(1-$I$11/$I$12)/2*$I$8 -> 6610.2941 | P23: =P20*(1-$I$11/$I$12)/2*$I$8 -> 7356.6176 | ... AC23: =AC20*(1-$I$11/$I$12)/2*$I$8 -> 17058.824

Sheet (EOQ v EPQ helper)
A1: Assumptions
H6: EOQ | I6: EPQ
G7: Optimal Quantity (Q*) | H7: =EOQ!I12 -> 16136.914 | I7: =EPQ!I14 -> 78140.457
G8: Reorder Point (R) | H8: =EOQ!I13 -> 43400 | I8: =EPQ!I15 -> 84574.251
G9: Economic order interval (T*) | H9: =EOQ!I14 -> 1.8590915 | I9: =EPQ!I16 -> 9.0023568
G10: S.S. + ExQ | H10: =EOQ!I15 -> 57311.165 | I10: =EPQ!I17 -> 119314.71
G11: Total Cost (TC) | H11: =EOQ!I16 -> 80684.571 | I11: =EPQ!I18 -> 16662.303

Sheet Discount model
A1: Assumptions
H3: Discount assumptions
H4: Order quantity range | I4: 0-50000 | J4: 50000-200000 | K4: 200000-300000 | L4: >300000
H5: MOQ | I5: 0 | J5: 50000 | K5: 200000 | L5: 300000
H6: Discount | I6: 0 | J6: 0.05 | K6: 0.08 | L6: 0.1
H7: Price | I7: 1 | J7: =$I$7*(1-J6) -> 0.95 | K7: =$I$7*(1-K6) -> 0.92 | L7: =$I$7*(1-L6) -> 0.9
H10: Parameters for | I10: Charging Circuitry x2
H11: Demand | I11: =EOQ!L4 -> 5208000
H12: Ordering costs | I12: =EOQ!L9 -> 250
H13: Holding costs | I13: =EOQ!L8 -> 1.75
H16: EOQ | I16: Q* | J16: In Range
H17: ="Q*("&TEXT(L7,"$0.00")&")" -> Q*($0.90) | I17: =POWER(2*$I$11*$I$12/(1-L6)/$I$13,0.5) -> 40661.202 | J17: =IF(AND(I17>=L5,I17<2^1023*(2-2^-52)),"Feasible", "Unfeasible") -> Unfeasible
H18: ="Q*("&TEXT(K7,"$0.00")&")" -> Q*($0.92) | I18: =POWER(2*$I$11*$I$12/(1-K6)/$I$13,0.5) -> 40216.804 | J18: =IF(AND(I18>=K5,I18<L5),"Feasible", "Unfeasible") -> Unfeasible
H19: ="Q*("&TEXT(J7,"$0.00")&")" -> Q*($0.95) | I19: =POWER(2*$I$11*$I$12/(1-J6)/$I$13,0.5) -> 39576.708 | J19: =IF(AND(I19>=J5,I19<K5),"Feasible", "Unfeasible") -> Unfeasible
